Workbook

Sheet TOC0
A1: Real Statistics Using Excel - Examples Workbook Regression 1
A2: Charles Zaiontz, 29 October 2018
A4: Copyright © 2013 - 2018 Charles Zaiontz
A6: Concise Table of Contents
A8: Linear Regression
A9: Multiple Regression
A10: Tables

Sheet TOC
A1: Real Statistics Using Excel - Examples Workbook Regression 1
A2: Charles Zaiontz, 29 October 2018
A4: Copyright © 2013 - 2018 Charles Zaiontz
A6: Table of Contents
A8: Linear Regression
A10: Method of least squares
B11: Regression line (Example 1)
A13: Regression analysis
B14: Using regression line for prediction (Example 1)
B15: Significance vs effect size (re correlation coefficient)
A17: Hypothesis testing whether the regression line is a good fit for the data
B18: Testing fit of regression line (Example 1)
A20: Hypothesis testing of the significance of the slope of the regression line
B21: Testing slope of regression line (Example 1)
B22: LINEST function (Figure 2)
B23: Regression data analysis tool (Figures 3 and 4)
B24: Comparing the slopes of two independent samples (Example 1 of Detail)
A26: Confidence and prediction intervals for forecasted values
B27: Confidence/prediction Intervals (Example 1)
B28: Testing intercept of regression line (Example 2)
B29: Plot
A31: Exponential regression
B32: Exponential Regression - linear regression (Example 1)
B33: LOGEST and GROWTH functions (Figure 4)
B34: Nonlinear regression via Solver, before (Example 1)
B35: Nonlinear regression via Solver, after (Example 1)
B36: Nonlinear regression via Newton's method (Example 1)
B37: Data analysis tool (Example 1)
A39: Power regression
B40: Log-log Regression (Example 1)
A42: Linear regression models for comparing means
B43: Regression to Compare Means (Example 1)
B44: Full results from data analysis tool for Example 1
B45: Regression to Compare Means (Example 2)
B46: Full results from data analysis tool for Example 2
A48: Total least squares regression
B49: Total least squares regression (Example 1)
B50: Comparison with ordinary linear regression
A52: Deming regression
B53: Deming regression with known variances (Example 1)
B54: Residuals
B55: Deming regression with unknown variances (Example 2)
B56: Standard error using jackknifing
B57: Hypothesis testing
B58: Prediction interval
B59: Prediction interval function
A61: Multiple Regression
A63: Method of least squares
B64: Method of least squares (Example 1)
B65: Method of least squares using covariance matrix (Example 2)
B66: Method of least squares using hat matrix (Example 3)
B67: Method of least squares using Real Statistics functions (Example 3)
A69: Multiple regression analysis
B70: Sample size requirements for multiple regression (Figure 1)
B71: TREND and LINEST function (Example 1)
B72: Data for Example 1 is normal via QQ plot (extra worksheet)
B73: Regression data analysis tool (Example 2)
B74: Real Statistics regression data analysis tool (Example 2)
B75: Formulas for regression analysis (for Figure 5 and 6)
B76: Real Statistics functions (for Figure 5)
B77: Alternative approach to multiple regression (Example 1 of Detail)
B78: Coding categorical data (Example 4)
A80: Confidence and prediction intervals
B81: Confidence and prediction intervals (Example 1)
A83: Shapely-Owen Decomposition
B84: Shapely-Owen (Example 1)
A86: Seasonal Forecasts
B87: Seasonality (Example 5)
A89: Polynomial regression
B90: Polynomial regression (Example 1)
B91: Full data analysis for quadratic model (Example 1)
B92: Full data analysis for linear model (Example 1)
B93: Real Statistics data analysis (Example 2)
B94: Real Statistics data analysis with optimization (Example 3)
B95: Real Statistics functions
B96: Using Extract Columns data analysis tool
A98: Multiple regression with log transformations
B99: Log-level transformation (Example 1)
B100: Log-log transformation (Example 2)
A102: Interaction
B103: Regression with interaction (Example 1)
A105: ANOVA using regression
B106: One factor ANOVA via Regression model (Example 1)
B107: One factor ANOVA via Regression model (Example 1 alternative coding)
B108: Group means and group effect sizes (Figure 5)
B109: Two factor ANOVA via Regression model (Example 2)
A111: Unbalanced factorial ANOVA
B112: Unbalanced ANOVA via Regression model (Example 1)
B113: Unbalanced ANOVA via Regression model using Real Statistics analysis tool (Example 1)
A115: Three factor ANOVA using regression
B116: Balanced model, including data format conversion (Example 1)
B117: Unbalanced model (Example 2)
A119: Unbalanced repeated measures ANOVA using regression
B120: Regression model
B121: Real Statistics data analysis, input in Excel format
B122: Real Statistics data analysis, input in standard format
A124: Other measures of effect size for ANOVA
B125: Omega square effect size for 1 factor ANOVA (Example 3 of Basic Concepts for ANOVA)
B126: Omega square effect size for 2 factor ANOVA (Example 2 of ANOVA using Regression)
A128: Residuals
...

Sheet Reg 1
A1: Regression
D2: cov(x,y) | E2: =COVAR(A4:A18,B4:B18) -> -90.946667 | G2: =COVAR(A4:A18,B4:B18) | N2: Prediction using y = a + b * x
A3: Cig (x) | B3: Life Exp (y) | D3: varp(x) | E3: =VARP(A4:A18) -> 144.77333 | G3: =VARP(A4:A18) | I3: Data | K3: Prediction
A4: 5 | B4: 80 | D4: slope b | E4: =E2/E3 -> -0.62820041 | G4: =E2/E3 | I4: Cig (x) | J4: Life Exp (y) | K4: Life Exp (ŷ) | L4: Error (e) | N4: x | O4: ŷ
A5: 23 | B5: 78 | D5: intercept a | E5: =AVERAGE(B4:B18)-E4*AVERAGE(A4:A18) -> 85.720421 | G5: =AVERAGE(B4:B18)-E4*AVERAGE(A4:A18) | I5: 5 | J5: 80 | K5: =I5*$E$4+$E$5 -> 82.579419 | L5: =J5-K5 -> -2.5794192 | N5: 4 | O5: =N5*$E$4+$E$5 -> 83.20762
A6: 25 | B6: 60 | I6: 23 | J6: 78 | K6: =I6*$E$4+$E$5 -> 71.271812 | L6: =J6-K6 -> 6.7281881 | N6: 24 | O6: =N6*$E$4+$E$5 -> 70.643611
A7: 48 | B7: 53 | I7: 25 | J7: 60 | K7: =I7*$E$4+$E$5 -> 70.015411 | L7: =J7-K7 -> -10.015411 | N7: 44 | O7: =N7*$E$4+$E$5 -> 58.079603
A8: 17 | B8: 85 | I8: 48 | J8: 53 | K8: =I8*$E$4+$E$5 -> 55.566802 | L8: =J8-K8 -> -2.5668017
A9: 8 | B9: 84 | I9: 17 | J9: 85 | K9: =I9*$E$4+$E$5 -> 75.041014 | L9: =J9-K9 -> 9.9589857 | N9: Prediction using FORECAST
A10: 4 | B10: 73 | I10: 8 | J10: 84 | K10: =I10*$E$4+$E$5 -> 80.694818 | L10: =J10-K10 -> 3.305182
A11: 26 | B11: 79 | I11: 4 | J11: 73 | K11: =I11*$E$4+$E$5 -> 83.20762 | L11: =J11-K11 -> -10.20762 | N11: x | O11: ŷ
A12: 11 | B12: 81 | I12: 26 | J12: 79 | K12: =I12*$E$4+$E$5 -> 69.387211 | L12: =J12-K12 -> 9.6127893 | N12: 4 | O12: =FORECAST(N12,$J$5:$J$19,$I$5:$I$19) -> 83.20762
A13: 19 | B13: 75 | I13: 11 | J13: 81 | K13: =I13*$E$4+$E$5 -> 78.810217 | L13: =J13-K13 -> 2.1897833 | N13: 24 | O13: =FORECAST(N13,$J$5:$J$19,$I$5:$I$19) -> 70.643611
A14: 14 | B14: 68 | I14: 19 | J14: 75 | K14: =I14*$E$4+$E$5 -> 73.784613 | L14: =J14-K14 -> 1.2153865 | N14: 44 | O14: =FORECAST(N14,$J$5:$J$19,$I$5:$I$19) -> 58.079603
A15: 35 | B15: 72 | I15: 14 | J15: 68 | K15: =I15*$E$4+$E$5 -> 76.925616 | L15: =J15-K15 -> -8.9256155
A16: 29 | B16: 58 | I16: 35 | J16: 72 | K16: =I16*$E$4+$E$5 -> 63.733407 | L16: =J16-K16 -> 8.266593 | N16: Prediction using TREND
A17: 4 | B17: 92 | I17: 29 | J17: 58 | K17: =I17*$E$4+$E$5 -> 67.502609 | L17: =J17-K17 -> -9.5026094
A18: 23 | B18: 65 | I18: 4 | J18: 92 | K18: =I18*$E$4+$E$5 -> 83.20762 | L18: =J18-K18 -> 8.7923804 | N18: x | O18: ŷ
I19: 23 | J19: 65 | K19: =I19*$E$4+$E$5 -> 71.271812 | L19: =J19-K19 -> -6.2718119 | N19: 4 | O19: {=TREND(J5:J19,I5:I19,N19:N21)} -> 83.20762
N20: 24 | O20: 70.643611
I21: =AVERAGE(I5:I19) -> 19.4 | J21: =AVERAGE(J5:J19) -> 73.533333 | N21: 44 | O21: 58.079603
I22: =STDEV(I5:I19) -> 12.454489 | J22: =STDEV(J5:J19) -> 10.966616

Sheet Reg 2
A1: Regression Testing | J1: Alternative 1 | T1: Alternative 2
A3: Cig (x) | B3: Life Exp (y) | D3: n | E3: =COUNT(A4:A18) -> 15 | J3: Data | L3: Prediction | P3: SS | Q3: df | R3: MS | T3: Data | V3: Prediction | W3: SS | AB3: SS | AC3: df | AD3: MS | AF3: Alternative ways to calculate SS-Res | AJ3: Correlations | AM3: Use of LINEST
A4: 5 | B4: 80 | D4: r | E4: =CORREL(A4:A18,B4:B18) -> -0.71343017 | J4: Cig (x) | K4: Life Exp (y) | L4: Life Exp (ŷ) | M4: Error (e) | O4: T | P4: =DEVSQ(K5:K19) -> 1683.7333 | Q4: =COUNT(K5:K19)-1 -> 14 | R4: =P4/Q4 -> 120.26667 | T4: Cig (x) | U4: Life Exp (y) | V4: Life Exp (ŷ) | W4: T | X4: Reg | Y4: Res | AA4: T | AB4: =W20 -> 1683.7333 | AC4: =U21-1 -> 14 | AD4: =AB4/AC4 -> 120.26667
A5: 23 | B5: 78 | J5: 5 | K5: 80 | L5: =FORECAST(J5,$K$5:$K$19,$J$5:$J$19) -> 82.579419 | M5: =K5-L5 -> -2.5794192 | O5: Reg | P5: =DEVSQ(L5:L19) -> 856.99099 | Q5: 1 | R5: =P5/Q5 -> 856.99099 | T5: 5 | U5: 80 | V5: =FORECAST(T5,$K$5:$K$19,$J$5:$J$19) -> 82.579419 | W5: =(U5-$U$22)^2 -> 41.817778 | X5: =(V5-$U$22)^2 -> 81.831669 | Y5: =(U5-V5)^2 -> 6.6534032 | AA5: Reg | AB5: =X20 -> 856.99099 | AC5: 1 | AD5: =AB5/AC5 -> 856.99099 | AF5: =AB4-AB5 -> 826.74234 | AH5: =AB4-AB5 | AJ5: x and y | AK5: =CORREL(T5:T19,U5:U19) -> -0.71343017 | AM5: Slope (b) | AN5: {=LINEST(B4:B18,A4:A18,TRUE,TRUE)} -> -0.62820041 | AO5: 85.720421 | AP5: Intercept (a)
A6: 25 | B6: 60 | E6: SS | F6: df | G6: MS | J6: 23 | K6: 78 | L6: =FORECAST(J6,$K$5:$K$19,$J$5:$J$19) -> 71.271812 | M6: =K6-L6 -> 6.7281881 | O6: Res | P6: =DEVSQ(M5:M19) -> 826.74234 | Q6: =Q4-1 -> 13 | R6: =P6/Q6 -> 63.595565 | T6: 23 | U6: 78 | V6: =FORECAST(T6,$K$5:$K$19,$J$5:$J$19) -> 71.271812 | W6: =(U6-$U$22)^2 -> 19.951111 | X6: =(V6-$U$22)^2 -> 5.1144793 | Y6: =(U6-V6)^2 -> 45.268515 | AA6: Res | AB6: =Y20 -> 826.74234 | AC6: =AC4-1 -> 13 | AD6: =AB6/AC6 -> 63.595565 | AF6: =SUMXMY2(U5:U19,V5:V19) -> 826.74234 | AH6: =SUMXMY2(U5:U19,V5:V19) | AJ6: x and ŷ | AK6: =CORREL(T5:T19,V5:V19) -> -1 | AM6: S.E. of slope (sb) | AN6: 0.17112895 | AO6: 3.9065908 | AP6: S.E. of intercept (sa)
A7: 48 | B7: 53 | D7: T | E7: =DEVSQ(B4:B18) -> 1683.7333 | F7: =E3-1 -> 14 | G7: =E7/F7 -> 120.26667 | J7: 25 | K7: 60 | L7: =FORECAST(J7,$K$5:$K$19,$J$5:$J$19) -> 70.015411 | M7: =K7-L7 -> -10.015411 | T7: 25 | U7: 60 | V7: =FORECAST(T7,$K$5:$K$19,$J$5:$J$19) -> 70.015411 | W7: =(U7-$U$22)^2 -> 183.15111 | X7: =(V7-$U$22)^2 -> 12.375777 | Y7: =(U7-V7)^2 -> 100.30846 | AJ7: y and ŷ | AK7: =CORREL(U5:U19,V5:V19) -> 0.71343017 | AM7: R Square | AN7: 0.50898261 | AO7: 7.9746827 | AP7: S.E. of estimate (sRes)
A8: 17 | B8: 85 | D8: Reg | E8: =E4^2*E7 -> 856.99099 | F8: 1 | G8: =E8/F8 -> 856.99099 | J8: 48 | K8: 53 | L8: =FORECAST(J8,$K$5:$K$19,$J$5:$J$19) -> 55.566802 | M8: =K8-L8 -> -2.5668017 | T8: 48 | U8: 53 | V8: =FORECAST(T8,$K$5:$K$19,$J$5:$J$19) -> 55.566802 | W8: =(U8-$U$22)^2 -> 421.61778 | X8: =(V8-$U$22)^2 -> 322.79626 | Y8: =(U8-V8)^2 -> 6.5884712 | AM8: F | AN8: 13.475641 | AO8: 13 | AP8: dfRes
A9: 8 | B9: 84 | D9: Res | E9: =E7-E8 -> 826.74234 | F9: =F7-1 -> 13 | G9: =E9/F9 -> 63.595565 | J9: 17 | K9: 85 | L9: =FORECAST(J9,$K$5:$K$19,$J$5:$J$19) -> 75.041014 | M9: =K9-L9 -> 9.9589857 | T9: 17 | U9: 85 | V9: =FORECAST(T9,$K$5:$K$19,$J$5:$J$19) -> 75.041014 | W9: =(U9-$U$22)^2 -> 131.48444 | X9: =(V9-$U$22)^2 -> 2.2731019 | Y9: =(U9-V9)^2 -> 99.181396 | AM9: SSReg | AN9: 856.99099 | AO9: 826.74234 | AP9: SSRes
A10: 4 | B10: 73 | J10: 8 | K10: 84 | L10: =FORECAST(J10,$K$5:$K$19,$J$5:$J$19) -> 80.694818 | M10: =K10-L10 -> 3.305182 | T10: 8 | U10: 84 | V10: =FORECAST(T10,$K$5:$K$19,$J$5:$J$19) -> 80.694818 | W10: =(U10-$U$22)^2 -> 109.55111 | X10: =(V10-$U$22)^2 -> 51.286862 | Y10: =(U10-V10)^2 -> 10.924228
A11: 26 | B11: 79 | D11: F | E11: =G8/G9 -> 13.475641 | G11: =G8/G9 | J11: 4 | K11: 73 | L11: =FORECAST(J11,$K$5:$K$19,$J$5:$J$19) -> 83.20762 | M11: =K11-L11 -> -10.20762 | T11: 4 | U11: 73 | V11: =FORECAST(T11,$K$5:$K$19,$J$5:$J$19) -> 83.20762 | W11: =(U11-$U$22)^2 -> 0.28444444 | X11: =(V11-$U$22)^2 -> 93.591814 | Y11: =(U11-V11)^2 -> 104.1955
A12: 11 | B12: 81 | D12: alpha | E12: 0.05 | J12: 26 | K12: 79 | L12: =FORECAST(J12,$K$5:$K$19,$J$5:$J$19) -> 69.387211 | M12: =K12-L12 -> 9.6127893 | T12: 26 | U12: 79 | V12: =FORECAST(T12,$K$5:$K$19,$J$5:$J$19) -> 69.387211 | W12: =(U12-$U$22)^2 -> 29.884444 | X12: =(V12-$U$22)^2 -> 17.190333 | Y12: =(U12-V12)^2 -> 92.405719
A13: 19 | B13: 75 | D13: F-crit | E13: =FINV(E12,F8,F9) -> 4.6671927 | G13: =FINV(E12,F8,F9) | J13: 11 | K13: 81 | L13: =FORECAST(J13,$K$5:$K$19,$J$5:$J$19) -> 78.810217 | M13: =K13-L13 -> 2.1897833 | T13: 11 | U13: 81 | V13: =FORECAST(T13,$K$5:$K$19,$J$5:$J$19) -> 78.810217 | W13: =(U13-$U$22)^2 -> 55.751111 | X13: =(V13-$U$22)^2 -> 27.845498 | Y13: =(U13-V13)^2 -> 4.7951507
A14: 14 | B14: 68 | D14: p-value | E14: =FDIST(E11,F8,F9) -> 0.002822343 | G14: =FDIST(E11,F8,F9) | J14: 19 | K14: 75 | L14: =FORECAST(J14,$K$5:$K$19,$J$5:$J$19) -> 73.784613 | M14: =K14-L14 -> 1.2153865 | T14: 19 | U14: 75 | V14: =FORECAST(T14,$K$5:$K$19,$J$5:$J$19) -> 73.784613 | W14: =(U14-$U$22)^2 -> 2.1511111 | X14: =(V14-$U$22)^2 -> 0.06314172 | Y14: =(U14-V14)^2 -> 1.4771644
A15: 35 | B15: 72 | D15: sig | E15: =IF(E14<E12,"yes","no") -> yes | G15: =IF(E14<E12,"yes","no") | J15: 14 | K15: 68 | L15: =FORECAST(J15,$K$5:$K$19,$J$5:$J$19) -> 76.925616 | M15: =K15-L15 -> -8.9256155 | T15: 14 | U15: 68 | V15: =FORECAST(T15,$K$5:$K$19,$J$5:$J$19) -> 76.925616 | W15: =(U15-$U$22)^2 -> 30.617778 | X15: =(V15-$U$22)^2 -> 11.507578 | Y15: =(U15-V15)^2 -> 79.666612
A16: 29 | B16: 58 | J16: 35 | K16: 72 | L16: =FORECAST(J16,$K$5:$K$19,$J$5:$J$19) -> 63.733407 | M16: =K16-L16 -> 8.266593 | T16: 35 | U16: 72 | V16: =FORECAST(T16,$K$5:$K$19,$J$5:$J$19) -> 63.733407 | W16: =(U16-$U$22)^2 -> 2.3511111 | X16: =(V16-$U$22)^2 -> 96.038556 | Y16: =(U16-V16)^2 -> 68.33656
A17: 4 | B17: 92 | J17: 29 | K17: 58 | L17: =FORECAST(J17,$K$5:$K$19,$J$5:$J$19) -> 67.502609 | M17: =K17-L17 -> -9.5026094 | T17: 29 | U17: 58 | V17: =FORECAST(T17,$K$5:$K$19,$J$5:$J$19) -> 67.502609 | W17: =(U17-$U$22)^2 -> 241.28444 | X17: =(V17-$U$22)^2 -> 36.369631 | Y17: =(U17-V17)^2 -> 90.299586
A18: 23 | B18: 65 | J18: 4 | K18: 92 | L18: =FORECAST(J18,$K$5:$K$19,$J$5:$J$19) -> 83.20762 | M18: =K18-L18 -> 8.7923804 | T18: 4 | U18: 92 | V18: =FORECAST(T18,$K$5:$K$19,$J$5:$J$19) -> 83.20762 | W18: =(U18-$U$22)^2 -> 341.01778 | X18: =(V18-$U$22)^2 -> 93.591814 | Y18: =(U18-V18)^2 -> 77.305954
J19: 23 | K19: 65 | L19: =FORECAST(J19,$K$5:$K$19,$J$5:$J$19) -> 71.271812 | M19: =K19-L19 -> -6.2718119 | T19: 23 | U19: 65 | V19: =FORECAST(T19,$K$5:$K$19,$J$5:$J$19) -> 71.271812 | W19: =(U19-$U$22)^2 -> 72.817778 | X19: =(V19-$U$22)^2 -> 5.1144793 | Y19: =(U19-V19)^2 -> 39.335624
W20: =SUM(W5:W19) -> 1683.7333 | X20: =SUM(X5:X19) -> 856.99099 | Y20: =SUM(Y5:Y19) -> 826.74234
J21: mean | K21: =AVERAGE(K5:K19) -> 73.533333 | L21: =AVERAGE(L5:L19) -> 73.533333 | M21: =AVERAGE(M5:M19) -> 6.6317322e-15 | T21: n | U21: =COUNT(T5:T19) -> 15
J22: std dev | K22: =STDEV(K5:K19) -> 10.966616 | L22: =STDEV(L5:L19) -> 7.8239148 | M22: =STDEV(M5:M19) -> 7.6845966 | T22: mean y | U22: =AVERAGE(U5:U19) -> 73.533333

Sheet Reg 3
A1: Test the slope of the regression line
A3: Cig (x) | B3: Life Exp (y) | D3: n | E3: =COUNT(A4:A18) -> 15 | G3: =COUNT(A4:A18) | I3: n | J3: =COUNT(A4:A18) -> 15 | L3: =COUNT(A4:A18)
A4: 5 | B4: 80 | D4: r | E4: =CORREL(A4:A18,B4:B18) -> -0.71343017 | G4: =CORREL(A4:A18,B4:B18) | I4: sx | J4: =STDEV(A4:A18) -> 12.454489 | L4: =STDEV(A4:A18)
A5: 23 | B5: 78 | D5: sx | E5: =STDEV(A4:A18) -> 12.454489 | G5: =STDEV(A4:A18) | I5: b | J5: =SLOPE(B4:B18,A4:A18) -> -0.62820041 | L5: =SLOPE(B4:B18,A4:A18)
A6: 25 | B6: 60 | D6: sy | E6: =STDEV(B4:B18) -> 10.966616 | G6: =STDEV(B4:B18) | I6: sy∙x | J6: =STEYX(B4:B18,A4:A18) -> 7.9746827 | L6: =STEYX(B4:B18,A4:A18)
A7: 48 | B7: 53 | D7: b | E7: =E4*E6/E5 -> -0.62820041 | G7: =E4*E6/E5 | I7: sb | J7: =J6/(J4*SQRT(J3-1)) -> 0.17112895 | L7: =J6/(J4*SQRT(J3-1))
A8: 17 | B8: 85 | D8: sy∙x | E8: =E6*SQRT((1-E4^2)*(E3-1)/(E3-2)) -> 7.9746827 | G8: =E6*SQRT((1-E4^2)*(E3-1)/(E3-2)) | I8: t | J8: =J5/J7 -> -3.6709183 | L8: =J5/J7
A9: 8 | B9: 84 | D9: sb | E9: =E8/(E5*SQRT(E3-1)) -> 0.17112895 | G9: =E8/(E5*SQRT(E3-1)) | I9: df | J9: =J3-2 -> 13 | L9: =J3-2
A10: 4 | B10: 73 | D10: t | E10: =E7/E9 -> -3.6709183 | G10: =E7/E9 | I10: p-value | J10: =TDIST(ABS(J8),J9,2) -> 0.002822343 | L10: =TDIST(ABS(J8),J9,2)
A11: 26 | B11: 79 | D11: df | E11: =E3-2 -> 13 | G11: =E3-2 | I11: alpha | J11: 0.05
A12: 11 | B12: 81 | D12: p-value | E12: =TDIST(ABS(E10),E11,2) -> 0.002822343 | G12: =TDIST(ABS(E10),E11,2) | I12: t-crit | J12: =TINV(0.05,J9) -> 2.1603687 | L12: =TINV(0.05,J9)
A13: 19 | B13: 75 | D13: alpha | E13: 0.05 | I13: sig | J13: =IF(J10<J11,"yes","no") -> yes | L13: =IF(J10<J11,"yes","no")
A14: 14 | B14: 68 | D14: t-crit | E14: =TINV(0.05,E11) -> 2.1603687 | G14: =TINV(0.05,E11)
A15: 35 | B15: 72 | D15: sig | E15: =IF(E12<E13,"yes","no") -> yes | G15: =IF(E12<E13,"yes","no") | I15: Confidence interval
A16: 29 | B16: 58
A17: 4 | B17: 92 | D17: Confidence interval | I17: lower | J17: =J5-J12*J7 -> -0.99790203 | L17: =J5-J12*J7
A18: 23 | B18: 65 | I18: upper | J18: =J5+J12*J7 -> -0.25849878 | L18: =J5+J12*J7
D19: lower | E19: =E7-E14*E9 -> -0.99790203 | G19: =E7-E14*E9
D20: upper | E20: =E7+E14*E9 -> -0.25849878 | G20: =E7+E14*E9

Sheet Reg 4
A1: SUMMARY OUTPUT
R2: RESIDUAL OUTPUT | W2: PROBABILITY OUTPUT
A3: Regression Statistics
A4: Multiple R | B4: 0.71343017 | R4: Observation | S4: Predicted Life Exp | T4: Residuals | U4: Standard Residuals | W4: Percentile | X4: Life Exp
A5: R Square | B5: 0.50898261 | R5: 1 | S5: 82.579419 | T5: -2.5794192 | U5: -0.33566097 | W5: 3.3333333 | X5: 53
A6: Adjusted R Square | B6: 0.47121205 | R6: 2 | S6: 71.271812 | T6: 6.7281881 | U6: 0.87554214 | W6: 10 | X6: 58
A7: Standard Error | B7: 7.9746827 | R7: 3 | S7: 70.015411 | T7: -10.015411 | U7: -1.3033099 | W7: 16.666667 | X7: 60
A8: Observations | B8: 15 | R8: 4 | S8: 55.566802 | T8: -2.5668017 | U8: -0.33401906 | W8: 23.333333 | X8: 65
R9: 5 | S9: 75.041014 | T9: 9.9589857 | U9: 1.2959673 | W9: 30 | X9: 68
A10: ANOVA | R10: 6 | S10: 80.694818 | T10: 3.305182 | U10: 0.43010482 | W10: 36.666667 | X10: 72
B11: df | C11: SS | D11: MS | E11: F | F11: Significance F | R11: 7 | S11: 83.20762 | T11: -10.20762 | U11: -1.3283221 | W11: 43.333333 | X11: 73
A12: Regression | B12: 1 | C12: 856.99099 | D12: 856.99099 | E12: 13.475641 | F12: 0.002822343 | R12: 8 | S12: 69.387211 | T12: 9.6127893 | U12: 1.2509166 | W12: 50 | X12: 75
A13: Residual | B13: 13 | C13: 826.74234 | D13: 63.595565 | R13: 9 | S13: 78.810217 | T13: 2.1897833 | U13: 0.28495748 | W13: 56.666667 | X13: 78
A14: Total | B14: 14 | C14: 1683.7333 | R14: 10 | S14: 73.784613 | T14: 1.2153865 | U14: 0.15815879 | W14: 63.333333 | X14: 79
R15: 11 | S15: 76.925616 | T15: -8.9256155 | U15: -1.1614944 | W15: 70 | X15: 80
B16: Coefficients | C16: Standard Error | D16: t Stat | E16: P-value | F16: Lower 95% | G16: Upper 95% | R16: 12 | S16: 63.733407 | T16: 8.266593 | U16: 1.0757355 | W16: 76.666667 | X16: 81
A17: Intercept | B17: 85.720421 | C17: 3.9065908 | D17: 21.942513 | E17: 1.1757939e-11 | F17: 77.280745 | G17: 94.160098 | R17: 13 | S17: 67.502609 | T17: -9.5026094 | U17: -1.2365788 | W17: 83.333333 | X17: 84
A18: Cig (x) | B18: -0.62820041 | C18: 0.17112895 | D18: -3.6709183 | E18: 0.002822343 | F18: -0.99790203 | G18: -0.25849878 | R18: 14 | S18: 83.20762 | T18: 8.7923804 | U18: 1.1441564 | W18: 90 | X18: 85
R19: 15 | S19: 71.271812 | T19: -6.2718119 | U19: -0.81615369 | W19: 96.666667 | X19: 92

Sheet Reg 5
A1: Testing two slopes | M1: Comparison of two slopes
A3: Men | D3: Women | N3: Men | O3: Women
A4: Cig (x) | B4: Life Exp (y) | D4: Cig (x) | E4: Life Exp (y) | M4: n | N4: =COUNT(A5:A19) -> 15 | O4: =COUNT(D5:D20) -> 16 | Q4: =COUNT(x)
A5: 5 | B5: 80 | D5: 22 | E5: 88 | M5: b | N5: =SLOPE(B5:B19,A5:A19) -> -0.62820041 | O5: =SLOPE(E5:E20,D5:D20) -> -0.46785962 | Q5: =SLOPE(y,x)
A6: 23 | B6: 78 | D6: 7 | E6: 95 | M6: sy∙x | N6: =STEYX(B5:B19,A5:A19) -> 7.9746827 | O6: =STEYX(E5:E20,D5:D20) -> 8.3792453 | Q6: =STEYX(y,x)
A7: 25 | B7: 60 | D7: 20 | E7: 86 | M7: sx | N7: =STDEV(A5:A19) -> 12.454489 | O7: =STDEV(D5:D20) -> 13.851594 | Q7: =STDEV(x)
A8: 48 | B8: 53 | D8: 23 | E8: 60 | M8: sb | N8: =N6/(N7*SQRT(N4-1)) -> 0.17112895 | O8: =O6/(O7*SQRT(O4-1)) -> 0.15619226 | Q8: = sy∙x / (sx * SQRT(n-1)) | S8: Using pooled error variance
A9: 17 | B9: 85 | D9: 15 | E9: 82 | S9: sRes2 | T9: =((N4-2)*N6^2+(O4-2)*O6^2)/(N4+O4-4) -> 67.02618 | V9: = ((n1-2)sy.x12+(n2-2)sy.x22)/(n1+n2-4)
A10: 8 | B10: 84 | D10: 34 | E10: 75 | M10: sb1-b2 | N10: =SQRT(N8^2+O8^2) -> 0.23169191 | Q10: = SQRT(sb12+sb22) | S10: sb1-b2 | T10: =SQRT(T9*(1/(N7^2*(N4-1))+1/(O7^2*(O4-1)))) -> 0.2327102 | V10: = sRes*SQRT(1/(sx12(n1-1))+1/(sx22(n2-1)))
A11: 4 | B11: 73 | D11: 4 | E11: 80 | M11: t | N11: =(N5-O5)/N10 -> -0.69204307 | Q11: = (b1-b2)/(sb1-b2) | S11: t | T11: =(N5-O5)/T10 -> -0.68901485 | V11: = (b1-b2)/(sb1-b2)
A12: 26 | B12: 79 | D12: 40 | E12: 68 | M12: df | N12: =N4+O4-4 -> 27 | Q12: = n1+n2-4 | S12: df | T12: =N4+O4-4 -> 27 | V12: = n1+n2-4
A13: 11 | B13: 81 | D13: 8 | E13: 93 | M13: alpha | N13: 0.05 | S13: alpha | T13: 0.05
A14: 19 | B14: 75 | D14: 16 | E14: 77 | M14: p-value | N14: =TDIST(ABS(N11),N12,2) -> 0.49481917 | Q14: = TDIST(|t|,df,2) | S14: p-value | T14: =TDIST(ABS(T11),T12,2) -> 0.49669273 | V14: = TDIST(|t|,df,2)
A15: 14 | B15: 68 | D15: 11 | E15: 72 | M15: t-crit | N15: =TINV(N13,N12) -> 2.0518305 | Q15: = TINV(α,df) | S15: t-crit | T15: =TINV(T13,T12) -> 2.0518305 | V15: = TINV(α,df)
A16: 35 | B16: 72 | D16: 52 | E16: 67 | M16: sig | N16: =IF(ABS(N11)<N15,"no","yes") -> no | Q16: = yes if p-value < α | S16: sig | T16: =IF(ABS(T11)<T15,"no","yes") -> no | V16: = yes if p-value < α
A17: 29 | B17: 58 | D17: 3 | E17: 90
A18: 4 | B18: 92 | D18: 31 | E18: 66
A19: 23 | B19: 65 | D19: 18 | E19: 72 | M19: Using Real Statistics functions
D20: 8 | E20: 78
M21: sb1-b2 | N21: {=SlopesTest(A5:A19,B5:B19,D5:D20,E5:E20,FALSE)} -> #NAME? | S21: sb1-b2 | T21: {=SlopesTest(A5:A19,B5:B19,D5:D20,E5:E20)} -> #NAME?
M22: t | N22: #NAME? | S22: t | T22: #NAME?
M23: df | N23: #NAME? | S23: df | T23: #NAME?
M24: p-value | N24: #NAME? | S24: p-value | T24: #NAME?
M26: Using Real Statistics functions
M27: with and w/o labels
N29: no pool | O29: pooled
M30: {=SlopesTest(A5:A19,B5:B19,D5:D20,E5:E20,FALSE,TRUE)} -> #NAME? | N30: #NAME? | O30: {=SlopesTest(A5:A19,B5:B19,D5:D20,E5:E20)} -> #NAME?
M31: #NAME? | N31: #NAME? | O31: #NAME?
M32: #NAME? | N32: #NAME? | O32: #NAME?
M33: #NAME? | N33: #NAME? | O33: #NAME?

Sheet Reg 6
A1: Confidence and Prediction Intervals
A3: Cig (x) | B3: Life Exp (y) | D3: Confidence interval for the forecasted value
A4: 5 | B4: 80
A5: 23 | B5: 78 | D5: n | E5: =COUNT(A4:A18) -> 15
A6: 25 | B6: 60 | D6: df | E6: =E5-2 -> 13 | G6: = n - 2
A7: 48 | B7: 53 | D7: mean(x) | E7: =AVERAGE(A4:A18) -> 19.4 | G7: = AVERAGE(x)
A8: 17 | B8: 85 | D8: x0 | E8: 20
A9: 8 | B9: 84 | D9: ŷ0 | E9: =FORECAST(E8,B4:B18,A4:A18) -> 73.156413 | G9: = FORECAST(y,x,x0) | I9: Prediction interval | L9: Test for y-intercept
A10: 4 | B10: 73 | D10: sRes | E10: =STEYX(B4:B18,A4:A18) -> 7.9746827 | G10: = STEYX(y,x)
A11: 26 | B11: 79 | D11: SSx | E11: =DEVSQ(A4:A18) -> 2171.6 | G11: = DEVSQ(x) | I11: ŷ0 | J11: =E9 -> 73.156413 | L11: ŷ0 | M11: =FORECAST(0,B4:B18,A4:A18) -> 85.720421
A12: 11 | B12: 81 | D12: se | E12: =E10*SQRT(1/E5+(E8-E7)^2/E11) -> 2.0616127 | G12: = sRes*SQRT(1/n+(x0-x̄)^2/SSx) | I12: se | J12: =E10*SQRT(1+1/E5+(E8-E7)^2/E11) -> 8.2368569 | L12: se | M12: =E10*SQRT(1/E5+E7^2/E11) -> 3.9065908
A13: 19 | B13: 75 | D13: t-crit | E13: =TINV(0.05,E6) -> 2.1603687 | G13: = TINV(0.05,df) | I13: t-crit | J13: =TINV(0.05,E6) -> 2.1603687 | L13: t-crit | M13: =E13 -> 2.1603687
A14: 14 | B14: 68 | D14: lower | E14: =E9-E13*E12 -> 68.70257 | G14: = ŷ0 - t-crit * se | I14: lower | J14: =J11-J13*J12 -> 55.361766 | L14: lower | M14: =M11-M13*M12 -> 77.280745
A15: 35 | B15: 72 | D15: upper | E15: =E9+E13*E12 -> 77.610257 | G15: = ŷ0 + t-crit * se | I15: upper | J15: =J11+J13*J12 -> 90.951061 | L15: upper | M15: =M11+M13*M12 -> 94.160098
A16: 29 | B16: 58
A17: 4 | B17: 92
A18: 23 | B18: 65

Sheet Reg 7
A1: Confidence and Prediction Intervals
A3: Cig (x) | B3: Life Exp (y) | D3: alpha | E3: 0.05 | G3: x | H3: y | I3: lower | J3: upper | K3: conf se | L3: pred | M3: lower | N3: upper | O3: pred se
A4: 5 | B4: 80 | D4: n | E4: =COUNT(A4:A18) -> 15 | G4: 0 | H4: {=TREND(B4:B18,A4:A18,G4:G14)} -> 85.720421 | I4: =H4-$E$8*K4 -> 77.280745 | J4: =H4+$E$8*K4 -> 94.160098 | K4: =$E$7*SQRT(1/$E$4+(G4-$E$5)^2/$E$6) -> 3.9065908 | L4: =H4 -> 85.720421 | M4: =L4-$E$8*O4 -> 66.536029 | N4: =L4+$E$8*O4 -> 104.90481 | O4: =$E$7*SQRT(1+1/$E$4+(G4-$E$5)^2/$E$6) -> 8.8801473
A5: 23 | B5: 78 | D5: mean(x) | E5: =AVERAGE(A4:A18) -> 19.4 | G5: =G4+5 -> 5 | H5: 82.579419 | I5: =H5-$E$8*K5 -> 75.641888 | J5: =H5+$E$8*K5 -> 89.51695 | K5: =$E$7*SQRT(1/$E$4+(G5-$E$5)^2/$E$6) -> 3.2112718 | L5: =H5 -> 82.579419 | M5: =L5-$E$8*O5 -> 64.006802 | N5: =L5+$E$8*O5 -> 101.15204 | O5: =$E$7*SQRT(1+1/$E$4+(G5-$E$5)^2/$E$6) -> 8.5969664
A6: 25 | B6: 60 | D6: devsq(x) | E6: =DEVSQ(A4:A18) -> 2171.6 | G6: =G5+5 -> 10 | H6: 79.438417 | I6: =H6-$E$8*K6 -> 73.793552 | J6: =H6+$E$8*K6 -> 85.083282 | K6: =$E$7*SQRT(1/$E$4+(G6-$E$5)^2/$E$6) -> 2.6129174 | L6: =H6 -> 79.438417 | M6: =L6-$E$8*O6 -> 61.308959 | N6: =L6+$E$8*O6 -> 97.567875 | O6: =$E$7*SQRT(1+1/$E$4+(G6-$E$5)^2/$E$6) -> 8.3918354
A7: 48 | B7: 53 | D7: steyx | E7: =STEYX(B4:B18,A4:A18) -> 7.9746827 | G7: =G6+5 -> 15 | H7: 76.297415 | I7: =H7-$E$8*K7 -> 71.561 | J7: =H7+$E$8*K7 -> 81.03383 | K7: =$E$7*SQRT(1/$E$4+(G7-$E$5)^2/$E$6) -> 2.1924106 | L7: =H7 -> 76.297415 | M7: =L7-$E$8*O7 -> 58.429948 | N7: =L7+$E$8*O7 -> 94.164882 | O7: =$E$7*SQRT(1+1/$E$4+(G7-$E$5)^2/$E$6) -> 8.270564
A8: 17 | B8: 85 | D8: t-crit | E8: =TINV(E3,E4-2) -> 2.1603687 | G8: =G7+5 -> 20 | H8: 73.156413 | I8: =H8-$E$8*K8 -> 68.70257 | J8: =H8+$E$8*K8 -> 77.610257 | K8: =$E$7*SQRT(1/$E$4+(G8-$E$5)^2/$E$6) -> 2.0616127 | L8: =H8 -> 73.156413 | M8: =L8-$E$8*O8 -> 55.361766 | N8: =L8+$E$8*O8 -> 90.951061 | O8: =$E$7*SQRT(1+1/$E$4+(G8-$E$5)^2/$E$6) -> 8.2368569
A9: 8 | B9: 84 | G9: =G8+5 -> 25 | H9: 70.015411 | I9: =H9-$E$8*K9 -> 65.108907 | J9: =H9+$E$8*K9 -> 74.921915 | K9: =$E$7*SQRT(1/$E$4+(G9-$E$5)^2/$E$6) -> 2.2711419 | L9: =H9 -> 70.015411 | M9: =L9-$E$8*O9 -> 52.102105 | N9: =L9+$E$8*O9 -> 87.928717 | O9: =$E$7*SQRT(1+1/$E$4+(G9-$E$5)^2/$E$6) -> 8.2917821
A10: 4 | B10: 73 | G10: =G9+5 -> 30 | H10: 66.874409 | I10: =H10-$E$8*K10 -> 60.946104 | J10: =H10+$E$8*K10 -> 72.802714 | K10: =$E$7*SQRT(1/$E$4+(G10-$E$5)^2/$E$6) -> 2.7441174 | L10: =H10 -> 66.874409 | M10: =L10-$E$8*O10 -> 48.654707 | N10: =L10+$E$8*O10 -> 85.094112 | O10: =$E$7*SQRT(1+1/$E$4+(G10-$E$5)^2/$E$6) -> 8.4336081
A11: 26 | B11: 79 | G11: =G10+5 -> 35 | H11: 63.733407 | I11: =H11-$E$8*K11 -> 56.449878 | J11: =H11+$E$8*K11 -> 71.016936 | K11: =$E$7*SQRT(1/$E$4+(G11-$E$5)^2/$E$6) -> 3.3714286 | L11: =H11 -> 63.733407 | M11: =L11-$E$8*O11 -> 45.028794 | N11: =L11+$E$8*O11 -> 82.43802 | O11: =$E$7*SQRT(1+1/$E$4+(G11-$E$5)^2/$E$6) -> 8.6580653
A12: 11 | B12: 81 | G12: =G11+5 -> 40 | H12: 60.592405 | I12: =H12-$E$8*K12 -> 51.772612 | J12: =H12+$E$8*K12 -> 69.412198 | K12: =$E$7*SQRT(1/$E$4+(G12-$E$5)^2/$E$6) -> 4.0825406 | L12: =H12 -> 60.592405 | M12: =L12-$E$8*O12 -> 41.23778 | N12: =L12+$E$8*O12 -> 79.94703 | O12: =$E$7*SQRT(1+1/$E$4+(G12-$E$5)^2/$E$6) -> 8.9589454
A13: 19 | B13: 75 | G13: =G12+5 -> 45 | H13: 57.451403 | I13: =H13-$E$8*K13 -> 46.99379 | J13: =H13+$E$8*K13 -> 67.909015 | K13: =$E$7*SQRT(1/$E$4+(G13-$E$5)^2/$E$6) -> 4.8406611 | L13: =H13 -> 57.451403 | M13: =L13-$E$8*O13 -> 37.297634 | N13: =L13+$E$8*O13 -> 77.605172 | O13: =$E$7*SQRT(1+1/$E$4+(G13-$E$5)^2/$E$6) -> 9.3288566
A14: 14 | B14: 68 | G14: =G13+5 -> 50 | H14: 54.310401 | I14: =H14-$E$8*K14 -> 42.154392 | J14: =H14+$E$8*K14 -> 66.466409 | K14: =$E$7*SQRT(1/$E$4+(G14-$E$5)^2/$E$6) -> 5.6268213 | L14: =H14 -> 54.310401 | M14: =L14-$E$8*O14 -> 33.225304 | N14: =L14+$E$8*O14 -> 75.395498 | O14: =$E$7*SQRT(1+1/$E$4+(G14-$E$5)^2/$E$6) -> 9.759953
A15: 35 | B15: 72
A16: 29 | B16: 58
A17: 4 | B17: 92
A18: 23 | B18: 65

Sheet Exp Reg
A1: Exponential Regression
A3: Original Data | D3: Log Transformed Data | G3: SUMMARY OUTPUT | O3: Use of LOGEST
A5: x | B5: y | D5: x | E5: ln y | G5: Regression Statistics | O5: Slope: Exp(b) | P5: {=LOGEST(B6:B16,A6:A16,TRUE,TRUE)} -> 1.0162211 | Q5: 14.051352 | R5: Intercept: Exp(a)
A6: 45 | B6: 33 | D6: =A6 -> 45 | E6: =LN(B6) -> 3.4965076 | G6: Multiple R | H6: 0.93894243 | O6: S.E. of slope | P6: 0.0019655063 | Q6: 0.12108366 | R6: S.E. of intercept (sa)
A7: 99 | B7: 72 | D7: =A7 -> 99 | E7: =LN(B7) -> 4.2766661 | G7: R Square | H7: 0.88161289 | O7: R-Squared | P7: 0.88161289 | Q7: 0.1866582 | R7: S.E. of estimate (sRes)
A8: 31 | B8: 19 | D8: =A8 -> 31 | E8: =LN(B8) -> 2.944439 | G8: Adjusted R Square | H8: 0.86845877 | O8: F | P8: 67.021793 | Q8: 9 | R8: dfRes
A9: 57 | B9: 27 | D9: =A9 -> 57 | E9: =LN(B9) -> 3.2958369 | G9: Standard Error | H9: 0.1866582 | O9: SSReg | P9: 2.3351253 | Q9: 0.31357155 | R9: SSRes
A10: 37 | B10: 23 | D10: =A10 -> 37 | E10: =LN(B10) -> 3.1354942 | G10: Observations | H10: 11
A11: 85 | B11: 62 | D11: =A11 -> 85 | E11: =LN(B11) -> 4.1271344
A12: 21 | B12: 24 | D12: =A12 -> 21 | E12: =LN(B12) -> 3.1780538 | G12: ANOVA | O12: Use of GROWTH
A13: 64 | B13: 32 | D13: =A13 -> 64 | E13: =LN(B13) -> 3.4657359 | H13: df | I13: SS | J13: MS | K13: F | L13: Significance F
A14: 17 | B14: 18 | D14: =A14 -> 17 | E14: =LN(B14) -> 2.8903718 | G14: Regression | H14: 1 | I14: 2.3351253 | J14: 2.3351253 | K14: 67.021793 | L14: 1.8400739e-05 | O14: x | P14: y
A15: 41 | B15: 36 | D15: =A15 -> 41 | E15: =LN(B15) -> 3.5835189 | G15: Residual | H15: 9 | I15: 0.31357155 | J15: 0.034841284 | O15: 25 | P15: {=GROWTH(B6:B16,A6:A16,O15:O16)} -> 21.009886
A16: 103 | B16: 76 | D16: =A16 -> 103 | E16: =LN(B16) -> 4.3307333 | G16: Total | H16: 10 | I16: 2.6486968 | O16: 35 | P16: 24.67777
H18: Coefficients | I18: Standard Error | J18: t Stat | K18: P-value | L18: Lower 95% | M18: Upper 95% | O18: Use of slope and intercept for prediction
A19: r | B19: =CORREL(E6:E16,D6:D16) -> 0.93894243 | G19: Intercept | H19: 2.6427186 | I19: 0.12108366 | J19: 21.825559 | K19: 4.1968546e-09 | L19: 2.3688083 | M19: 2.9166289
G20: x | H20: 0.016090979 | I20: 0.0019655063 | J20: 8.1866839 | K20: 1.8400739e-05 | L20: 0.011644695 | M20: 0.020537263 | O20: x | P20: y
O21: 25 | P21: =Q5*P5^O21 -> 21.009886
G22: ea | H22: =EXP(H19) -> 14.051352 | J22: x | K22: 26 | O22: 35 | P22: =Q5*P5^O22 -> 24.67777
G23: eb | H23: =EXP(H20) -> 1.0162211 | J23: y | K23: =H22*H23^K22 -> 21.35069
O24: Use of TREND
O26: x | P26: y
O27: 25 | P27: {=EXP(TREND(LN(B6:B16),A6:A16,O15:O16))} -> 21.009886
O28: 35 | P28: 24.67777

Sheet Exp Reg1
A1: Exponential Regression
A3: x | B3: y | C3: pred y | D3: residual | E3: resid-sq
A4: 45 | B4: 33 | C4: =$B$16*EXP($B$17*A4) -> 28.985991 | D4: =B4-C4 -> 4.0140089 | E4: =D4^2 -> 16.112268
A5: 99 | B5: 72 | C5: =$B$16*EXP($B$17*A5) -> 69.111802 | D5: =B5-C5 -> 2.8881982 | E5: =D5^2 -> 8.341689
A6: 31 | B6: 19 | C6: =$B$16*EXP($B$17*A6) -> 23.13945 | D6: =B6-C6 -> -4.1394497 | E6: =D6^2 -> 17.135044
A7: 57 | B7: 27 | C7: =$B$16*EXP($B$17*A7) -> 35.159835 | D7: =B7-C7 -> -8.1598355 | E7: =D7^2 -> 66.582915
A8: 37 | B8: 23 | C8: =$B$16*EXP($B$17*A8) -> 25.484867 | D8: =B8-C8 -> -2.4848667 | E8: =D8^2 -> 6.1745627
A9: 85 | B9: 62 | C9: =$B$16*EXP($B$17*A9) -> 55.171792 | D9: =B9-C9 -> 6.8282083 | E9: =D9^2 -> 46.624428
A10: 21 | B10: 24 | C10: =$B$16*EXP($B$17*A10) -> 19.700207 | D10: =B10-C10 -> 4.2997928 | E10: =D10^2 -> 18.488218
A11: 64 | B11: 32 | C11: =$B$16*EXP($B$17*A11) -> 39.351781 | D11: =B11-C11 -> -7.3517815 | E11: =D11^2 -> 54.048691
A12: 17 | B12: 18 | C12: =$B$16*EXP($B$17*A12) -> 18.472169 | D12: =B12-C12 -> -0.47216928 | E12: =D12^2 -> 0.22294383
A13: 41 | B13: 36 | C13: =$B$16*EXP($B$17*A13) -> 27.179112 | D13: =B13-C13 -> 8.8208882 | E13: =D13^2 -> 77.808068
A14: 103 | B14: 76 | C14: =$B$16*EXP($B$17*A14) -> 73.706385 | D14: =B14-C14 -> 2.2936154 | E14: =D14^2 -> 5.2606718
E15: =SUM(E4:E14) -> 316.7995
A16: α | B16: 14.051352
A17: β | B17: 0.016090979

Sheet Exp Reg2
A1: Exponential Regression
A3: x | B3: y | C3: pred y | D3: residual | E3: resid-sq
A4: 45 | B4: 33 | C4: =$B$16*EXP($B$17*A4) -> 28.83166 | D4: =B4-C4 -> 4.1683403 | E4: =D4^2 -> 17.375061
A5: 99 | B5: 72 | C5: =$B$16*EXP($B$17*A5) -> 71.635683 | D5: =B5-C5 -> 0.36431709 | E5: =D5^2 -> 0.13272694
A6: 31 | B6: 19 | C6: =$B$16*EXP($B$17*A6) -> 22.77167 | D6: =B6-C6 -> -3.7716705 | E6: =D6^2 -> 14.225498
A7: 57 | B7: 27 | C7: =$B$16*EXP($B$17*A7) -> 35.294347 | D7: =B7-C7 -> -8.2943466 | E7: =D7^2 -> 68.796186
A8: 37 | B8: 23 | C8: =$B$16*EXP($B$17*A8) -> 25.1949 | D8: =B8-C8 -> -2.1949002 | E8: =D8^2 -> 4.8175868
A9: 85 | B9: 62 | C9: =$B$16*EXP($B$17*A9) -> 56.57892 | D9: =B9-C9 -> 5.4210801 | E9: =D9^2 -> 29.38811
A10: 21 | B10: 24 | C10: =$B$16*EXP($B$17*A10) -> 19.239715 | D10: =B10-C10 -> 4.7602848 | E10: =D10^2 -> 22.660312
A11: 64 | B11: 32 | C11: =$B$16*EXP($B$17*A11) -> 39.713899 | D11: =B11-C11 -> -7.7138986 | E11: =D11^2 -> 59.504232
A12: 17 | B12: 18 | C12: =$B$16*EXP($B$17*A12) -> 17.985402 | D12: =B12-C12 -> 0.014598485 | E12: =D12^2 -> 0.00021311576
A13: 41 | B13: 36 | C13: =$B$16*EXP($B$17*A13) -> 26.952009 | D13: =B13-C13 -> 9.047991 | E13: =D13^2 -> 81.866141
A14: 103 | B14: 76 | C14: =$B$16*EXP($B$17*A14) -> 76.631602 | D14: =B14-C14 -> -0.63160228 | E14: =D14^2 -> 0.39892144
E15: =SUM(E4:E14) -> 299.16499
A16: α | B16: 13.504749
A17: β | B17: 0.01685406

Sheet Exp Reg3
A1: Exponential Regression
A3: x | B3: y | D3: Exp(bx) | E3: F1 | F3: F2 | G3: J11 | H3: J12 | I3: J22 | K3: pred-y | L3: resid-sq
A4: 45 | B4: 33 | D4: =EXP($B$20*A4) -> 2.0628614 | E4: =(B4-$B$19*D4)*D4 -> 8.2803441 | F4: =E4*A4*$B$19 -> 5235.7512 | G4: =-(D4^2) -> -4.2553972 | H4: =(B4-2*$B$19*D4)*D4*A4 -> -2318.1182 | I4: =H4*$B$19*A4 -> -1465771.2 | K4: =$B$31*EXP($B$32*A4) -> 28.831681 | L4: =(B4-K4)^2 -> 17.374887
A5: 99 | B5: 72 | D5: =EXP($B$20*A5) -> 4.9185163 | E5: =(B5-$B$19*D5)*D5 -> 14.20565 | F5: =E5*A5*$B$19 -> 19761.25 | G5: =-(D5^2) -> -24.191802 | H5: =(B5-2*$B$19*D5)*D5*A5 -> -32246.465 | I5: =H5*$B$19*A5 -> -44857536 | K5: =$B$31*EXP($B$32*A5) -> 71.635797 | L5: =(B5-K5)^2 -> 0.13264377
A6: 31 | B6: 19 | D6: =EXP($B$20*A6) -> 1.6467775 | E6: =(B6-$B$19*D6)*D6 -> -6.8167527 | F6: =E6*A6*$B$19 -> -2969.3222 | G6: =-(D6^2) -> -2.7118761 | H6: =(B6-2*$B$19*D6)*D6*A6 -> -1392.5906 | I6: =H6*$B$19*A6 -> -606601.19 | K6: =$B$31*EXP($B$32*A6) -> 22.771682 | L6: =(B6-K6)^2 -> 14.225584
A7: 57 | B7: 27 | D7: =EXP($B$20*A7) -> 2.5022387 | E7: =(B7-$B$19*D7)*D7 -> -20.417856 | F7: =E7*A7*$B$19 -> -16353.213 | G7: =-(D7^2) -> -6.2611984 | H7: =(B7-2*$B$19*D7)*D7*A7 -> -6178.5809 | I7: =H7*$B$19*A7 -> -4948592.5 | K7: =$B$31*EXP($B$32*A7) -> 35.294379 | L7: =(B7-K7)^2 -> 68.796723
A8: 37 | B8: 23 | D8: =EXP($B$20*A8) -> 1.813695 | E8: =(B8-$B$19*D8)*D8 -> -4.5067905 | F8: =E8*A8*$B$19 -> -2343.0804 | G8: =-(D8^2) -> -3.2894897 | H8: =(B8-2*$B$19*D8)*D8*A8 -> -1876.957 | I8: =H8*$B$19*A8 -> -975829.95 | K8: =$B$31*EXP($B$32*A8) -> 25.194915 | L8: =(B8-K8)^2 -> 4.8176526
A9: 85 | B9: 62 | D9: =EXP($B$20*A9) -> 3.9264402 | E9: =(B9-$B$19*D9)*D9 -> 26.810551 | F9: =E9*A9*$B$19 -> 32021.581 | G9: =-(D9^2) -> -15.416933 | H9: =(B9-2*$B$19*D9)*D9*A9 -> -16134.546 | I9: =H9*$B$19*A9 -> -19270535 | K9: =$B$31*EXP($B$32*A9) -> 56.578997 | L9: =(B9-K9)^2 -> 29.38727
A10: 21 | B10: 24 | D10: =EXP($B$20*A10) -> 1.4020151 | E10: =(B10-$B$19*D10)*D10 -> 6.0283745 | F10: =E10*A10*$B$19 -> 1778.843 | G10: =-(D10^2) -> -1.9656463 | H10: =(B10-2*$B$19*D10)*D10*A10 -> -453.42388 | I10: =H10*$B$19*A10 -> -133795.59 | K10: =$B$31*EXP($B$32*A10) -> 19.239722 | L10: =(B10-K10)^2 -> 22.66025
A11: 64 | B11: 32 | D11: =EXP($B$20*A11) -> 2.8005691 | E11: =(B11-$B$19*D11)*D11 -> -20.589172 | F11: =E11*A11*$B$19 -> -18515.565 | G11: =-(D11^2) -> -7.8431874 | H11: =(B11-2*$B$19*D11)*D11*A11 -> -8370.9796 | I11: =H11*$B$19*A11 -> -7527909 | K11: =$B$31*EXP($B$32*A11) -> 39.71394 | L11: =(B11-K11)^2 -> 59.504863
A12: 17 | B12: 18 | D12: =EXP($B$20*A12) -> 1.3146187 | E12: =(B12-$B$19*D12)*D12 -> -0.62072255 | F12: =E12*A12*$B$19 -> -148.27384 | G12: =-(D12^2) -> -1.7282223 | H12: =(B12-2*$B$19*D12)*D12*A12 -> -423.37788 | I12: =H12*$B$19*A12 -> -101133.54 | K12: =$B$31*EXP($B$32*A12) -> 17.985406 | L12: =(B12-K12)^2 -> 0.00021297252
A13: 41 | B13: 36 | D13: =EXP($B$20*A13) -> 1.9342703 | E13: =(B13-$B$19*D13)*D13 -> 17.061982 | F13: =E13*A13*$B$19 -> 9829.5002 | G13: =-(D13^2) -> -3.7414015 | H13: =(B13-2*$B$19*D13)*D13*A13 -> -1455.9004 | I13: =H13*$B$19*A13 -> -838752.12 | K13: =$B$31*EXP($B$32*A13) -> 26.952027 | L13: =(B13-K13)^2 -> 81.86582
A14: 103 | B14: 76 | D14: =EXP($B$20*A14) -> 5.2455014 | E14: =(B14-$B$19*D14)*D14 -> 12.031163 | F14: =E14*A14*$B$19 -> 17412.572 | G14: =-(D14^2) -> -27.515285 | H14: =(B14-2*$B$19*D14)*D14*A14 -> -38583.365 | I14: =H14*$B$19*A14 -> -55841289 | K14: =$B$31*EXP($B$32*A14) -> 76.631729 | L14: =(B14-K14)^2 -> 0.39908198
E15: =SUM(E4:E14) -> 31.466771 | F15: =SUM(F4:F14) -> 45710.044 | G15: =SUM(G4:G14) -> -98.920438 | H15: =SUM(H4:H14) -> -109434.31 | I15: =SUM(I4:I14) -> -1.3656775e+08 | L15: =SUM(L4:L14) -> 299.16499
B18: B | D18: F | F18: J | I18: J-1 | L18: (JTJ)-1 | O18: ANOVA
A19: a | B19: =EXP('Exp Reg'!H19) -> 14.051352 | D19: =SUMPRODUCT(SUMPRODUCT($B$4:$B$14-B19*EXP(B20*$A$4:$A$14),EXP(B20*$A$4:$A$14))) -> 31.466771 | F19: =-SUMPRODUCT(EXP(2*B20*$A$4:$A$14)) -> -98.920438 | G19: =SUMPRODUCT(SUMPRODUCT($B$4:$B$14-2*B19*EXP(B20*$A$4:$A$14),EXP(B20*$A$4:$A$14),$A$4:$A$14)) -> -109434.31 | I19: {=MINVERSE(F19:G20)} -> -0.089057745 | J19: 7.1363648e-05 | L19: {=MINVERSE(MMULT(TRANSPOSE(F19:G20),F19:G20))} -> 0.007931287 | M19: -6.3554901e-06 | P19: df | Q19: SS | R19: MS | S19: F | T19: Significance F
A20: b | B20: ='Exp Reg'!H20 -> 0.016090979 | D20: =B19*SUMPRODUCT(SUMPRODUCT($B$4:$B$14-B19*EXP(B20*$A$4:$A$14),EXP(B20*$A$4:$A$14),$A$4:$A$14)) -> 45710.044 | F20: =G19 -> -109434.31 | G20: =B19*SUMPRODUCT(SUMPRODUCT($B$4:$B$14-2*B19*EXP(B20*$A$4:$A$14),EXP(B20*$A$4:$A$14),$A$4:$A$14^2)) -> -1.3656775e+08 | I20: 7.1363648e-05 | J20: -6.4507408e-08 | L20: -6.3554901e-06 | M20: 5.0927744e-09 | O20: Regression | P20: 1 | Q20: =DEVSQ(K4:K14) -> 4333.0059 | R20: =Q20/P20 -> 4333.0059 | S20: =R20/R21 -> 130.353 | T20: =FDIST(S20,P20,P21) -> 1.1753122e-06
O21: Residual | P21: 9 | Q21: =SUMPRODUCT((B4:B14-B31*EXP(B32*A4:A14))^2) -> 299.16499 | R21: =Q21/P21 -> 33.240554
A22: a | B22: {=B19:B20-MMULT(I19:J20,D19:D20)} -> 13.591676 | D22: =SUMPRODUCT(SUMPRODUCT($B$4:$B$14-B22*EXP(B23*$A$4:$A$14),EXP(B23*$A$4:$A$14))) -> -2.2474664 | F22: =-SUMPRODUCT(EXP(2*B23*$A$4:$A$14)) -> -110.93721 | G22: =SUMPRODUCT(SUMPRODUCT($B$4:$B$14-2*B22*EXP(B23*$A$4:$A$14),EXP(B23*$A$4:$A$14),$A$4:$A$14)) -> -123761.05 | I22: {=MINVERSE(F22:G23)} -> -0.10659293 | J22: 8.7467926e-05 | L22: {=MINVERSE(MMULT(TRANSPOSE(F22:G23),F22:G23))} -> 0.01136206 | M22: -9.3234691e-06 | O22: Total | P22: =COUNT(A4:A14)-1 -> 10 | Q22: =DEVSQ(B4:B14) -> 4542.5455
A23: b | B23: 0.016794032 | D23: =B22*SUMPRODUCT(SUMPRODUCT($B$4:$B$14-B22*EXP(B23*$A$4:$A$14),EXP(B23*$A$4:$A$14),$A$4:$A$14)) -> -1730.7024 | F23: =G22 -> -123761.05 | G23: =B22*SUMPRODUCT(SUMPRODUCT($B$4:$B$14-2*B22*EXP(B23*$A$4:$A$14),EXP(B23*$A$4:$A$14),$A$4:$A$14^2)) -> -1.5082161e+08 | I23: 8.7467926e-05 | J23: -7.8404698e-08 | L23: -9.3234691e-06 | M23: 7.650644e-09
P24: Coefficients | Q24: Standard Error | R24: t Stat | S24: P-value | T24: Lower 95% | U24: Upper 95%
A25: a | B25: {=B22:B23-MMULT(I22:J23,D22:D23)} -> 13.503493 | D25: =SUMPRODUCT(SUMPRODUCT($B$4:$B$14-B25*EXP(B26*$A$4:$A$14),EXP(B26*$A$4:$A$14))) -> 0.036187446 | F25: =-SUMPRODUCT(EXP(2*B26*$A$4:$A$14)) -> -112.05097 | G25: =SUMPRODUCT(SUMPRODUCT($B$4:$B$14-2*B25*EXP(B26*$A$4:$A$14),EXP(B26*$A$4:$A$14),$A$4:$A$14)) -> -124181.15 | I25: {=MINVERSE(F25:G26)} -> -0.10456456 | J25: 8.6297807e-05 | L25: {=MINVERSE(MMULT(TRANSPOSE(F25:G26),F25:G26))} -> 0.010933756 | M25: -9.0236995e-06 | O25: Intercept | P25: =B31 -> 13.504749 | Q25: =SQRT(L31*R21) -> 0.60304238 | R25: =P25/Q25 -> 22.394361 | S25: =TDIST(ABS(R25),P21,2) -> 3.3420876e-09 | T25: =P25-Q25*TINV(0.05,P21) -> 12.140572 | U25: =P25+Q25*TINV(0.05,P21) -> 14.868925
A26: b | B26: 0.016854918 | D26: =B25*SUMPRODUCT(SUMPRODUCT($B$4:$B$14-B25*EXP(B26*$A$4:$A$14),EXP(B26*$A$4:$A$14),$A$4:$A$14)) -> 29.29688 | F26: =G25 -> -124181.15 | G26: =B25*SUMPRODUCT(SUMPRODUCT($B$4:$B$14-2*B25*EXP(B26*$A$4:$A$14),EXP(B26*$A$4:$A$14),$A$4:$A$14^2)) -> -1.5046671e+08 | I26: 8.6297807e-05 | J26: -7.7868124e-08 | L26: -9.0236995e-06 | M26: 7.4473178e-09 | O26: x | P26: =B32 -> 0.016854076 | Q26: =SQRT(M32*R21) -> 0.00049765376 | R26: =P26/Q26 -> 33.867073 | S26: =TDIST(ABS(R26),P21,2) -> 8.4136531e-11 | T26: =P26-Q26*TINV(0.05,P21) -> 0.015728305 | U26: =P26+Q26*TINV(0.05,P21) -> 0.017979847
A28: a | B28: {=B25:B26-MMULT(I25:J26,D25:D26)} -> 13.504748 | D28: =SUMPRODUCT(SUMPRODUCT($B$4:$B$14-B28*EXP(B29*$A$4:$A$14),EXP(B29*$A$4:$A$14))) -> 7.582459e-06 | F28: =-SUMPRODUCT(EXP(2*B29*$A$4:$A$14)) -> -112.03549 | G28: =SUMPRODUCT(SUMPRODUCT($B$4:$B$14-2*B28*EXP(B29*$A$4:$A$14),EXP(B29*$A$4:$A$14),$A$4:$A$14)) -> -124176.07 | I28: {=MINVERSE(F28:G29)} -> -0.10459563 | J28: 8.631633e-05 | L28: {=MINVERSE(MMULT(TRANSPOSE(F28:G29),F28:G29))} -> 0.010940253 | M28: -9.0283175e-06
A29: b | B29: 0.016854076 | D29: =B28*SUMPRODUCT(SUMPRODUCT($B$4:$B$14-B28*EXP(B29*$A$4:$A$14),EXP(B29*$A$4:$A$14),$A$4:$A$14)) -> 0.0058190187 | F29: =G28 -> -124176.07 | G29: =B28*SUMPRODUCT(SUMPRODUCT($B$4:$B$14-2*B28*EXP(B29*$A$4:$A$14),EXP(B29*$A$4:$A$14),$A$4:$A$14^2)) -> -1.5047297e+08 | I29: 8.631633e-05 | J29: -7.7877262e-08 | L29: -9.0283175e-06 | M29: 7.4505148e-09
A31: a | B31: {=B28:B29-MMULT(I28:J29,D28:D29)} -> 13.504749 | D31: =SUMPRODUCT(SUMPRODUCT($B$4:$B$14-B31*EXP(B32*$A$4:$A$14),EXP(B32*$A$4:$A$14))) -> 2.8288483e-13 | F31: =-SUMPRODUCT(EXP(2*B32*$A$4:$A$14)) -> -112.03549 | G31: =SUMPRODUCT(SUMPRODUCT($B$4:$B$14-2*B31*EXP(B32*$A$4:$A$14),EXP(B32*$A$4:$A$14),$A$4:$A$14)) -> -124176.07 | I31: {=MINVERSE(F31:G32)} -> -0.10459564 | J31: 8.6316334e-05 | L31: {=MINVERSE(MMULT(TRANSPOSE(F31:G32),F31:G32))} -> 0.010940254 | M31: -9.0283184e-06
A32: b | B32: 0.016854076 | D32: =B31*SUMPRODUCT(SUMPRODUCT($B$4:$B$14-B31*EXP(B32*$A$4:$A$14),EXP(B32*$A$4:$A$14),$A$4:$A$14)) -> 1.4969294e-10 | F32: =G31 -> -124176.07 | G32: =B31*SUMPRODUCT(SUMPRODUCT($B$4:$B$14-2*B31*EXP(B32*$A$4:$A$14),EXP(B32*$A$4:$A$14),$A$4:$A$14^2)) -> -1.5047297e+08 | I32: 8.6316334e-05 | J32: -7.7877263e-08 | L32: -9.0283184e-06 | M32: 7.4505154e-09

Sheet Exp Reg4
A1: Exponential Regression
A3: x | B3: y | C3: pred y | D3: residual | E3: resid-sq | H3: ANOVA
A4: 45 | B4: 33 | C4: {=ExpPred(A4:A14,A4:A14,B4:B14)} -> #NAME? | D4: =B4-C4 -> #NAME? | E4: =D4^2 -> #NAME? | I4: df | J4: SS | K4: MS | L4: F | M4: Sig F
A5: 99 | B5: 72 | C5: #NAME? | D5: =B5-C5 -> #NAME? | E5: =D5^2 -> #NAME? | H5: Regression | I5: 1 | J5: =DEVSQ(C4:C14) -> #NAME? | K5: =J5/I5 -> #NAME? | L5: =K5/K6 -> #NAME? | M5: =FDIST(L5,I5,I6) -> #NAME?
A6: 31 | B6: 19 | C6: #NAME? | D6: =B6-C6 -> #NAME? | E6: =D6^2 -> #NAME? | H6: Residual | I6: 9 | J6: =E15 -> #NAME? | K6: =J6/I6 -> #NAME?
A7: 57 | B7: 27 | C7: #NAME? | D7: =B7-C7 -> #NAME? | E7: =D7^2 -> #NAME? | H7: Total | I7: =COUNT(A4:A14)-1 -> 10 | J7: =DEVSQ(B4:B14) -> 4542.5455
A8: 37 | B8: 23 | C8: #NAME? | D8: =B8-C8 -> #NAME? | E8: =D8^2 -> #NAME?
A9: 85 | B9: 62 | C9: #NAME? | D9: =B9-C9 -> #NAME? | E9: =D9^2 -> #NAME? | I9: Coeff | J9: Std Error | K9: t Stat | L9: P-value | M9: Lower 95% | N9: Upper 95%
A10: 21 | B10: 24 | C10: #NAME? | D10: =B10-C10 -> #NAME? | E10: =D10^2 -> #NAME? | H10: Intercept | I10: {=ExpCoeff(A4:A14,B4:B14)} -> #NAME? | J10: #NAME? | K10: =I10/J10 -> #NAME? | L10: =TDIST(ABS(K10),I6,2) -> #NAME? | M10: =I10-J10*TINV(0.05,I6) -> #NAME? | N10: =I10+J10*TINV(0.05,I6) -> #NAME?
A11: 64 | B11: 32 | C11: #NAME? | D11: =B11-C11 -> #NAME? | E11: =D11^2 -> #NAME? | H11: x | I11: #NAME? | J11: #NAME? | K11: =I11/J11 -> #NAME? | L11: =TDIST(ABS(K11),I6,2) -> #NAME? | M11: =I11-J11*TINV(0.05,I6) -> #NAME? | N11: =I11+J11*TINV(0.05,I6) -> #NAME?
A12: 17 | B12: 18 | C12: #NAME? | D12: =B12-C12 -> #NAME? | E12: =D12^2 -> #NAME?
A13: 41 | B13: 36 | C13: #NAME? | D13: =B13-C13 -> #NAME? | E13: =D13^2 -> #NAME?
A14: 103 | B14: 76 | C14: #NAME? | D14: =B14-C14 -> #NAME? | E14: =D14^2 -> #NAME? | I14: {=ExpCoeff(A4:A14,B4:B14,,TRUE)} -> #NAME? | J14: #NAME? | K14: #NAME? | L14: #NAME? | N14: x | O14: pred y | P14: x | Q14: pred y
E15: =SUM(E4:E14) -> #NAME? | H15: alpha | I15: #NAME? | J15: #NAME? | K15: #NAME? | L15: #NAME? | N15: 45 | O15: {=ExpPred(N15:N16,A4:A14,B4:B14)} -> #NAME? | P15: 45 | Q15: {=ExpPredC(P15:P16,B16,B17)} -> #NAME?
A16: α | B16: {=ExpCoeff(A4:A14,B4:B14)} -> #NAME? | H16: beta | I16: #NAME? | J16: #NAME? | K16: #NAME? | L16: #NAME? | N16: 50 | O16: #NAME? | P16: 50 | Q16: #NAME?
A17: β | B17: #NAME?

Sheet Exp Reg5
A1: Exponential Regression
A3: x | B3: y | D3: Exponential Regression Analysis
A4: 45 | B4: 33
A5: 99 | B5: 72 | D5: ANOVA | H5: Alpha | I5: 0.05
A6: 31 | B6: 19 | E6: df | F6: SS | G6: MS | H6: F | I6: p-value | J6: sig
A7: 57 | B7: 27 | D7: Regression | E7: 1 | F7: =DEVSQ(ExpPredC(A4:A14,E12,E13)) -> #NAME? | G7: =F7/E7 -> #NAME? | H7: =G7/G8 -> #NAME? | I7: =FDIST(H7,E7,E8) -> #NAME? | J7: =IF(I7<I5,"yes","no") -> #NAME?
A8: 37 | B8: 23 | D8: Residual | E8: =E9-E7 -> 9 | F8: {=SUMSQ(ExpPredC(A4:A14,E12,E13)-B4:B14)} -> #NAME? | G8: =F8/E8 -> #NAME?
A9: 85 | B9: 62 | D9: Total | E9: =COUNT(B4:B14)-1 -> 10 | F9: =DEVSQ(B4:B14) -> 4542.5455
A10: 21 | B10: 24
A11: 64 | B11: 32 | E11: coeff | F11: std err | G11: t stat | H11: p-value | I11: lower | J11: upper
A12: 17 | B12: 18 | D12: Intercept | E12: {=ExpCoeff(A4:A14,B4:B14)} -> #NAME? | F12: #NAME? | G12: =E12/F12 -> #NAME? | H12: =TDIST(ABS(G12),$E$8,2) -> #NAME? | I12: =E12-TINV(I$5,$E$8)*F12 -> #NAME? | J12: =E12+TINV(I$5,$E$8)*F12 -> #NAME?
A13: 41 | B13: 36 | D13: =A3 -> x | E13: #NAME? | F13: #NAME? | G13: =E13/F13 -> #NAME? | H13: =TDIST(ABS(G13),$E$8,2) -> #NAME? | I13: =E13-TINV(I$5,$E$8)*F13 -> #NAME? | J13: =E13+TINV(I$5,$E$8)*F13 -> #NAME?
A14: 103 | B14: 76

Sheet Pow Reg
A1: Power Regression
A3: Original Data | D3: Log Transformed Data | G3: SUMMARY OUTPUT | O3: Use of slope and intercept for prediction
A5: x | B5: y | D5: ln x | E5: ln y | G5: Regression Statistics | O5: x | P5: y
A6: 8.1 | B6: 33 | D6: =LN(A6) -> 2.0918641 | E6: =LN(B6) -> 3.4965076 | G6: Multiple R | H6: 0.75380689 | O6: 25 | P6: =$H$22*$H$23^LN(O6) -> 35.421098
A7: 69.9 | B7: 49 | D7: =LN(A7) -> 4.2470656 | E7: =LN(B7) -> 3.8918203 | G7: R Square | H7: 0.56822483 | O7: 35 | P7: =$H$22*$H$23^LN(O7) -> 38.327608
A8: 4.2 | B8: 19 | D8: =LN(A8) -> 1.4350845 | E8: =LN(B8) -> 2.944439 | G8: Adjusted R Square | H8: 0.52024982
A9: 14.1 | B9: 27 | D9: =LN(A9) -> 2.6461748 | E9: =LN(B9) -> 3.2958369 | G9: Standard Error | H9: 0.21085977 | O9: Use of TREND
A10: 5.6 | B10: 23 | D10: =LN(A10) -> 1.7227666 | E10: =LN(B10) -> 3.1354942 | G10: Observations | H10: 11
A11: 52.1 | B11: 51 | D11: =LN(A11) -> 3.9531649 | E11: =LN(B11) -> 3.9318256 | O11: x | P11: y
A12: 44.6 | B12: 34 | D12: =LN(A12) -> 3.7977339 | E12: =LN(B12) -> 3.5263605 | G12: ANOVA | O12: 25 | P12: {=EXP(TREND(LN(B6:B16),LN(A6:A16),LN(O12:O13)))} -> 35.421098
A13: 19.6 | B13: 32 | D13: =LN(A13) -> 2.9755296 | E13: =LN(B13) -> 3.4657359 | H13: df | I13: SS | J13: MS | K13: F | L13: Significance F | O13: 35 | P13: 38.327608
A14: 33 | B14: 28 | D14: =LN(A14) -> 3.4965076 | E14: =LN(B14) -> 3.3322045 | G14: Regression | H14: 1 | I14: 0.52661416 | J14: 0.52661416 | K14: 11.844182 | L14: 0.0073725828
A15: 6.7 | B15: 36 | D15: =LN(A15) -> 1.9021075 | E15: =LN(B15) -> 3.5835189 | G15: Residual | H15: 9 | I15: 0.4001566 | J15: 0.044461844 | O15: 26 | P15: =EXP(TREND(LN(B6:B16),LN(A6:A16),LN(O15))) -> 35.748211
A16: 30.1 | B16: 43 | D16: =LN(A16) -> 3.4045252 | E16: =LN(B16) -> 3.7612001 | G16: Total | H16: 10 | I16: 0.92677076
H18: Coefficients | I18: Standard Error | J18: t Stat | K18: P-value | L18: Lower 95% | M18: Upper 95%
A19: r | B19: =CORREL(E6:E16,D6:D16) -> 0.75380689 | G19: Intercept | H19: 2.8128629 | I19: 0.20614121 | J19: 13.645321 | K19: 2.5593094e-07 | L19: 2.3465391 | M19: 3.2791867
G20: ln x | H20: 0.23438143 | I20: 0.068103695 | J20: 3.4415377 | K20: 0.0073725828 | L20: 0.080320171 | M20: 0.38844269
G22: ea | H22: =EXP(H19) -> 16.657539 | J22: x | K22: 26
G23: eb | H23: =EXP(H20) -> 1.2641266 | J23: y | K23: =H22*H23^LN(K22) -> 35.748211

Sheet Reg T 1
A1: Two Sample t-Test by Regression
A3: New | B3: Old | D3: x | E3: y | G3: SUMMARY OUTPUT | O3: t-Test: Two-Sample Assuming Equal Variances | S3: Comparison
A4: 13 | B4: 12 | D4: 0 | E4: 13
A5: 17 | B5: 8 | D5: 0 | E5: 17 | G5: Regression Statistics | P5: New | Q5: Old | S5: F | T5: =K14 -> 4.7383178
A6: 19 | B6: 6 | D6: 0 | E6: 19 | G6: Multiple R | H6: 0.45649174 | O6: Mean | P6: 15 | Q6: 11.1 | S6: t2 | T6: =P12^2 -> 4.7383178
A7: 11 | B7: 16 | D7: 0 | E7: 11 | G7: R Square | H7: 0.20838471 | O7: Variance | P7: 13.333333 | Q7: 18.766667
A8: 20 | B8: 12 | D8: 0 | E8: 20 | G8: Adjusted R Square | H8: 0.16440608 | O8: Observations | P8: 10 | Q8: 10 | S8: Sig F | T8: =L14 -> 0.043052717
A9: 15 | B9: 14 | D9: 0 | E9: 15 | G9: Standard Error | H9: 4.0062451 | O9: Pooled Variance | P9: 16.05 | S9: P(T<t) two-tail | T9: =P15 -> 0.043052715
A10: 18 | B10: 10 | D10: 0 | E10: 18 | G10: Observations | H10: 20 | O10: Hypothesized Mean Difference | P10: 0
A11: 9 | B11: 18 | D11: 0 | E11: 9 | O11: df | P11: 18 | S11: Multiple R | T11: =H6 -> 0.45649174
A12: 12 | B12: 4 | D12: 0 | E12: 12 | G12: ANOVA | O12: t Stat | P12: 2.1767677 | S12: df | T12: =18 -> 18
A13: 16 | B13: 11 | D13: 0 | E13: 16 | H13: df | I13: SS | J13: MS | K13: F | L13: Significance F | O13: P(T<=t) one-tail | P13: 0.021526358 | S13: √(F/(F+df)) | T13: =SQRT(T5/(T5+T12)) -> 0.45649174
D14: 1 | E14: 12 | G14: Regression | H14: 1 | I14: 76.05 | J14: 76.05 | K14: 4.7383178 | L14: 0.043052717 | O14: t Critical one-tail | P14: 1.7340636
D15: 1 | E15: 8 | G15: Residual | H15: 18 | I15: 288.9 | J15: 16.05 | O15: P(T<=t) two-tail | P15: 0.043052715
D16: 1 | E16: 6 | G16: Total | H16: 19 | I16: 364.95 | O16: t Critical two-tail | P16: 2.100922
D17: 1 | E17: 16
D18: 1 | E18: 12 | H18: Coefficients | I18: Standard Error | J18: t Stat | K18: P-value | L18: Lower 95% | M18: Upper 95%
D19: 1 | E19: 14 | G19: Intercept | H19: 15 | I19: 1.2668859 | J19: 11.840056 | K19: 6.2614482e-10 | L19: 12.338371 | M19: 17.661629
D20: 1 | E20: 10 | G20: x | H20: -3.9 | I20: 1.7916473 | J20: -2.1767677 | K20: 0.043052717 | L20: -7.6641113 | M20: -0.13588873
D21: 1 | E21: 18
D22: 1 | E22: 4
D23: 1 | E23: 11

Sheet Reg T 1A
A1: SUMMARY OUTPUT
A3: Regression Statistics
A4: Multiple R | B4: 0.45649174
A5: R Square | B5: 0.20838471
A6: Adjusted R Square | B6: 0.16440608
A7: Standard Error | B7: 4.0062451
A8: Observations | B8: 20
A10: ANOVA
B11: df | C11: SS | D11: MS | E11: F | F11: Significance F
A12: Regression | B12: 1 | C12: 76.05 | D12: 76.05 | E12: 4.7383178 | F12: 0.043052717
A13: Residual | B13: 18 | C13: 288.9 | D13: 16.05
A14: Total | B14: 19 | C14: 364.95
B16: Coefficients | C16: Standard Error | D16: t Stat | E16: P-value | F16: Lower 95% | G16: Upper 95%
A17: Intercept | B17: 15 | C17: 1.2668859 | D17: 11.840056 | E17: 6.2614482e-10 | F17: 12.338371 | G17: 17.661629
A18: x | B18: -3.9 | C18: 1.7916473 | D18: -2.1767677 | E18: 0.043052717 | F18: -7.6641113 | G18: -0.13588873
A22: RESIDUAL OUTPUT | F22: PROBABILITY OUTPUT
A24: Observation | B24: Predicted y | C24: Residuals | D24: Standard Residuals | F24: Percentile | G24: y
A25: 1 | B25: 15 | C25: -2 | D25: -0.51290039 | F25: 2.5 | G25: 4
A26: 2 | B26: 15 | C26: 2 | D26: 0.51290039 | F26: 7.5 | G26: 6
A27: 3 | B27: 15 | C27: 4 | D27: 1.0258008 | F27: 12.5 | G27: 8
A28: 4 | B28: 15 | C28: -4 | D28: -1.0258008 | F28: 17.5 | G28: 9
A29: 5 | B29: 15 | C29: 5 | D29: 1.282251 | F29: 22.5 | G29: 10
A30: 6 | B30: 15 | C30: 0 | D30: 0 | F30: 27.5 | G30: 11
A31: 7 | B31: 15 | C31: 3 | D31: 0.76935058 | F31: 32.5 | G31: 11
A32: 8 | B32: 15 | C32: -6 | D32: -1.5387012 | F32: 37.5 | G32: 12
A33: 9 | B33: 15 | C33: -3 | D33: -0.76935058 | F33: 42.5 | G33: 12
A34: 10 | B34: 15 | C34: 1 | D34: 0.25645019 | F34: 47.5 | G34: 12
A35: 11 | B35: 11.1 | C35: 0.9 | D35: 0.23080517 | F35: 52.5 | G35: 13
A36: 12 | B36: 11.1 | C36: -3.1 | D36: -0.7949956 | F36: 57.5 | G36: 14
... A44: 20 | B44: 11.1 | C44: -0.1 | D44: -0.025645019 | F44: 97.5 | G44: 20

Sheet Reg T 2
A1: Two Sample t-Test by Regression
A3: New | B3: Old | D3: x | E3: y | G3: SUMMARY OUTPUT | O3: t-Test: Two-Sample Assuming Equal Variances | S3: t-Test: Two-Sample Assuming Unequal Variances
A4: 34 | B4: 12 | D4: 0 | E4: 34
A5: 52 | B5: 8 | D5: 0 | E5: 52 | G5: Regression Statistics | P5: New | Q5: Old | T5: New | U5: Old
A6: 17 | B6: 6 | D6: 0 | E6: 17 | G6: Multiple R | H6: 0.63143952 | O6: Mean | P6: 33.5 | Q6: 11.1 | S6: Mean | T6: 33.5 | U6: 11.1
A7: 45 | B7: 16 | D7: 0 | E7: 45 | G7: R Square | H7: 0.39871587 | O7: Variance | P7: 401.61111 | Q7: 18.766667 | S7: Variance | T7: 401.61111 | U7: 18.766667
A8: 5 | B8: 12 | D8: 0 | E8: 5 | G8: Adjusted R Square | H8: 0.3653112 | O8: Observations | P8: 10 | Q8: 10 | S8: Observations | T8: 10 | U8: 10
A9: 29 | B9: 14 | D9: 0 | E9: 29 | G9: Standard Error | H9: 14.497893 | O9: Pooled Variance | P9: 210.18889 | S9: Hypothesized Mean Difference | T9: 0
A10: 31 | B10: 10 | D10: 0 | E10: 31 | G10: Observations | H10: 20 | O10: Hypothesized Mean Difference | P10: 0 | S10: df | T10: 10
A11: 6 | B11: 18 | D11: 0 | E11: 6 | O11: df | P11: 18 | S11: t Stat | T11: 3.4548416
A12: 52 | B12: 4 | D12: 0 | E12: 52 | G12: ANOVA | O12: t Stat | P12: 3.4548416 | S12: P(T<=t) one-tail | T12: 0.0030879404
A13: 64 | B13: 11 | D13: 0 | E13: 64 | H13: df | I13: SS | J13: MS | K13: F | L13: Significance F | O13: P(T<=t) one-tail | P13: 0.0014131154 | S13: t Critical one-tail | T13: 1.8124611
D14: 1 | E14: 12 | G14: Regression | H14: 1 | I14: 2508.8 | J14: 2508.8 | K14: 11.935931 | L14: 0.0028262308 | O14: t Critical one-tail | P14: 1.7340636 | S14: P(T<=t) two-tail | T14: 0.0061758809
D15: 1 | E15: 8 | G15: Residual | H15: 18 | I15: 3783.4 | J15: 210.18889 | O15: P(T<=t) two-tail | P15: 0.0028262308 | S15: t Critical two-tail | T15: 2.2281388
D16: 1 | E16: 6 | G16: Total | H16: 19 | I16: 6292.2 | O16: t Critical two-tail | P16: 2.100922
D17: 1 | E17: 16
D18: 1 | E18: 12 | H18: Coefficients | I18: Standard Error | J18: t Stat | K18: P-value | L18: Lower 95% | M18: Upper 95%
D19: 1 | E19: 14 | G19: Intercept | H19: 33.5 | I19: 4.5846362 | J19: 7.3070138 | K19: 8.687209e-07 | L19: 23.868037 | M19: 43.131963
D20: 1 | E20: 10 | G20: x | H20: -22.4 | I20: 6.4836547 | J20: -3.4548416 | K20: 0.0028262308 | L20: -36.021653 | M20: -8.778347
D21: 1 | E21: 18
D22: 1 | E22: 4
D23: 1 | E23: 11

Sheet Reg T 2A
A1: SUMMARY OUTPUT
A3: Regression Statistics
A4: Multiple R | B4: 0.63143952
A5: R Square | B5: 0.39871587
A6: Adjusted R Square | B6: 0.3653112
A7: Standard Error | B7: 14.497893
A8: Observations | B8: 20
A10: ANOVA
B11: df | C11: SS | D11: MS | E11: F | F11: Significance F
A12: Regression | B12: 1 | C12: 2508.8 | D12: 2508.8 | E12: 11.935931 | F12: 0.0028262308
A13: Residual | B13: 18 | C13: 3783.4 | D13: 210.18889
A14: Total | B14: 19 | C14: 6292.2
B16: Coefficients | C16: Standard Error | D16: t Stat | E16: P-value | F16: Lower 95% | G16: Upper 95%
A17: Intercept | B17: 33.5 | C17: 4.5846362 | D17: 7.3070138 | E17: 8.687209e-07 | F17: 23.868037 | G17: 43.131963
A18: x | B18: -22.4 | C18: 6.4836547 | D18: -3.4548416 | E18: 0.0028262308 | F18: -36.021653 | G18: -8.778347
A22: RESIDUAL OUTPUT | F22: PROBABILITY OUTPUT
A24: Observation | B24: Predicted y | C24: Residuals | D24: Standard Residuals | F24: Percentile | G24: y
A25: 1 | B25: 33.5 | C25: 0.5 | D25: 0.035432816 | F25: 2.5 | G25: 4
A26: 2 | B26: 33.5 | C26: 18.5 | D26: 1.3110142 | F26: 7.5 | G26: 5
A27: 3 | B27: 33.5 | C27: -16.5 | D27: -1.1692829 | F27: 12.5 | G27: 6
A28: 4 | B28: 33.5 | C28: 11.5 | D28: 0.81495478 | F28: 17.5 | G28: 6
A29: 5 | B29: 33.5 | C29: -28.5 | D29: -2.0196705 | F29: 22.5 | G29: 8
A30: 6 | B30: 33.5 | C30: -4.5 | D30: -0.31889535 | F30: 27.5 | G30: 10
A31: 7 | B31: 33.5 | C31: -2.5 | D31: -0.17716408 | F31: 32.5 | G31: 11
A32: 8 | B32: 33.5 | C32: -27.5 | D32: -1.9488049 | F32: 37.5 | G32: 12
A33: 9 | B33: 33.5 | C33: 18.5 | D33: 1.3110142 | F33: 42.5 | G33: 12
A34: 10 | B34: 33.5 | C34: 30.5 | D34: 2.1614018 | F34: 47.5 | G34: 14
A35: 11 | B35: 11.1 | C35: 0.9 | D35: 0.06377907 | F35: 52.5 | G35: 16
A36: 12 | B36: 11.1 | C36: -3.1 | D36: -0.21968346 | F36: 57.5 | G36: 17
... A44: 20 | B44: 11.1 | C44: -0.1 | D44: -0.0070865633 | F44: 97.5 | G44: 64

Sheet TReg
A1: Total Least Squares Regression
A3: Cig | B3: Life Exp | I3: Regression Analysis | Q3: TLS
A4: 5 | B4: 80 | D4: x̅ | E4: =AVERAGE(A4:A18) -> 19.4 | G4: =FTEXT(E4) -> #NAME?
A5: 23 | B5: 78 | D5: y̅ | E5: =AVERAGE(B4:B18) -> 73.533333 | G5: =FTEXT(E5) -> #NAME? | I5: OVERALL FIT | Q5: Cig | R5: Life Exp
A6: 25 | B6: 60 | D6: n | E6: =COUNT(A4:A18) -> 15 | G6: =FTEXT(E6) -> #NAME? | I6: Multiple R | J6: =SQRT(J7) -> #NAME? | L6: AIC | M6: =J10*LN(K15/J10)+2*(J14+1) -> #NAME? | Q6: 5 | R6: =Q6*$E$11+$E$10 -> 85.586857
A7: 48 | B7: 53 | D7: w | E7: =DEVSQ(B4:B18)-DEVSQ(A4:A18) -> -487.86667 | G7: =FTEXT(E7) -> #NAME? | I7: R Square | J7: =K14/K16 -> #NAME? | L7: AICc | M7: =M6+2*(J14+2)*(J14+3)/(J10-J14-3) -> #NAME? | Q7: 23 | R7: =Q7*$E$11+$E$10 -> 70.519952
A8: 17 | B8: 85 | D8: r | E8: =2*COVAR(A4:A18,B4:B18)*E6 -> -2728.4 | G8: =FTEXT(E8) -> #NAME? | I8: Adjusted R Square | J8: =1-(1-J7)*(J10-1)/(J10-J14-1) -> #NAME? | L8: SBC | M8: =J10*LN(K15/J10)+(J14+1)*LN(J10) -> #NAME? | Q8: 25 | R8: =Q8*$E$11+$E$10 -> 68.845852
A9: 8 | B9: 84 | I9: Standard Error | J9: =SQRT(L15) -> #NAME? | Q9: 48 | R9: =Q9*$E$11+$E$10 -> 49.593695
A10: 4 | B10: 73 | D10: a | E10: =E5-E4*E11 -> 89.772109 | G10: =FTEXT(E10) -> #NAME? | I10: Observations | J10: =COUNT(B4:B18) -> 15 | Q10: 17 | R10: =Q10*$E$11+$E$10 -> 75.542254
A11: 26 | B11: 79 | D11: b | E11: =(E7+SQRT(E7^2+E8^2))/E8 -> -0.83705028 | G11: =FTEXT(E11) -> #NAME? | Q11: 8 | R11: =Q11*$E$11+$E$10 -> 83.075707
A12: 11 | B12: 81 | I12: ANOVA | M12: Alpha | N12: 0.05 | Q12: 4 | R12: =Q12*$E$11+$E$10 -> 86.423908
A13: 19 | B13: 75 | D13: a | E13: {=TRegCoeff0(A4:A18,B4:B18)} -> #NAME? | G13: =FTEXT(E13) -> #NAME? | J13: df | K13: SS | L13: MS | M13: F | N13: p-value | O13: sig | Q13: 26 | R13: =Q13*$E$11+$E$10 -> 68.008801
A14: 14 | B14: 68 | D14: b | E14: #NAME? | I14: Regression | J14: =COUNT(A4) -> 1 | K14: =DEVSQ(MMULT(DESIGN(A4:A18),J19:J20)) -> #NAME? | L14: =K14/J14 -> #NAME? | M14: =L14/L15 -> #NAME? | N14: =FDIST(M14,J14,J15) -> #NAME? | O14: =IF(N14<N12,"yes","no") -> #NAME? | Q14: 11 | R14: =Q14*$E$11+$E$10 -> 80.564556
A15: 35 | B15: 72 | I15: Residual | J15: =J16-J14 -> 13 | K15: =K16-K14 -> #NAME? | L15: =K15/J15 -> #NAME? | Q15: 19 | R15: =Q15*$E$11+$E$10 -> 73.868153
A16: 29 | B16: 58 | D16: a | E16: {=TRegCoeff(A4:A18,B4:B18)} -> #NAME? | G16: =FTEXT(E16) -> #NAME? | I16: Total | J16: =J10-1 -> 14 | K16: =DEVSQ(B4:B18) -> 1683.7333 | Q16: 14 | R16: =Q16*$E$11+$E$10 -> 78.053405
A17: 4 | B17: 92 | D17: b | E17: #NAME? | Q17: 35 | R17: =Q17*$E$11+$E$10 -> 60.475349
A18: 23 | B18: 65 | J18: coeff | K18: std err | L18: t stat | M18: p-value | N18: lower | O18: upper | Q18: 29 | R18: =Q18*$E$11+$E$10 -> 65.497651
I19: Intercept | J19: {=RegCoeff(A4:A18,B4:B18)} -> #NAME? | K19: #NAME? | L19: =J19/K19 -> #NAME? | M19: =TDIST(ABS(L19),$J$15,2) -> #NAME? | N19: =J19-TINV(N$12,$J$15)*K19 -> #NAME? | O19: =J19+TINV(N$12,$J$15)*K19 -> #NAME? | Q19: 4 | R19: =Q19*$E$11+$E$10 -> 86.423908
I20: {=TRANSPOSE(A3)} -> Cig | J20: #NAME? | K20: #NAME? | L20: =J20/K20 -> #NAME? | M20: =TDIST(ABS(L20),$J$15,2) -> #NAME? | N20: =J20-TINV(N$12,$J$15)*K20 -> #NAME? | O20: =J20+TINV(N$12,$J$15)*K20 -> #NAME? | Q20: 23 | R20: =Q20*$E$11+$E$10 -> 70.519952

Sheet Dem 1
A1: Deming Regression - Known Variances
A3: Subject | B3: x | C3: y | E3: Regression coefficients | J3: Residuals Report | U3: Shapiro-Wilk Test | AE3: QQ Plot - opt res
A4: 1 | B4: 5.1 | C4: 5.4
A5: 2 | B5: 5.6 | C5: 5.6 | E5: x̅ | F5: =AVERAGE(B4:B13) -> 5.6 | H5: =FTEXT(F5) -> #NAME? | J5: Subject | K5: x | L5: y | M5: pred y | N5: x-hat | O5: y-hat | P5: raw res | Q5: x-res | R5: y-res | S5: opt res | V5: =S5 -> opt res | AE5: Count | AF5: =COUNT(S6:S15) -> 10 | AG5: =2*AF5 -> 20
A6: 3 | B6: 6.8 | C6: 6.3 | E6: y̅ | F6: =AVERAGE(C4:C13) -> 5.53 | H6: =FTEXT(F6) -> #NAME? | J6: 1 | K6: =B4 -> 5.1 | L6: =C4 -> 5.4 | M6: =F$12+K6*F$13 -> 5.0210001 | N6: =K6+$F$11*$F$13*P6/($F$11*$F$13^2+1) -> 5.3686176 | O6: =L6-P6/($F$11*$F$13^2+1) -> 5.2944528 | P6: =L6-M6 -> 0.37899992 | Q6: =K6-N6 -> -0.26861763 | R6: =L6-O6 -> 0.10554722 | S6: =SIGN(P6)*SQRT(Q6^2+$F$11*R6^2) -> 0.3162372 | U6: W | V6: =SHAPIRO(S6:S15) -> #NAME? | AE6: Mean | AF6: =AVERAGE(S6:S15) -> 1.2878587e-15
A7: 4 | B7: 5.9 | C7: 6.1 | E7: u | F7: =DEVSQ(B4:B13) -> 7.92 | H7: =FTEXT(F7) -> #NAME? | J7: 2 | K7: =B5 -> 5.6 | L7: =C5 -> 5.6 | M7: =F$12+K7*F$13 -> 5.53 | N7: =K7+$F$11*$F$13*P7/($F$11*$F$13^2+1) -> 5.6496128 | O7: =L7-P7/($F$11*$F$13^2+1) -> 5.5805058 | P7: =L7-M7 -> 0.07 | Q7: =K7-N7 -> -0.049612765 | R7: =L7-O7 -> 0.019494213 | S7: =SIGN(P7)*SQRT(Q7^2+$F$11*R7^2) -> 0.058407939 | U7: p-value | V7: =SWTEST(S6:S15) -> #NAME? | AE7: Std Dev | AF7: =STDEV(S6:S15) -> 0.35621511
A8: 5 | B8: 4 | C8: 4.7 | E8: v | F8: =DEVSQ(C4:C13) -> 7.481 | H8: =FTEXT(F8) -> #NAME? | J8: 3 | K8: =B6 -> 6.8 | L8: =C6 -> 6.3 | M8: =F$12+K8*F$13 -> 6.7515998 | N8: =K8+$F$11*$F$13*P8/($F$11*$F$13^2+1) -> 6.4799269 | O8: =L8-P8/($F$11*$F$13^2+1) -> 6.4257655 | P8: =L8-M8 -> -0.4515998 | Q8: =K8-N8 -> 0.32007307 | R8: =L8-O8 -> -0.12576547 | S8: =SIGN(P8)*SQRT(Q8^2+$F$11*R8^2) -> -0.37681448 | U8: alpha | V8: 0.05
A9: 6 | B9: 5.6 | C9: 5.1 | E9: r | F9: =SUMPRODUCT(B4:B13-F5,C4:C13-F6) -> 6.9 | H9: =FTEXT(F9) -> #NAME? | J9: 4 | K9: =B7 -> 5.9 | L9: =C7 -> 6.1 | M9: =F$12+K9*F$13 -> 5.8354 | N9: =K9+$F$11*$F$13*P9/($F$11*$F$13^2+1) -> 6.0875363 | O9: =L9-P9/($F$11*$F$13^2+1) -> 6.0263119 | P9: =L9-M9 -> 0.26460005 | Q9: =K9-N9 -> -0.18753629 | R9: =L9-O9 -> 0.07368814 | S9: =SIGN(P9)*SQRT(Q9^2+$F$11*R9^2) -> 0.22078205 | U9: normal | V9: =IF(V7<V8,"no","yes") -> #NAME? | AE9: Interval | AF9: Data | AG9: Std Norm | AH9: Std Data
A10: 7 | B10: 6.6 | C10: 6.6 | E10: n | F10: =COUNT(B4:B13) -> 10 | H10: =FTEXT(F10) -> #NAME? | J10: 5 | K10: =B8 -> 4 | L10: =C8 -> 4.7 | M10: =F$12+K10*F$13 -> 3.9012003 | N10: =K10+$F$11*$F$13*P10/($F$11*$F$13^2+1) -> 4.5661523 | O10: =L10-P10/($F$11*$F$13^2+1) -> 4.4775432 | P10: =L10-M10 -> 0.79879974 | Q10: =K10-N10 -> -0.56615234 | R10: =L10-O10 -> 0.22245675 | S10: =SIGN(P10)*SQRT(Q10^2+$F$11*R10^2) -> 0.6665178 | AE10: 1 | AF10: {=QSORT(S6:S15)} -> #NAME? | AG10: =NORMSINV(AE10/AG$5) -> -1.6448536 | AH10: =STANDARDIZE(AF10,AF$6,AF$7) -> #NAME?
A11: 8 | B11: 6.7 | C11: 6.8 | E11: λ | F11: =B15/C15 -> 2.5 | H11: =FTEXT(F11) -> #NAME? | J11: 6 | K11: =B9 -> 5.6 | L11: =C9 -> 5.1 | M11: =F$12+K11*F$13 -> 5.53 | N11: =K11+$F$11*$F$13*P11/($F$11*$F$13^2+1) -> 5.2952359 | O11: =L11-P11/($F$11*$F$13^2+1) -> 5.2197502 | P11: =L11-M11 -> -0.43 | Q11: =K11-N11 -> 0.30476413 | R11: =L11-O11 -> -0.11975017 | S11: =SIGN(P11)*SQRT(Q11^2+$F$11*R11^2) -> -0.35879163 | AE11: =AE10+2 -> 3 | AF11: #NAME? | AG11: =NORMSINV(AE11/AG$5) -> -1.0364334 | AH11: =STANDARDIZE(AF11,AF$6,AF$7) -> #NAME?
A12: 9 | B12: 5.2 | C12: 4.6 | E12: b0 | F12: =F6-F5*F13 -> -0.17079908 | H12: =FTEXT(F12) -> #NAME? | J12: 7 | K12: =B10 -> 6.6 | L12: =C10 -> 6.6 | M12: =F$12+K12*F$13 -> 6.5479998 | N12: =K12+$F$11*$F$13*P12/($F$11*$F$13^2+1) -> 6.6368553 | O12: =L12-P12/($F$11*$F$13^2+1) -> 6.5855185 | P12: =L12-M12 -> 0.052000164 | Q12: =K12-N12 -> -0.036855313 | R12: =L12-O12 -> 0.014481461 | S12: =SIGN(P12)*SQRT(Q12^2+$F$11*R12^2) -> 0.043388892 | AE12: =AE11+2 -> 5 | AF12: #NAME? | AG12: =NORMSINV(AE12/AG$5) -> -0.67448975 | AH12: =STANDARDIZE(AF12,AF$6,AF$7) -> #NAME?
A13: 10 | B13: 4.5 | C13: 4.1 | E13: b1 | F13: =(F11*F8-F7+SQRT((F11*F8-F7)^2+4*F11*F9^2))/(2*F11*F9) -> 1.0179998 | H13: =FTEXT(F13) -> #NAME? | J13: 8 | K13: =B11 -> 6.7 | L13: =C11 -> 6.8 | M13: =F$12+K13*F$13 -> 6.6497998 | N13: =K13+$F$11*$F$13*P13/($F$11*$F$13^2+1) -> 6.8064549 | O13: =L13-P13/($F$11*$F$13^2+1) -> 6.7581709 | P13: =L13-M13 -> 0.15020018 | Q13: =K13-N13 -> -0.10645495 | R13: =L13-O13 -> 0.041829062 | S13: =SIGN(P13)*SQRT(Q13^2+$F$11*R13^2) -> 0.1253269 | AE13: =AE12+2 -> 7 | AF13: #NAME? | AG13: =NORMSINV(AE13/AG$5) -> -0.38532047 | AH13: =STANDARDIZE(AF13,AF$6,AF$7) -> #NAME?
J14: 9 | K14: =B12 -> 5.2 | L14: =C12 -> 4.6 | M14: =F$12+K14*F$13 -> 5.1228001 | N14: =K14+$F$11*$F$13*P14/($F$11*$F$13^2+1) -> 4.8294635 | O14: =L14-P14/($F$11*$F$13^2+1) -> 4.7455939 | P14: =L14-M14 -> -0.52280007 | Q14: =K14-N14 -> 0.37053653 | R14: =L14-O14 -> -0.14559394 | S14: =SIGN(P14)*SQRT(Q14^2+$F$11*R14^2) -> -0.43622392 | AE14: =AE13+2 -> 9 | AF14: #NAME? | AG14: =NORMSINV(AE14/AG$5) -> -0.12566135 | AH14: =STANDARDIZE(AF14,AF$6,AF$7) -> #NAME?
A15: var | B15: 0.05 | C15: 0.02 | J15: 10 | K15: =B13 -> 4.5 | L15: =C13 -> 4.1 | M15: =F$12+K15*F$13 -> 4.4102002 | N15: =K15+$F$11*$F$13*P15/($F$11*$F$13^2+1) -> 4.2801444 | O15: =L15-P15/($F$11*$F$13^2+1) -> 4.1863873 | P15: =L15-M15 -> -0.31020018 | Q15: =K15-N15 -> 0.21985555 | R15: =L15-O15 -> -0.086387264 | S15: =SIGN(P15)*SQRT(Q15^2+$F$11*R15^2) -> -0.25883076 | AE15: =AE14+2 -> 11 | AF15: #NAME? | AG15: =NORMSINV(AE15/AG$5) -> 0.12566135 | AH15: =STANDARDIZE(AF15,AF$6,AF$7) -> #NAME?
E16: {=DRegCoeff(B4:B13,C4:C13,F11,TRUE)} -> #NAME? | F16: #NAME? | H16: =FTEXT(F16) -> #NAME? | P16: =AVERAGE(P6:P15) -> 1.4210855e-15 | Q16: =AVERAGE(Q6:Q15) -> -9.7699626e-16 | R16: =AVERAGE(R6:R15) -> 5.3290705e-16 | S16: =AVERAGE(S6:S15) -> 1.2878587e-15 | AE16: =AE15+2 -> 13 | AF16: #NAME? | AG16: =NORMSINV(AE16/AG$5) -> 0.38532047 | AH16: =STANDARDIZE(AF16,AF$6,AF$7) -> #NAME?
E17: #NAME? | F17: #NAME? | AE17: =AE16+2 -> 15 | AF17: #NAME? | AG17: =NORMSINV(AE17/AG$5) -> 0.67448975 | AH17: =STANDARDIZE(AF17,AF$6,AF$7) -> #NAME?
J18: Real Statistics Function | AE18: =AE17+2 -> 17 | AF18: #NAME? | AG18: =NORMSINV(AE18/AG$5) -> 1.0364334 | AH18: =STANDARDIZE(AF18,AF$6,AF$7) -> #NAME?
AE19: =AE18+2 -> 19 | AF19: #NAME? | AG19: =NORMSINV(AE19/AG$5) -> 1.6448536 | AH19: =STANDARDIZE(AF19,AF$6,AF$7) -> #NAME?
J20: Subject | K20: x | L20: y | M20: {=DRegResiduals(K21:K30,L21:L30,F11,TRUE)} -> #NAME? | N20: #NAME? | O20: #NAME? | P20: #NAME? | Q20: #NAME? | R20: #NAME? | S20: #NAME?
J21: 1 | K21: =B4 -> 5.1 | L21: =C4 -> 5.4 | M21: #NAME? | N21: #NAME? | O21: #NAME? | P21: #NAME? | Q21: #NAME? | R21: #NAME? | S21: #NAME?
J22: 2 | K22: =B5 -> 5.6 | L22: =C5 -> 5.6 | M22: #NAME? | N22: #NAME? | O22: #NAME? | P22: #NAME? | Q22: #NAME? | R22: #NAME? | S22: #NAME?
J23: 3 | K23: =B6 -> 6.8 | L23: =C6 -> 6.3 | M23: #NAME? | N23: #NAME? | O23: #NAME? | P23: #NAME? | Q23: #NAME? | R23: #NAME? | S23: #NAME?
J24: 4 | K24: =B7 -> 5.9 | L24: =C7 -> 6.1 | M24: #NAME? | N24: #NAME? | O24: #NAME? | P24: #NAME? | Q24: #NAME? | R24: #NAME? | S24: #NAME?
J25: 5 | K25: =B8 -> 4 | L25: =C8 -> 4.7 | M25: #NAME? | N25: #NAME? | O25: #NAME? | P25: #NAME? | Q25: #NAME? | R25: #NAME? | S25: #NAME?
J26: 6 | K26: =B9 -> 5.6 | L26: =C9 -> 5.1 | M26: #NAME? | N26: #NAME? | O26: #NAME? | P26: #NAME? | Q26: #NAME? | R26: #NAME? | S26: #NAME?
J27: 7 | K27: =B10 -> 6.6 | L27: =C10 -> 6.6 | M27: #NAME? | N27: #NAME? | O27: #NAME? | P27: #NAME? | Q27: #NAME? | R27: #NAME? | S27: #NAME?
J28: 8 | K28: =B11 -> 6.7 | L28: =C11 -> 6.8 | M28: #NAME? | N28: #NAME? | O28: #NAME? | P28: #NAME? | Q28: #NAME? | R28: #NAME? | S28: #NAME?
J29: 9 | K29: =B12 -> 5.2 | L29: =C12 -> 4.6 | M29: #NAME? | N29: #NAME? | O29: #NAME? | P29: #NAME? | Q29: #NAME? | R29: #NAME? | S29: #NAME?
J30: 10 | K30: =B13 -> 4.5 | L30: =C13 -> 4.1 | M30: #NAME? | N30: #NAME? | O30: #NAME? | P30: #NAME? | Q30: #NAME? | R30: #NAME? | S30: #NAME?
P31: =AVERAGE(P21:P30) -> #NAME? | Q31: =AVERAGE(Q21:Q30) -> #NAME? | R31: =AVERAGE(R21:R30) -> #NAME? | S31: =AVERAGE(S21:S30) -> #NAME?

Sheet Dem 2
A1: Deming Regression - Unknown variances
H2: Deviations | O2: Regression coeff
A3: Subject | B3: x1 | C3: x2 | D3: x3 | E3: y1 | F3: y2 | H3: x | I3: y | K3: Subject | L3: x | M3: y | R3: Subject | S3: x | T3: y | V3: {=DRegCoeff(B4:D13,E4:F13,,TRUE)} -> #NAME? | W3: #NAME?
A4: 1 | B4: 96 | C4: 110 | D4: 104 | E4: 80 | F4: 75 | H4: =DEVSQ(B4:D4) -> 98.666667 | I4: =DEVSQ(E4:F4) -> 12.5 | K4: 1 | L4: =AVERAGE(B4:D4) -> 103.33333 | M4: =AVERAGE(E4:F4) -> 77.5 | O4: x̅ | P4: =AVERAGE(L4:L13) -> 243.1 | R4: 1 | S4: {=MEANROW(B4:D13)} -> #NAME? | T4: {=MEANROW(E4:F13)} -> #NAME? | V4: #NAME? | W4: #NAME?
A5: 2 | B5: 124 | C5: 130 | D5: 132 | E5: 89 | F5: 80 | H5: =DEVSQ(B5:D5) -> 34.666667 | I5: =DEVSQ(E5:F5) -> 40.5 | K5: 2 | L5: =AVERAGE(B5:D5) -> 128.66667 | M5: =AVERAGE(E5:F5) -> 84.5 | O5: y̅ | P5: =AVERAGE(M4:M13) -> 172 | R5: 2 | S5: #NAME? | T5: #NAME?
A6: 3 | B6: 146 | C6: 150 | D6: 160 | E6: 93 | F6: 102 | H6: =DEVSQ(B6:D6) -> 104 | I6: =DEVSQ(E6:F6) -> 40.5 | K6: 3 | L6: =AVERAGE(B6:D6) -> 152 | M6: =AVERAGE(E6:F6) -> 97.5 | O6: u | P6: =DEVSQ(L4:L13) -> 94254.233 | R6: 3 | S6: #NAME? | T6: #NAME? | V6: λ | W6: =DRegLambda(B4:D13,E4:F13) -> #NAME?
A7: 4 | B7: 184 | C7: 188 | D7: 192 | E7: 111 | F7: 111 | H7: =DEVSQ(B7:D7) -> 32 | I7: =DEVSQ(E7:F7) -> 0 | K7: 4 | L7: =AVERAGE(B7:D7) -> 188 | M7: =AVERAGE(E7:F7) -> 111 | O7: v | P7: =DEVSQ(M4:M13) -> 56154.5 | R7: 4 | S7: #NAME? | T7: #NAME?
A8: 5 | B8: 224 | C8: 230 | D8: 220 | E8: 163 | F8: 170 | H8: =DEVSQ(B8:D8) -> 50.666667 | I8: =DEVSQ(E8:F8) -> 24.5 | K8: 5 | L8: =AVERAGE(B8:D8) -> 224.66667 | M8: =AVERAGE(E8:F8) -> 166.5 | O8: r | P8: =SUMPRODUCT(L4:L13-P4,M4:M13-P5) -> 72170 | R8: 5 | S8: #NAME? | T8: #NAME?
A9: 6 | B9: 256 | C9: 252 | D9: 246 | E9: 188 | F9: 177 | H9: =DEVSQ(B9:D9) -> 50.666667 | I9: =DEVSQ(E9:F9) -> 60.5 | K9: 6 | L9: =AVERAGE(B9:D9) -> 251.33333 | M9: =AVERAGE(E9:F9) -> 182.5 | O9: n | P9: =COUNT(L4:L13) -> 10 | R9: 6 | S9: #NAME? | T9: #NAME?
A10: 7 | B10: 284 | C10: 284 | D10: 288 | E10: 201 | F10: 196 | H10: =DEVSQ(B10:D10) -> 10.666667 | I10: =DEVSQ(E10:F10) -> 12.5 | K10: 7 | L10: =AVERAGE(B10:D10) -> 285.33333 | M10: =AVERAGE(E10:F10) -> 198.5 | O10: λ | P10: =L15/M15 -> 2.4111675 | R10: 7 | S10: #NAME? | T10: #NAME?
A11: 8 | B11: 332 | C11: 326 | D11: 346 | E11: 232 | F11: 234 | H11: =DEVSQ(B11:D11) -> 210.66667 | I11: =DEVSQ(E11:F11) -> 2 | K11: 8 | L11: =AVERAGE(B11:D11) -> 334.66667 | M11: =AVERAGE(E11:F11) -> 233 | O11: b0 | P11: =P5-P4*P12 -> -15.911683 | R11: 8 | S11: #NAME? | T11: #NAME?
A12: 9 | B12: 352 | C12: 344 | D12: 369 | E12: 269 | F12: 271 | H12: =DEVSQ(B12:D12) -> 326 | I12: =DEVSQ(E12:F12) -> 2 | K12: 9 | L12: =AVERAGE(B12:D12) -> 355 | M12: =AVERAGE(E12:F12) -> 270 | O12: b1 | P12: =(P10*P7-P6+SQRT((P10*P7-P6)^2+4*P10*P8^2))/(2*P10*P8) -> 0.77298101 | R12: 9 | S12: #NAME? | T12: #NAME?
A13: 10 | B13: 412 | C13: 404 | D13: 408 | E13: 300 | F13: 298 | H13: =DEVSQ(B13:D13) -> 32 | I13: =DEVSQ(E13:F13) -> 2 | K13: 10 | L13: =AVERAGE(B13:D13) -> 408 | M13: =AVERAGE(E13:F13) -> 299 | R13: 10 | S13: #NAME? | T13: #NAME?
K15: var | L15: =SUM(H4:H13)/(COUNT(B4:D13)-A13) -> 47.5 | M15: =SUM(I4:I13)/(COUNT(E4:F13)-A13) -> 19.7

Sheet Dem 3
A1: Deming Regression - Standard Error
A3: Subject | B3: x | C3: y | E3: x̄ | F3: y̅ | G3: u | H3: v | I3: r | J3: b0 | K3: b1
A4: 1 | B4: 5.1 | C4: 5.4 | E4: =($A$13*E$14-B4)/($A$13-1) -> 5.6555556 | F4: =($A$13*F$14-C4)/($A$13-1) -> 5.5444444 | G4: =G$14-$A$13*(E$14-B4)^2/($A$13-1) -> 7.6422222 | H4: =H$14-$A$13*(F$14-C4)^2/($A$13-1) -> 7.4622222 | I4: =I$14-$A$13*(E$14-B4)*(F$14-C4)/($A$13-1) -> 6.8277778 | J4: =F4-K4*E4 -> -0.29539655 | K4: =($B$15*H4-G4+SQRT(($B$15*H4-G4)^2+4*$B$15*I4^2))/(2*$B$15*I4) -> 1.0325849
A5: 2 | B5: 5.6 | C5: 5.6 | E5: =($A$13*E$14-B5)/($A$13-1) -> 5.6 | F5: =($A$13*F$14-C5)/($A$13-1) -> 5.5222222 | G5: =G$14-$A$13*(E$14-B5)^2/($A$13-1) -> 7.92 | H5: =H$14-$A$13*(F$14-C5)^2/($A$13-1) -> 7.4755556 | I5: =I$14-$A$13*(E$14-B5)*(F$14-C5)/($A$13-1) -> 6.9 | J5: =F5-K5*E5 -> -0.17538923 | K5: =($B$15*H5-G5+SQRT(($B$15*H5-G5)^2+4*$B$15*I5^2))/(2*$B$15*I5) -> 1.0174306
A6: 3 | B6: 6.8 | C6: 6.3 | E6: =($A$13*E$14-B6)/($A$13-1) -> 5.4666667 | F6: =($A$13*F$14-C6)/($A$13-1) -> 5.4444444 | G6: =G$14-$A$13*(E$14-B6)^2/($A$13-1) -> 6.32 | H6: =H$14-$A$13*(F$14-C6)^2/($A$13-1) -> 6.8222222 | I6: =I$14-$A$13*(E$14-B6)*(F$14-C6)/($A$13-1) -> 5.8733333 | J6: =F6-K6*E6 -> -0.54744202 | K6: =($B$15*H6-G6+SQRT(($B$15*H6-G6)^2+4*$B$15*I6^2))/(2*$B$15*I6) -> 1.0960768
A7: 4 | B7: 5.9 | C7: 6.1 | E7: =($A$13*E$14-B7)/($A$13-1) -> 5.5666667 | F7: =($A$13*F$14-C7)/($A$13-1) -> 5.4666667 | G7: =G$14-$A$13*(E$14-B7)^2/($A$13-1) -> 7.82 | H7: =H$14-$A$13*(F$14-C7)^2/($A$13-1) -> 7.12 | I7: =I$14-$A$13*(E$14-B7)*(F$14-C7)/($A$13-1) -> 6.71 | J7: =F7-K7*E7 -> -0.079873255 | K7: =($B$15*H7-G7+SQRT(($B$15*H7-G7)^2+4*$B$15*I7^2))/(2*$B$15*I7) -> 0.99638442
A8: 5 | B8: 4 | C8: 4.7 | E8: =($A$13*E$14-B8)/($A$13-1) -> 5.7777778 | F8: =($A$13*F$14-C8)/($A$13-1) -> 5.6222222 | G8: =G$14-$A$13*(E$14-B8)^2/($A$13-1) -> 5.0755556 | H8: =H$14-$A$13*(F$14-C8)^2/($A$13-1) -> 6.7155556 | I8: =I$14-$A$13*(E$14-B8)*(F$14-C8)/($A$13-1) -> 5.4244444 | J8: =F8-K8*E8 -> -1.2979027 | K8: =($B$15*H8-G8+SQRT(($B$15*H8-G8)^2+4*$B$15*I8^2))/(2*$B$15*I8) -> 1.1977139
A9: 6 | B9: 5.6 | C9: 5.1 | E9: =($A$13*E$14-B9)/($A$13-1) -> 5.6 | F9: =($A$13*F$14-C9)/($A$13-1) -> 5.5777778 | G9: =G$14-$A$13*(E$14-B9)^2/($A$13-1) -> 7.92 | H9: =H$14-$A$13*(F$14-C9)^2/($A$13-1) -> 7.2755556 | I9: =I$14-$A$13*(E$14-B9)*(F$14-C9)/($A$13-1) -> 6.9 | J9: =F9-K9*E9 -> -0.0034319233 | K9: =($B$15*H9-G9+SQRT(($B$15*H9-G9)^2+4*$B$15*I9^2))/(2*$B$15*I9) -> 0.99664459
A10: 7 | B10: 6.6 | C10: 6.6 | E10: =($A$13*E$14-B10)/($A$13-1) -> 5.4888889 | F10: =($A$13*F$14-C10)/($A$13-1) -> 5.4111111 | G10: =G$14-$A$13*(E$14-B10)^2/($A$13-1) -> 6.8088889 | H10: =H$14-$A$13*(F$14-C10)^2/($A$13-1) -> 6.2088889 | I10: =I$14-$A$13*(E$14-B10)*(F$14-C10)/($A$13-1) -> 5.7111111 | J10: =F10-K10*E10 -> -0.11813617 | K10: =($B$15*H10-G10+SQRT(($B$15*H10-G10)^2+4*$B$15*I10^2))/(2*$B$15*I10) -> 1.0073527
A11: 8 | B11: 6.7 | C11: 6.8 | E11: =($A$13*E$14-B11)/($A$13-1) -> 5.4777778 | F11: =($A$13*F$14-C11)/($A$13-1) -> 5.3888889 | G11: =G$14-$A$13*(E$14-B11)^2/($A$13-1) -> 6.5755556 | H11: =H$14-$A$13*(F$14-C11)^2/($A$13-1) -> 5.6888889 | I11: =I$14-$A$13*(E$14-B11)*(F$14-C11)/($A$13-1) -> 5.3477778 | J11: =F11-K11*E11 -> 0.020224907 | K11: =($B$15*H11-G11+SQRT(($B$15*H11-G11)^2+4*$B$15*I11^2))/(2*$B$15*I11) -> 0.98008065
A12: 9 | B12: 5.2 | C12: 4.6 | E12: =($A$13*E$14-B12)/($A$13-1) -> 5.6444444 | F12: =($A$13*F$14-C12)/($A$13-1) -> 5.6333333 | G12: =G$14-$A$13*(E$14-B12)^2/($A$13-1) -> 7.7422222 | H12: =H$14-$A$13*(F$14-C12)^2/($A$13-1) -> 6.52 | I12: =I$14-$A$13*(E$14-B12)*(F$14-C12)/($A$13-1) -> 6.4866667 | J12: =F12-K12*E12 -> 0.27592972 | K12: =($B$15*H12-G12+SQRT(($B$15*H12-G12)^2+4*$B$15*I12^2))/(2*$B$15*I12) -> 0.94914631
A13: 10 | B13: 4.5 | C13: 4.1 | E13: =($A$13*E$14-B13)/($A$13-1) -> 5.7222222 | F13: =($A$13*F$14-C13)/($A$13-1) -> 5.6888889 | G13: =G$14-$A$13*(E$14-B13)^2/($A$13-1) -> 6.5755556 | H13: =H$14-$A$13*(F$14-C13)^2/($A$13-1) -> 5.2088889 | I13: =I$14-$A$13*(E$14-B13)*(F$14-C13)/($A$13-1) -> 5.1522222 | J13: =F13-K13*E13 -> 0.36486044 | K13: =($B$15*H13-G13+SQRT(($B$15*H13-G13)^2+4*$B$15*I13^2))/(2*$B$15*I13) -> 0.93041274
E14: =AVERAGE(B4:B13) -> 5.6 | F14: =AVERAGE(C4:C13) -> 5.53 | G14: =DEVSQ(B4:B13) -> 7.92 | H14: =DEVSQ(C4:C13) -> 7.481 | I14: =SUMPRODUCT(B4:B13-E14,C4:C13-F14) -> 6.9 | J14: =F14-K14*E14 -> -0.17079908 | K14: =($B$15*H14-G14+SQRT(($B$15*H14-G14)^2+4*$B$15*I14^2))/(2*$B$15*I14) -> 1.0179998
A15: λ | B15: 2.5
I16: var | J16: =DEVSQ(J4:J13)*($A$13-1) -> 17.888413 | K16: =DEVSQ(K4:K13)*($A$13-1) -> 0.48092613
I17: s.e. | J17: =SQRT(J16/$A$13) -> 1.3374757 | K17: =SQRT(K16/$A$13) -> 0.21930028
E19: Coefficient Report
J20: alpha | K20: 0.05
F21: coeff | G21: s.e. | H21: df | I21: t stat | J21: p-value | K21: lower | L21: upper
E22: intercept | F22: =J14 -> -0.17079908 | G22: =J17 -> 1.3374757 | H22: =A13-1 -> 9 | I22: =F22/G22 -> -0.12770256 | J22: =TDIST(ABS(I22),H22,2) -> 0.90119222 | K22: =F22-TINV(K$20,H22)*G22 -> -3.1963794 | L22: =F22+TINV(K$20,H22)*G22 -> 2.8547812 | N22: {=DRegCoeff(B4:B13,C4:C13,B15,TRUE)} -> #NAME? | O22: #NAME? | P22: #NAME?
E23: slope | F23: =K14 -> 1.0179998 | G23: =K17 -> 0.21930028 | H23: =A13-1 -> 9 | I23: =F23/G23 -> 4.6420362 | J23: =TDIST(ABS(I23),H23,2) -> 0.0012157505 | K23: =F23-TINV(K$20,H23)*G23 -> 0.52190814 | L23: =F23+TINV(K$20,H23)*G23 -> 1.5140915 | N23: #NAME? | O23: #NAME? | P23: #NAME?
E25: Deming Regression
J26: alpha | K26: 0.05
F27: coeff | G27: std err | H27: df | I27: t stat | J27: p-value | K27: lower | L27: upper
E28: {=DRegCoeff(B4:B13,C4:C13,2.5,TRUE)} -> #NAME? | F28: #NAME? | G28: #NAME? | H28: =COUNT(C4:C13)-1 -> 9 | I28: =F28/G28 -> #NAME? | J28: =TDIST(ABS(I28),H28,2) -> #NAME? | K28: =F28-TINV(K$26,H28)*G28 -> #NAME? | L28: =F28+TINV(K$26,H28)*G28 -> #NAME?
E29: #NAME? | F29: #NAME? | G29: #NAME? | H29: =H28 -> 9 | I29: =F29/G29 -> #NAME? | J29: =TDIST(ABS(I29),H29,2) -> #NAME? | K29: =F29-TINV(K$26,H29)*G29 -> #NAME? | L29: =F29+TINV(K$26,H29)*G29 -> #NAME?

Sheet Dem 4
A1: Deming Regression - Hypothesis Testing
A3: Subject | B3: x | C3: y | E3: x̅ | F3: y̅ | G3: y̅ - x̅ | I3: Hypothesis Testing | U3: Deming Regression
A4: 1 | B4: 5.1 | C4: 5.4 | E4: {=AVERAGE(IF($A$4:$A$13=$A4,"",B$4:B$13))} -> 5.6555556 | F4: {=AVERAGE(IF($A$4:$A$13=$A4,"",C$4:C$13))} -> 5.5444444 | G4: =F4-E4 -> -0.11111111 | N4: alpha | O4: 0.025 | Z4: alpha | AA4: 0.05
A5: 2 | B5: 5.6 | C5: 5.6 | E5: {=AVERAGE(IF($A$4:$A$13=$A5,"",B$4:B$13))} -> 5.6 | F5: {=AVERAGE(IF($A$4:$A$13=$A5,"",C$4:C$13))} -> 5.5222222 | G5: =F5-E5 -> -0.077777778 | J5: param | K5: s.e. | L5: df | M5: t stat | N5: p-value | O5: lower | P5: upper | V5: coeff | W5: std err | X5: df | Y5: t stat | Z5: p-value | AA5: lower | AB5: upper
A6: 3 | B6: 6.8 | C6: 6.3 | E6: {=AVERAGE(IF($A$4:$A$13=$A6,"",B$4:B$13))} -> 5.4666667 | F6: {=AVERAGE(IF($A$4:$A$13=$A6,"",C$4:C$13))} -> 5.4444444 | G6: =F6-E6 -> -0.022222222 | I6: test 1 | J6: =1-'Dem 3'!K14 -> -0.017999836 | K6: ='Dem 3'!K17 -> 0.21930028 | L6: =A13-1 -> 9 | M6: =J6/K6 -> -0.082078489 | N6: =TDIST(ABS(M6),L6,2) -> 0.93638072 | O6: =J6-TINV(O$4,L6)*K6 -> -0.60682347 | P6: =J6+TINV(O$4,L6)*K6 -> 0.5708238 | R6: {=DRegIdentity(B4:B13,C4:C13,B15,TRUE)} -> #NAME? | S6: #NAME? | U6: {=DRegCoeff(B4:B13,C4:C13,2.5,TRUE)} -> #NAME? | V6: #NAME? | W6: #NAME? | X6: =COUNT(C4:C13)-1 -> 9 | Y6: =V6/W6 -> #NAME? | Z6: =TDIST(ABS(Y6),X6,2) -> #NAME? | AA6: =V6-TINV(AA$4,X6)*W6 -> #NAME? | AB6: =V6+TINV(AA$4,X6)*W6 -> #NAME?
A7: 4 | B7: 5.9 | C7: 6.1 | E7: {=AVERAGE(IF($A$4:$A$13=$A7,"",B$4:B$13))} -> 5.5666667 | F7: {=AVERAGE(IF($A$4:$A$13=$A7,"",C$4:C$13))} -> 5.4666667 | G7: =F7-E7 -> -0.1 | I7: test 2 | J7: =F14-E14 -> -0.07 | K7: =G17 -> 0.13337499 | L7: =A13-1 -> 9 | M7: =J7/K7 -> -0.52483601 | N7: =TDIST(ABS(M7),L7,2) -> 0.6123785 | O7: =J7-TINV(O$4,L7)*K7 -> -0.4281133 | P7: =J7+TINV(O$4,L7)*K7 -> 0.2881133 | R7: #NAME? | S7: #NAME? | U7: #NAME? | V7: #NAME? | W7: #NAME? | X7: =X6 -> 9 | Y7: =V7/W7 -> #NAME? | Z7: =TDIST(ABS(Y7),X7,2) -> #NAME? | AA7: =V7-TINV(AA$4,X7)*W7 -> #NAME? | AB7: =V7+TINV(AA$4,X7)*W7 -> #NAME?
A8: 5 | B8: 4 | C8: 4.7 | E8: {=AVERAGE(IF($A$4:$A$13=$A8,"",B$4:B$13))} -> 5.7777778 | F8: {=AVERAGE(IF($A$4:$A$13=$A8,"",C$4:C$13))} -> 5.6222222 | G8: =F8-E8 -> -0.15555556
A9: 6 | B9: 5.6 | C9: 5.1 | E9: {=AVERAGE(IF($A$4:$A$13=$A9,"",B$4:B$13))} -> 5.6 | F9: {=AVERAGE(IF($A$4:$A$13=$A9,"",C$4:C$13))} -> 5.5777778 | G9: =F9-E9 -> -0.022222222 | U9: Hypothesis Testing
A10: 7 | B10: 6.6 | C10: 6.6 | E10: {=AVERAGE(IF($A$4:$A$13=$A10,"",B$4:B$13))} -> 5.4888889 | F10: {=AVERAGE(IF($A$4:$A$13=$A10,"",C$4:C$13))} -> 5.4111111 | G10: =F10-E10 -> -0.077777778 | R10: {=TRANSPOSE(DRegIdentity(B4:B13,C4:C13,B15,TRUE))} -> #NAME? | S10: #NAME? | Z10: alpha | AA10: 0.025
A11: 8 | B11: 6.7 | C11: 6.8 | E11: {=AVERAGE(IF($A$4:$A$13=$A11,"",B$4:B$13))} -> 5.4777778 | F11: {=AVERAGE(IF($A$4:$A$13=$A11,"",C$4:C$13))} -> 5.3888889 | G11: =F11-E11 -> -0.088888889 | R11: #NAME? | S11: #NAME? | U11: test | V11: param | W11: std err | X11: df | Y11: t stat | Z11: p-value | AA11: lower | AB11: upper
A12: 9 | B12: 5.2 | C12: 4.6 | E12: {=AVERAGE(IF($A$4:$A$13=$A12,"",B$4:B$13))} -> 5.6444444 | F12: {=AVERAGE(IF($A$4:$A$13=$A12,"",C$4:C$13))} -> 5.6333333 | G12: =F12-E12 -> -0.011111111 | U12: slope = 1 | V12: =1-V7 -> #NAME? | W12: =W7 -> #NAME? | X12: =X6 -> 9 | Y12: =V12/W12 -> #NAME? | Z12: =TDIST(ABS(Y12),X12,2) -> #NAME? | AA12: =V12-TINV(AA$10,X12)*W12 -> #NAME? | AB12: =V12+TINV(AA$10,X12)*W12 -> #NAME?
A13: 10 | B13: 4.5 | C13: 4.1 | E13: {=AVERAGE(IF($A$4:$A$13=$A13,"",B$4:B$13))} -> 5.7222222 | F13: {=AVERAGE(IF($A$4:$A$13=$A13,"",C$4:C$13))} -> 5.6888889 | G13: =F13-E13 -> -0.033333333 | U13: identity | V13: {=TRANSPOSE(DRegIdentity(B4:B13,C4:C13,2.5))} -> #NAME? | W13: #NAME? | X13: =X12 -> 9 | Y13: =V13/W13 -> #NAME? | Z13: =TDIST(ABS(Y13),X13,2) -> #NAME? | AA13: =V13-TINV(AA$10,X13)*W13 -> #NAME? | AB13: =V13+TINV(AA$10,X13)*W13 -> #NAME?
E14: =AVERAGE(B4:B13) -> 5.6 | F14: =AVERAGE(C4:C13) -> 5.53
A15: λ | B15: 2.5
F16: var | G16: =DEVSQ(G4:G13)*(A13-1) -> 0.17788889
F17: s.e. | G17: =SQRT(G16/$A$13) -> 0.13337499

Sheet Dem 5
A1: Deming Regression - Prediction Interval
A3: Subject | B3: x | C3: y | E3: x̄ | F3: y̅ | G3: u | H3: v | I3: r | J3: b0 | K3: b1 | L3: p | N3: {=DRegPred(B17,B4:B13,C4:C13,B15,,TRUE)} -> #NAME? | O3: #NAME?
A4: 1 | B4: 5.1 | C4: 5.4 | E4: =($A$13*E$14-B4)/($A$13-1) -> 5.6555556 | F4: =($A$13*F$14-C4)/($A$13-1) -> 5.5444444 | G4: =G$14-$A$13*(E$14-B4)^2/($A$13-1) -> 7.6422222 | H4: =H$14-$A$13*(F$14-C4)^2/($A$13-1) -> 7.4622222 | I4: =I$14-$A$13*(E$14-B4)*(F$14-C4)/($A$13-1) -> 6.8277778 | J4: =F4-K4*E4 -> -0.29539655 | K4: =($B$15*H4-G4+SQRT(($B$15*H4-G4)^2+4*$B$15*I4^2))/(2*$B$15*I4) -> 1.0325849 | L4: =J4+$B$17*K4 -> 5.9001126 | N4: #NAME? | O4: #NAME?
A5: 2 | B5: 5.6 | C5: 5.6 | E5: =($A$13*E$14-B5)/($A$13-1) -> 5.6 | F5: =($A$13*F$14-C5)/($A$13-1) -> 5.5222222 | G5: =G$14-$A$13*(E$14-B5)^2/($A$13-1) -> 7.92 | H5: =H$14-$A$13*(F$14-C5)^2/($A$13-1) -> 7.4755556 | I5: =I$14-$A$13*(E$14-B5)*(F$14-C5)/($A$13-1) -> 6.9 | J5: =F5-K5*E5 -> -0.17538923 | K5: =($B$15*H5-G5+SQRT(($B$15*H5-G5)^2+4*$B$15*I5^2))/(2*$B$15*I5) -> 1.0174306 | L5: =J5+$B$17*K5 -> 5.9291945 | N5: #NAME? | O5: #NAME?
A6: 3 | B6: 6.8 | C6: 6.3 | E6: =($A$13*E$14-B6)/($A$13-1) -> 5.4666667 | F6: =($A$13*F$14-C6)/($A$13-1) -> 5.4444444 | G6: =G$14-$A$13*(E$14-B6)^2/($A$13-1) -> 6.32 | H6: =H$14-$A$13*(F$14-C6)^2/($A$13-1) -> 6.8222222 | I6: =I$14-$A$13*(E$14-B6)*(F$14-C6)/($A$13-1) -> 5.8733333 | J6: =F6-K6*E6 -> -0.54744202 | K6: =($B$15*H6-G6+SQRT(($B$15*H6-G6)^2+4*$B$15*I6^2))/(2*$B$15*I6) -> 1.0960768 | L6: =J6+$B$17*K6 -> 6.0290187 | N6: #NAME? | O6: #NAME?
A7: 4 | B7: 5.9 | C7: 6.1 | E7: =($A$13*E$14-B7)/($A$13-1) -> 5.5666667 | F7: =($A$13*F$14-C7)/($A$13-1) -> 5.4666667 | G7: =G$14-$A$13*(E$14-B7)^2/($A$13-1) -> 7.82 | H7: =H$14-$A$13*(F$14-C7)^2/($A$13-1) -> 7.12 | I7: =I$14-$A$13*(E$14-B7)*(F$14-C7)/($A$13-1) -> 6.71 | J7: =F7-K7*E7 -> -0.079873255 | K7: =($B$15*H7-G7+SQRT(($B$15*H7-G7)^2+4*$B$15*I7^2))/(2*$B$15*I7) -> 0.99638442 | L7: =J7+$B$17*K7 -> 5.8984332
A8: 5 | B8: 4 | C8: 4.7 | E8: =($A$13*E$14-B8)/($A$13-1) -> 5.7777778 | F8: =($A$13*F$14-C8)/($A$13-1) -> 5.6222222 | G8: =G$14-$A$13*(E$14-B8)^2/($A$13-1) -> 5.0755556 | H8: =H$14-$A$13*(F$14-C8)^2/($A$13-1) -> 6.7155556 | I8: =I$14-$A$13*(E$14-B8)*(F$14-C8)/($A$13-1) -> 5.4244444 | J8: =F8-K8*E8 -> -1.2979027 | K8: =($B$15*H8-G8+SQRT(($B$15*H8-G8)^2+4*$B$15*I8^2))/(2*$B$15*I8) -> 1.1977139 | L8: =J8+$B$17*K8 -> 5.8883809
A9: 6 | B9: 5.6 | C9: 5.1 | E9: =($A$13*E$14-B9)/($A$13-1) -> 5.6 | F9: =($A$13*F$14-C9)/($A$13-1) -> 5.5777778 | G9: =G$14-$A$13*(E$14-B9)^2/($A$13-1) -> 7.92 | H9: =H$14-$A$13*(F$14-C9)^2/($A$13-1) -> 7.2755556 | I9: =I$14-$A$13*(E$14-B9)*(F$14-C9)/($A$13-1) -> 6.9 | J9: =F9-K9*E9 -> -0.0034319233 | K9: =($B$15*H9-G9+SQRT(($B$15*H9-G9)^2+4*$B$15*I9^2))/(2*$B$15*I9) -> 0.99664459 | L9: =J9+$B$17*K9 -> 5.9764356
A10: 7 | B10: 6.6 | C10: 6.6 | E10: =($A$13*E$14-B10)/($A$13-1) -> 5.4888889 | F10: =($A$13*F$14-C10)/($A$13-1) -> 5.4111111 | G10: =G$14-$A$13*(E$14-B10)^2/($A$13-1) -> 6.8088889 | H10: =H$14-$A$13*(F$14-C10)^2/($A$13-1) -> 6.2088889 | I10: =I$14-$A$13*(E$14-B10)*(F$14-C10)/($A$13-1) -> 5.7111111 | J10: =F10-K10*E10 -> -0.11813617 | K10: =($B$15*H10-G10+SQRT(($B$15*H10-G10)^2+4*$B$15*I10^2))/(2*$B$15*I10) -> 1.0073527 | L10: =J10+$B$17*K10 -> 5.9259803
A11: 8 | B11: 6.7 | C11: 6.8 | E11: =($A$13*E$14-B11)/($A$13-1) -> 5.4777778 | F11: =($A$13*F$14-C11)/($A$13-1) -> 5.3888889 | G11: =G$14-$A$13*(E$14-B11)^2/($A$13-1) -> 6.5755556 | H11: =H$14-$A$13*(F$14-C11)^2/($A$13-1) -> 5.6888889 | I11: =I$14-$A$13*(E$14-B11)*(F$14-C11)/($A$13-1) -> 5.3477778 | J11: =F11-K11*E11 -> 0.020224907 | K11: =($B$15*H11-G11+SQRT(($B$15*H11-G11)^2+4*$B$15*I11^2))/(2*$B$15*I11) -> 0.98008065 | L11: =J11+$B$17*K11 -> 5.9007088
A12: 9 | B12: 5.2 | C12: 4.6 | E12: =($A$13*E$14-B12)/($A$13-1) -> 5.6444444 | F12: =($A$13*F$14-C12)/($A$13-1) -> 5.6333333 | G12: =G$14-$A$13*(E$14-B12)^2/($A$13-1) -> 7.7422222 | H12: =H$14-$A$13*(F$14-C12)^2/($A$13-1) -> 6.52 | I12: =I$14-$A$13*(E$14-B12)*(F$14-C12)/($A$13-1) -> 6.4866667 | J12: =F12-K12*E12 -> 0.27592972 | K12: =($B$15*H12-G12+SQRT(($B$15*H12-G12)^2+4*$B$15*I12^2))/(2*$B$15*I12) -> 0.94914631 | L12: =J12+$B$17*K12 -> 5.9708076
A13: 10 | B13: 4.5 | C13: 4.1 | E13: =($A$13*E$14-B13)/($A$13-1) -> 5.7222222 | F13: =($A$13*F$14-C13)/($A$13-1) -> 5.6888889 | G13: =G$14-$A$13*(E$14-B13)^2/($A$13-1) -> 6.5755556 | H13: =H$14-$A$13*(F$14-C13)^2/($A$13-1) -> 5.2088889 | I13: =I$14-$A$13*(E$14-B13)*(F$14-C13)/($A$13-1) -> 5.1522222 | J13: =F13-K13*E13 -> 0.36486044 | K13: =($B$15*H13-G13+SQRT(($B$15*H13-G13)^2+4*$B$15*I13^2))/(2*$B$15*I13) -> 0.93041274 | L13: =J13+$B$17*K13 -> 5.9473369
E14: =AVERAGE(B4:B13) -> 5.6 | F14: =AVERAGE(C4:C13) -> 5.53 | G14: =DEVSQ(B4:B13) -> 7.92 | H14: =DEVSQ(C4:C13) -> 7.481 | I14: =SUMPRODUCT(B4:B13-E14,C4:C13-F14) -> 6.9 | J14: =F14-K14*E14 -> -0.17079908 | K14: =($B$15*H14-G14+SQRT(($B$15*H14-G14)^2+4*$B$15*I14^2))/(2*$B$15*I14) -> 1.0179998 | L14: =J14+$B$17*K14 -> 5.9371999
A15: λ | B15: 2.5
K16: var | L16: =DEVSQ(L4:L13)*(A13-1) -> 0.16184195
A17: new | B17: 6 | C17: =B17*K14+J14 -> 5.9371999 | K17: s.e. | L17: =SQRT(L16/$A$13) -> 0.12721712

Sheet Dem 6
A1: Deming Regression - Prediction Intervals
A3: Confidence Interval for Sample Data Predictions | I3: Prediction Intervals
A5: Subject | B5: x | C5: y | D5: pred y | E5: s.e. | F5: lower | G5: upper | I5: x | J5: 4 | K5: 5 | L5: 6 | M5: 7
A6: 1 | B6: 5.1 | C6: 5.4 | D6: {=TRANSPOSE(DRegPred(B6,$B$6:$B$15,$C$6:$C$15,$B$17))} -> #NAME? | E6: #NAME? | F6: #NAME? | G6: #NAME? | I6: {=DRegPred(J5,B6:B15,C6:C15,B17,B18,TRUE)} -> #NAME? | J6: #NAME? | K6: {=DRegPred(K5,$B$6:$B$15,$C$6:$C$15,$B$17,$B$18)} -> #NAME? | L6: {=DRegPred(L5,$B$6:$B$15,$C$6:$C$15,$B$17,$B$18)} -> #NAME? | M6: {=DRegPred(M5,$B$6:$B$15,$C$6:$C$15,$B$17,$B$18)} -> #NAME?
A7: 2 | B7: 5.6 | C7: 5.6 | D7: {=TRANSPOSE(DRegPred(B7,$B$6:$B$15,$C$6:$C$15,$B$17))} -> #NAME? | E7: #NAME? | F7: #NAME? | G7: #NAME? | I7: #NAME? | J7: #NAME? | K7: #NAME? | L7: #NAME? | M7: #NAME?
A8: 3 | B8: 6.8 | C8: 6.3 | D8: {=TRANSPOSE(DRegPred(B8,$B$6:$B$15,$C$6:$C$15,$B$17))} -> #NAME? | E8: #NAME? | F8: #NAME? | G8: #NAME? | I8: #NAME? | J8: #NAME? | K8: #NAME? | L8: #NAME? | M8: #NAME?
A9: 4 | B9: 5.9 | C9: 6.1 | D9: {=TRANSPOSE(DRegPred(B9,$B$6:$B$15,$C$6:$C$15,$B$17))} -> #NAME? | E9: #NAME? | F9: #NAME? | G9: #NAME? | I9: #NAME? | J9: #NAME? | K9: #NAME? | L9: #NAME? | M9: #NAME?
A10: 5 | B10: 4 | C10: 4.7 | D10: {=TRANSPOSE(DRegPred(B10,$B$6:$B$15,$C$6:$C$15,$B$17))} -> #NAME? | E10: #NAME? | F10: #NAME? | G10: #NAME?
A11: 6 | B11: 5.6 | C11: 5.1 | D11: {=TRANSPOSE(DRegPred(B11,$B$6:$B$15,$C$6:$C$15,$B$17))} -> #NAME? | E11: #NAME? | F11: #NAME? | G11: #NAME?
A12: 7 | B12: 6.6 | C12: 6.6 | D12: {=TRANSPOSE(DRegPred(B12,$B$6:$B$15,$C$6:$C$15,$B$17))} -> #NAME? | E12: #NAME? | F12: #NAME? | G12: #NAME?
A13: 8 | B13: 6.7 | C13: 6.8 | D13: {=TRANSPOSE(DRegPred(B13,$B$6:$B$15,$C$6:$C$15,$B$17))} -> #NAME? | E13: #NAME? | F13: #NAME? | G13: #NAME?
A14: 9 | B14: 5.2 | C14: 4.6 | D14: {=TRANSPOSE(DRegPred(B14,$B$6:$B$15,$C$6:$C$15,$B$17))} -> #NAME? | E14: #NAME? | F14: #NAME? | G14: #NAME?
A15: 10 | B15: 4.5 | C15: 4.1 | D15: {=TRANSPOSE(DRegPred(B15,$B$6:$B$15,$C$6:$C$15,$B$17))} -> #NAME? | E15: #NAME? | F15: #NAME? | G15: #NAME?
A17: lambda | B17: 2.5
A18: alpha | B18: 0.05
A19: df | B19: =A15-1 -> 9
A20: crit | B20: =TINV(B18,B19) -> 2.2621572

Sheet Mult Reg 1
A1: Method of Least Squares
A3: Color | B3: Quality | C3: Price | F3: Covariance matrix
A4: 7 | B4: 5 | C4: 65
A5: 3 | B5: 7 | C5: 38 | G5: Color | H5: Quality | I5: Price
A6: 5 | B6: 8 | C6: 51 | F6: Color | G6: {=MMULT(TRANSPOSE(A4:C14-A15:C15),A4:C14-A15:C15)/(B17-1)} -> 5.8 | H6: -2.1 | I6: 20.5
A7: 8 | B7: 1 | C7: 38 | F7: Quality | G7: -2.1 | H7: 6.8181818 | I7: 15.345455
A8: 9 | B8: 3 | C8: 55 | F8: Price | G8: 20.5 | H8: 15.345455 | I8: 185.76364
A9: 5 | B9: 4 | C9: 43
A10: 4 | B10: 0 | C10: 25 | F10: Equations
A11: 2 | B11: 6 | C11: 33 | G11: b1 | H11: b2 | I11: const
A12: 8 | B12: 7 | C12: 71 | G12: =G6 -> 5.8 | H12: =H6 -> -2.1 | I12: =I6 -> 20.5
A13: 6 | B13: 4 | C13: 51 | G13: =G7 -> -2.1 | H13: =H7 -> 6.8181818 | I13: =I7 -> 15.345455
A14: 9 | B14: 2 | C14: 49
A15: =AVERAGE(A4:A14) -> 6 | B15: =AVERAGE(B4:B14) -> 4.2727273 | C15: =AVERAGE(C4:C14) -> 47.181818 | D15: mean | F15: A | I15: C | K15: A-1C
F16: =G12 -> 5.8 | G16: =H12 -> -2.1 | I16: =I12 -> 20.5 | K16: {=MMULT(MINVERSE(F16:G17),I16:I17)} -> 4.8952884
A17: n | B17: =COUNT(A4:A14) -> 11 | F17: =G13 -> -2.1 | G17: =H13 -> 6.8181818 | I17: =I13 -> 15.345455 | K17: 3.7584155
F19: b0 | G19: =C15-MMULT(A15:B15,G20:G21) -> 1.7514037
F20: b1 | G20: {=MMULT(MINVERSE(G12:H13),I12:I13)} -> 4.8952884
F21: b2 | G21: 3.7584155
F23: Covariance matrix using COV function
G25: Color | H25: Quality | I25: Price
F26: Color | G26: {=COV(A4:C14)} -> #NAME? | H26: #NAME? | I26: #NAME?
F27: Quality | G27: #NAME? | H27: #NAME? | I27: #NAME?
F28: Price | G28: #NAME? | H28: #NAME? | I28: #NAME?

Sheet Mult Reg 2
A1: Method of Least Squares
A3: Color | B3: Quality | C3: Price | E3: X | I3: Y | K3: B | M3: Ŷ | O3: E | Q3: H = X(XTX)-1XT | AC3: Stud E
A4: 7 | B4: 5 | C4: 65 | E4: 1 | F4: =A4 -> 7 | G4: =B4 -> 5 | I4: =C4 -> 65 | K4: {=MMULT(E17:G19,MMULT(TRANSPOSE(E4:G14),I4:I14))} -> 1.7514037 | M4: {=MMULT(E4:G14,K4:K6)} -> 54.8105 | O4: =I4-M4 -> 10.1895 | Q4: {=MMULT(MMULT(E4:G14,E17:G19),TRANSPOSE(E4:G14))} -> 0.1277394 | R4: 0.06869518 | S4: 0.134182 | T4: 0.079562214 | U4: 0.13927915 | V4: 0.062252581 | W4: -0.033429067 | X4: 0.026960594 | Y4: 0.18745634 | Z4: 0.086004813 | AA4: 0.1212968 | AB4: 1 | AC4: {=O4:O14/SQRT(O19*(1-INDEX(Q4:AA14,AB4:AB14,AB4:AB14)))} -> 1.852916
A5: 3 | B5: 7 | C5: 38 | E5: 1 | F5: =A5 -> 3 | G5: =B5 -> 7 | I5: =C5 -> 38 | K5: 4.8952884 | M5: 42.746177 | O5: =I5-M5 -> -4.7461771 | Q5: 0.06869518 | R5: 0.29053792 | S5: 0.23379648 | T5: -0.081580377 | U5: -0.069316153 | V5: 0.12543662 | W5: 0.058992471 | X5: 0.30536366 | Y5: 0.080959404 | Z5: 0.083520919 | AA5: -0.096406117 | AB5: =AB4+1 -> 2 | AC5: -0.95698541
A6: 5 | B6: 8 | C6: 51 | E6: 1 | F6: =A6 -> 5 | G6: =B6 -> 8 | I6: =C6 -> 51 | K6: 3.7584155 | M6: 56.295169 | O6: =I6-M6 -> -5.2951693 | Q6: 0.134182 | R6: 0.23379648 | S6: 0.29509172 | T6: -0.085150974 | U6: 0.028823514 | V6: 0.07288675 | W6: -0.15219022 | X6: 0.17537323 | Y6: 0.24815649 | Z6: 0.075758752 | AA6: -0.026727729 | AB6: =AB5+1 -> 3 | AC6: -1.0711234
A7: 8 | B7: 1 | C7: 38 | E7: 1 | F7: =A7 -> 8 | G7: =B7 -> 1 | I7: =C7 -> 38 | M7: 44.672126 | O7: =I7-M7 -> -6.6721261 | Q7: 0.079562214 | R7: -0.081580377 | S7: -0.085150974 | T7: 0.26709617 | U7: 0.20220446 | V7: 0.083132811 | W7: 0.23216642 | X7: -0.058759606 | Y7: 0.014670496 | Z7: 0.10238299 | AA7: 0.2442754 | AB7: =AB6+1 -> 4 | AC7: -1.3236304
A8: 9 | B8: 3 | C8: 55 | E8: 1 | F8: =A8 -> 9 | G8: =B8 -> 3 | I8: =C8 -> 55 | K8: s.e. | M8: 57.084245 | O8: =I8-M8 -> -2.0842454 | Q8: 0.13927915 | R8: -0.069316153 | S8: 0.028823514 | T8: 0.20220446 | U8: 0.2466558 | V8: 0.041139486 | W8: 0.002846128 | X8: -0.11684649 | Y8: 0.1837305 | Z8: 0.091748816 | AA8: 0.24973479 | AB8: =AB7+1 -> 5 | AC8: -0.40782899
A9: 5 | B9: 4 | C9: 43 | E9: 1 | F9: =A9 -> 5 | G9: =B9 -> 4 | I9: =C9 -> 43 | K9: =SQRT(I17) -> 6.9602027 | M9: 41.261507 | O9: =I9-M9 -> 1.7384926 | Q9: 0.062252581 | R9: 0.12543662 | S9: 0.07288675 | T9: 0.083132811 | U9: 0.041139486 | V9: 0.11480245 | W9: 0.17775363 | X9: 0.15695102 | Y9: 0.020259256 | Z9: 0.09376698 | AA9: 0.051618412 | AB9: =AB8+1 -> 6 | AC9: 0.31381862
A10: 4 | B10: 0 | C10: 25 | E10: 1 | F10: =A10 -> 4 | G10: =B10 -> 0 | I10: =C10 -> 25 | K10: =SQRT(J18) -> 0.82022978 | M10: 21.332557 | O10: =I10-M10 -> 3.6674429 | Q10: -0.033429067 | R10: 0.058992471 | S10: -0.15219022 | T10: 0.23216642 | U10: 0.002846128 | V10: 0.17775363 | W10: 0.57204585 | X10: 0.2058268 | Y10: -0.26274936 | Z10: 0.11340526 | AA10: 0.085332091 | AB10: =AB9+1 -> 7 | AC10: 0.95211785
A11: 2 | B11: 6 | C11: 33 | E11: 1 | F11: =A11 -> 2 | G11: =B11 -> 6 | I11: =C11 -> 33 | K11: =SQRT(K19) -> 0.75651099 | M11: 34.092473 | O11: =I11-M11 -> -1.0924733 | Q11: 0.026960594 | R11: 0.30536366 | S11: 0.17537323 | T11: -0.058759606 | U11: -0.11684649 | V11: 0.15695102 | W11: 0.2058268 | X11: 0.36805609 | Y11: -0.03112629 | Z11: 0.089653031 | AA11: -0.12145204 | AB11: =AB10+1 -> 8 | AC11: -0.23339821
A12: 8 | B12: 7 | C12: 71 | E12: 1 | F12: =A12 -> 8 | G12: =B12 -> 7 | I12: =C12 -> 71 | M12: 67.222619 | O12: =I12-M12 -> 3.777381 | Q12: 0.18745634 | R12: 0.080959404 | S12: 0.24815649 | T12: 0.014670496 | U12: 0.1837305 | V12: 0.020259256 | W12: -0.26274936 | X12: -0.03112629 | Y12: 0.35651634 | Z12: 0.075370643 | AA12: 0.12675619 | AB12: =AB11+1 -> 9 | AC12: 0.7997385
A13: 6 | B13: 4 | C13: 51 | E13: 1 | F13: =A13 -> 6 | G13: =B13 -> 4 | I13: =C13 -> 51 | M13: 46.156796 | O13: =I13-M13 -> 4.8432042 | Q13: 0.086004813 | R13: 0.083520919 | S13: 0.075758752 | T13: 0.10238299 | U13: 0.091748816 | V13: 0.09376698 | W13: 0.11340526 | X13: 0.089653031 | Y13: 0.075370643 | Z13: 0.092136925 | AA13: 0.096250873 | AB13: =AB12+1 -> 10 | AC13: 0.86327383
A14: 9 | B14: 2 | C14: 49 | E14: 1 | F14: =A14 -> 9 | G14: =B14 -> 2 | I14: =C14 -> 49 | M14: 53.32583 | O14: =I14-M14 -> -4.3258299 | Q14: 0.1212968 | R14: -0.096406117 | S14: -0.026727729 | T14: 0.2442754 | U14: 0.24973479 | V14: 0.051618412 | W14: 0.085332091 | X14: -0.12145204 | Y14: 0.12675619 | Z14: 0.096250873 | AA14: 0.26932133 | AB14: =AB13+1 -> 11 | AC14: -0.85947291
E16: (XTX)-1 | I16: MSRes(XTX)-1
E17: {=MINVERSE(MMULT(TRANSPOSE(E4:G14),E4:G14))} -> 1.3973195 | F17: -0.14197004 | G17: -0.10639344 | I17: {=O19*E17:G19} -> 48.444421 | J17: -4.9220357 | K17: -3.6886114 | N17: SSRes | O17: =DEVSQ(O4:O14) -> 277.35631
E18: -0.14197004 | F18: 0.019405418 | G18: 0.0059768687 | I18: -4.9220357 | J18: 0.67277689 | K18: 0.20721528 | N18: dfRes | O18: =COUNT(A4:A14)-COUNT(A4:B4)-1 -> 8
E19: -0.10639344 | F19: 0.0059768687 | G19: 0.016507542 | I19: -3.6886114 | J19: 0.20721528 | K19: 0.57230887 | N19: MSRes | O19: =O17/O18 -> 34.669539
A21: Normality
A23: QQ Tables - stud. res | R23: QQ Tables - y
A25: Count | B25: =COUNT(AC4:AC14) -> 11 | C25: =2*B25 -> 22 | R25: Count | S25: =COUNT(I4:I14) -> 11 | T25: =2*S25 -> 22
A26: Mean | B26: =AVERAGE(AC4:AC14) -> -0.0064158645 | R26: Mean | S26: =AVERAGE(I4:I14) -> 47.181818
A27: Std Dev | B27: =STDEV(AC4:AC14) -> 1.0294317 | R27: Std Dev | S27: =STDEV(I4:I14) -> 13.629513
A29: Interval | B29: Data | C29: Std Norm | D29: Std Data | R29: Interval | S29: Data | T29: Std Norm | U29: Std Data
A30: 1 | B30: -1.3236304 | C30: =NORMSINV(A30/C$25) -> -1.6906216 | D30: =STANDARDIZE(B30,B$26,B$27) -> -1.2795551 | R30: 1 | S30: 25 | T30: =NORMSINV(R30/T$25) -> -1.6906216 | U30: =STANDARDIZE(S30,S$26,S$27) -> -1.6274842
A31: =A30+2 -> 3 | B31: -1.0711234 | C31: =NORMSINV(A31/C$25) -> -1.0968036 | D31: =STANDARDIZE(B31,B$26,B$27) -> -1.0342674 | R31: =R30+2 -> 3 | S31: 33 | T31: =NORMSINV(R31/T$25) -> -1.0968036 | U31: =STANDARDIZE(S31,S$26,S$27) -> -1.0405227
A32: =A31+2 -> 5 | B32: -0.95698541 | C32: =NORMSINV(A32/C$25) -> -0.74785859 | D32: =STANDARDIZE(B32,B$26,B$27) -> -0.92339257 | R32: =R31+2 -> 5 | S32: 38 | T32: =NORMSINV(R32/T$25) -> -0.74785859 | U32: =STANDARDIZE(S32,S$26,S$27) -> -0.67367175
A33: =A32+2 -> 7 | B33: -0.85947291 | C33: =NORMSINV(A33/C$25) -> -0.47278912 | D33: =STANDARDIZE(B33,B$26,B$27) -> -0.82866797 | R33: =R32+2 -> 7 | S33: 38 | T33: =NORMSINV(R33/T$25) -> -0.47278912 | U33: =STANDARDIZE(S33,S$26,S$27) -> -0.67367175
A34: =A33+2 -> 9 | B34: -0.40782899 | C34: =NORMSINV(A34/C$25) -> -0.22988412 | D34: =STANDARDIZE(B34,B$26,B$27) -> -0.38993664 | R34: =R33+2 -> 9 | S34: 43 | T34: =NORMSINV(R34/T$25) -> -0.22988412 | U34: =STANDARDIZE(S34,S$26,S$27) -> -0.3068208
A35: =A34+2 -> 11 | B35: -0.23339821 | C35: =NORMSINV(A35/C$25) -> 0 | D35: =STANDARDIZE(B35,B$26,B$27) -> -0.22049288 | R35: =R34+2 -> 11 | S35: 49 | T35: =NORMSINV(R35/T$25) -> 0 | U35: =STANDARDIZE(S35,S$26,S$27) -> 0.13340035
A36: =A35+2 -> 13 | B36: 0.31381862 | C36: =NORMSINV(A36/C$25) -> 0.22988412 | D36: =STANDARDIZE(B36,B$26,B$27) -> 0.31107892 | R36: =R35+2 -> 13 | S36: 51 | T36: =NORMSINV(R36/T$25) -> 0.22988412 | U36: =STANDARDIZE(S36,S$26,S$27) -> 0.28014073
A37: =A36+2 -> 15 | B37: 0.7997385 | C37: =NORMSINV(A37/C$25) -> 0.47278912 | D37: =STANDARDIZE(B37,B$26,B$27) -> 0.78310625 | R37: =R36+2 -> 15 | S37: 51 | T37: =NORMSINV(R37/T$25) -> 0.47278912 | U37: =STANDARDIZE(S37,S$26,S$27) -> 0.28014073
A38: =A37+2 -> 17 | B38: 0.86327383 | C38: =NORMSINV(A38/C$25) -> 0.74785859 | D38: =STANDARDIZE(B38,B$26,B$27) -> 0.84482509 | R38: =R37+2 -> 17 | S38: 55 | T38: =NORMSINV(R38/T$25) -> 0.74785859 | U38: =STANDARDIZE(S38,S$26,S$27) -> 0.57362149
A39: =A38+2 -> 19 | B39: 0.95211785 | C39: =NORMSINV(A39/C$25) -> 1.0968036 | D39: =STANDARDIZE(B39,B$26,B$27) -> 0.93112904 | R39: =R38+2 -> 19 | S39: 65 | T39: =NORMSINV(R39/T$25) -> 1.0968036 | U39: =STANDARDIZE(S39,S$26,S$27) -> 1.3073234
A40: =A39+2 -> 21 | B40: 1.852916 | C40: =NORMSINV(A40/C$25) -> 1.6906216 | D40: =STANDARDIZE(B40,B$26,B$27) -> 1.8061732 | R40: =R39+2 -> 21 | S40: 71 | T40: =NORMSINV(R40/T$25) -> 1.6906216 | U40: =STANDARDIZE(S40,S$26,S$27) -> 1.7475445
A45: Homogeneity of variances
A47: Ŷ | B47: Stud. E
A48: =M4 -> 54.8105 | B48: =AC4 -> 1.852916
A49: =M5 -> 42.746177 | B49: =AC5 -> -0.95698541
A50: =M6 -> 56.295169 | B50: =AC6 -> -1.0711234
A51: =M7 -> 44.672126 | B51: =AC7 -> -1.3236304
A52: =M8 -> 57.084245 | B52: =AC8 -> -0.40782899
A53: =M9 -> 41.261507 | B53: =AC9 -> 0.31381862
A54: =M10 -> 21.332557 | B54: =AC10 -> 0.95211785
A55: =M11 -> 34.092473 | B55: =AC11 -> -0.23339821
A56: =M12 -> 67.222619 | B56: =AC12 -> 0.7997385
A57: =M13 -> 46.156796 | B57: =AC13 -> 0.86327383
A58: =M14 -> 53.32583 | B58: =AC14 -> -0.85947291

Sheet Mult Reg 2A
A1: Method of Least Squares (using Real Statistics functions)
A3: Color | B3: Quality | C3: Price | E3: X | I3: Y | K3: B | M3: Ŷ | O3: E | Q3: H = X(XTX)-1XT | AC3: Stud E
A4: 7 | B4: 5 | C4: 65 | E4: {=DESIGN(A4:B14)} -> #NAME? | F4: #NAME? | G4: #NAME? | I4: =C4 -> 65 | K4: {=RegCoeff(A4:B14,C4:C14)} -> #NAME? | M4: {=RegY(A4:B14,C4:C14)} -> #NAME? | O4: {=RegE(A4:B14,C4:C14)} -> #NAME? | Q4: {=HAT(A4:B14)} -> #NAME? | R4: #NAME? | S4: #NAME? | T4: #NAME? | U4: #NAME? | V4: #NAME? | W4: #NAME? | X4: #NAME? | Y4: #NAME? | Z4: #NAME? | AA4: #NAME? | AB4: 1 | AC4: {=RegStudE(A4:B14,C4:C14)} -> #NAME?
A5: 3 | B5: 7 | C5: 38 | E5: #NAME? | F5: #NAME? | G5: #NAME? | I5: =C5 -> 38 | K5: #NAME? | M5: #NAME? | O5: #NAME? | Q5: #NAME? | R5: #NAME? | S5: #NAME? | T5: #NAME? | U5: #NAME? | V5: #NAME? | W5: #NAME? | X5: #NAME? | Y5: #NAME? | Z5: #NAME? | AA5: #NAME? | AB5: =AB4+1 -> 2 | AC5: #NAME?
A6: 5 | B6: 8 | C6: 51 | E6: #NAME? | F6: #NAME? | G6: #NAME? | I6: =C6 -> 51 | K6: #NAME? | M6: #NAME? | O6: #NAME? | Q6: #NAME? | R6: #NAME? | S6: #NAME? | T6: #NAME? | U6: #NAME? | V6: #NAME? | W6: #NAME? | X6: #NAME? | Y6: #NAME? | Z6: #NAME? | AA6: #NAME? | AB6: =AB5+1 -> 3 | AC6: #NAME?
A7: 8 | B7: 1 | C7: 38 | E7: #NAME? | F7: #NAME? | G7: #NAME? | I7: =C7 -> 38 | M7: #NAME? | O7: #NAME? | Q7: #NAME? | R7: #NAME? | S7: #NAME? | T7: #NAME? | U7: #NAME? | V7: #NAME? | W7: #NAME? | X7: #NAME? | Y7: #NAME? | Z7: #NAME? | AA7: #NAME? | AB7: =AB6+1 -> 4 | AC7: #NAME?
A8: 9 | B8: 3 | C8: 55 | E8: #NAME? | F8: #NAME? | G8: #NAME? | I8: =C8 -> 55 | K8: s.e. | M8: #NAME? | O8: #NAME? | Q8: #NAME? | R8: #NAME? | S8: #NAME? | T8: #NAME? | U8: #NAME? | V8: #NAME? | W8: #NAME? | X8: #NAME? | Y8: #NAME? | Z8: #NAME? | AA8: #NAME? | AB8: =AB7+1 -> 5 | AC8: #NAME?
A9: 5 | B9: 4 | C9: 43 | E9: #NAME? | F9: #NAME? | G9: #NAME? | I9: =C9 -> 43 | K9: {=RegCoeffSE(A4:B14,C4:C14)} -> #NAME? | M9: #NAME? | O9: #NAME? | Q9: #NAME? | R9: #NAME? | S9: #NAME? | T9: #NAME? | U9: #NAME? | V9: #NAME? | W9: #NAME? | X9: #NAME? | Y9: #NAME? | Z9: #NAME? | AA9: #NAME? | AB9: =AB8+1 -> 6 | AC9: #NAME?
A10: 4 | B10: 0 | C10: 25 | E10: #NAME? | F10: #NAME? | G10: #NAME? | I10: =C10 -> 25 | K10: #NAME? | M10: #NAME? | O10: #NAME? | Q10: #NAME? | R10: #NAME? | S10: #NAME? | T10: #NAME? | U10: #NAME? | V10: #NAME? | W10: #NAME? | X10: #NAME? | Y10: #NAME? | Z10: #NAME? | AA10: #NAME? | AB10: =AB9+1 -> 7 | AC10: #NAME?
A11: 2 | B11: 6 | C11: 33 | E11: #NAME? | F11: #NAME? | G11: #NAME? | I11: =C11 -> 33 | K11: #NAME? | M11: #NAME? | O11: #NAME? | Q11: #NAME? | R11: #NAME? | S11: #NAME? | T11: #NAME? | U11: #NAME? | V11: #NAME? | W11: #NAME? | X11: #NAME? | Y11: #NAME? | Z11: #NAME? | AA11: #NAME? | AB11: =AB10+1 -> 8 | AC11: #NAME?
A12: 8 | B12: 7 | C12: 71 | E12: #NAME? | F12: #NAME? | G12: #NAME? | I12: =C12 -> 71 | M12: #NAME? | O12: #NAME? | Q12: #NAME? | R12: #NAME? | S12: #NAME? | T12: #NAME? | U12: #NAME? | V12: #NAME? | W12: #NAME? | X12: #NAME? | Y12: #NAME? | Z12: #NAME? | AA12: #NAME? | AB12: =AB11+1 -> 9 | AC12: #NAME?
A13: 6 | B13: 4 | C13: 51 | E13: #NAME? | F13: #NAME? | G13: #NAME? | I13: =C13 -> 51 | M13: #NAME? | O13: #NAME? | Q13: #NAME? | R13: #NAME? | S13: #NAME? | T13: #NAME? | U13: #NAME? | V13: #NAME? | W13: #NAME? | X13: #NAME? | Y13: #NAME? | Z13: #NAME? | AA13: #NAME? | AB13: =AB12+1 -> 10 | AC13: #NAME?
A14: 9 | B14: 2 | C14: 49 | E14: #NAME? | F14: #NAME? | G14: #NAME? | I14: =C14 -> 49 | M14: #NAME? | O14: #NAME? | Q14: #NAME? | R14: #NAME? | S14: #NAME? | T14: #NAME? | U14: #NAME? | V14: #NAME? | W14: #NAME? | X14: #NAME? | Y14: #NAME? | Z14: #NAME? | AA14: #NAME? | AB14: =AB13+1 -> 11 | AC14: #NAME?
E16: (XTX)-1 | I16: MSRes(XTX)-1
E17: {=CORE(A4:B14)} -> #NAME? | F17: #NAME? | G17: #NAME? | I17: {=RegCov(A4:B14,C4:C14)} -> #NAME? | J17: #NAME? | K17: #NAME? | N17: SSRes | O17: =SSRes(A4:B14,C4:C14) -> #NAME? | Q17: {=MMULT(TRANSPOSE(I4:I14-M4:M14),I4:I14-M4:M14)} -> #NAME? | R17: =MMULT(TRANSPOSE(I4:I14-M4:M14),I4:I14-M4:M14)
E18: #NAME? | F18: #NAME? | G18: #NAME? | I18: #NAME? | J18: #NAME? | K18: #NAME? | N18: dfRes | O18: {=dfRes(A4:B14)} -> #NAME?
E19: #NAME? | F19: #NAME? | G19: #NAME? | I19: #NAME? | J19: #NAME? | K19: #NAME? | N19: MSRes | O19: =MSRes(A4:B14,C4:C14) -> #NAME?

Sheet Mult Reg 2B
A1: Finding regression coefficients using Solver
A3: Color | B3: Quality | C3: Price (Y) | F3: B | H3: Ŷ | J3: E
A4: 7 | B4: 5 | C4: 65 | E4: intercept | F4: 1.751632 | H4: =A4*$F$5+B4*$F$6+$F$4 -> 54.810484 | J4: =C4-H4 -> 10.189516
A5: 3 | B5: 7 | C5: 38 | E5: color | F5: 4.8952633 | H5: =A5*$F$5+B5*$F$6+$F$4 -> 42.746234 | J5: =C5-H5 -> -4.7462341
A6: 5 | B6: 8 | C6: 51 | E6: quality | F6: 3.7584018 | H6: =A6*$F$5+B6*$F$6+$F$4 -> 56.295162 | J6: =C6-H6 -> -5.2951623
A7: 8 | B7: 1 | C7: 38 | H7: =A7*$F$5+B7*$F$6+$F$4 -> 44.67214 | J7: =C7-H7 -> -6.6721399
A8: 9 | B8: 3 | C8: 55 | E8: SSE | F8: =SUMSQ(J4:J14) -> 277.35631 | H8: =A8*$F$5+B8*$F$6+$F$4 -> 57.084207 | J8: =C8-H8 -> -2.0842066
A9: 5 | B9: 4 | C9: 43 | H9: =A9*$F$5+B9*$F$6+$F$4 -> 41.261555 | J9: =C9-H9 -> 1.7384447
A10: 4 | B10: 0 | C10: 25 | H10: =A10*$F$5+B10*$F$6+$F$4 -> 21.332685 | J10: =C10-H10 -> 3.6673149
A11: 2 | B11: 6 | C11: 33 | H11: =A11*$F$5+B11*$F$6+$F$4 -> 34.092569 | J11: =C11-H11 -> -1.0925691
A12: 8 | B12: 7 | C12: 71 | H12: =A12*$F$5+B12*$F$6+$F$4 -> 67.22255 | J12: =C12-H12 -> 3.7774496
A13: 6 | B13: 4 | C13: 51 | H13: =A13*$F$5+B13*$F$6+$F$4 -> 46.156819 | J13: =C13-H13 -> 4.8431814
A14: 9 | B14: 2 | C14: 49 | H14: =A14*$F$5+B14*$F$6+$F$4 -> 53.325805 | J14: =C14-H14 -> -4.3258049

Sheet Mult Reg 3
A1: Sample size requirements
B3: Significance level α = .01 | G3: Significance level α = .05
A4: k | B4: 2 | C4: 5 | D4: 10 | E4: 20 | G4: 2 | H4: 5 | I4: 10 | J4: 20
A5: 20 | B5: 0.45 | C5: 0.56 | D5: 0.71 | E5: N/A | G5: 0.39 | H5: 0.48 | I5: 0.64 | J5: N/A
A6: 50 | B6: 0.23 | C6: 0.29 | D6: 0.36 | E6: 0.49 | G6: 0.19 | H6: 0.23 | I6: 0.29 | J6: 0.42
A7: 100 | B7: 0.13 | C7: 0.16 | D7: 0.2 | E7: 0.26 | G7: 0.1 | H7: 0.12 | I7: 0.15 | J7: 0.21
A8: 250 | B8: 0.05 | C8: 0.07 | D8: 0.08 | E8: 0.11 | G8: 0.04 | H8: 0.05 | I8: 0.06 | J8: 0.09
A9: 500 | B9: 0.03 | C9: 0.03 | D9: 0.04 | E9: 0.06 | G9: 0.03 | H9: 0.04 | I9: 0.05 | J9: 0.08
A10: 1000 | B10: 0.01 | C10: 0.02 | D10: 0.02 | E10: 0.03 | G10: 0.01 | H10: 0.01 | I10: 0.02 | J10: 0.02
A12: Table lists the minimum value of R2 that can be detected by a given sample size and # of dependent variables k
A13: N/A = not applicable

Sheet Mult Reg 4
A1: Multiple Regression | M1: Model with all three independent variables | U1: Model only with Infant mortality | AC1: Test for significance of eliminating White and Crime | AJ1: AIC/SBC for the two models
B3: Poverty | C3: Infant Mort | D3: White | E3: Crime | G3: Forecast using TREND | M3: SUMMARY OUTPUT | U3: SUMMARY OUTPUT | AD3: complete | AE3: reduced | AF3: difference | AK3: complete | AL3: reduced
A4: Alabama | B4: 15.7 | C4: 9 | D4: 71.027178 | E4: 448 | AC4: SSE | AD4: =O15 -> 280.69844 | AE4: =W15 -> 288.40989 | AF4: =AE4-AD4 -> 7.7114449 | AH4: =AE4-AD4 | AJ4: n | AK4: =N10 -> 50 | AL4: =AK4 -> 50
A5: Alaska | B5: 8.4 | C5: 6.9 | D5: 70.623189 | E5: 661.2 | G5: Infant Mort | H5: White | I5: Crime | J5: Poverty | M5: Regression Statistics | U5: Regression Statistics | AC5: dfE | AD5: =N15 -> 46 | AE5: =V15 -> 48 | AF5: =AE5-AD5 -> 2 | AH5: =AE5-AD5 | AJ5: k | AK5: =N14 -> 3 | AL5: =V14 -> 1
A6: Arizona | B6: 14.7 | C6: 6.4 | D6: 86.505697 | E6: 482.7 | G6: 7 | H6: 80 | I6: 400 | J6: {=TREND(B4:B53,C4:E53,G6:I8)} -> 12.867466 | M6: Multiple R | N6: 0.58034506 | U6: Multiple R | V6: 0.56442957 | AC6: MSE | AD6: =AD4/AD5 -> 6.10214 | AF6: =AF4/AF5 -> 3.8557224 | AH6: =AF4/AF5 | AJ6: SSE | AK6: =O15 -> 280.69844 | AL6: =W15 -> 288.40989
A7: Arkansas | B7: 17.3 | C7: 8.5 | D7: 80.783956 | E7: 529.4 | G7: 7.5 | H7: 70 | I7: 500 | J7: 13.286032 | M7: R Square | N7: 0.33680039 | U7: R Square | V7: 0.31858074 | AC7: F | AF7: =AF6/AD6 -> 0.63186397 | AH7: =AF6/AD6 | AJ7: AIC | AK7: =AK4*LN(AK6/AK4)+2*(AK5+1) -> 94.262896 | AL7: =AL4*LN(AL6/AL4)+2*(AL5+1) -> 91.617984
A8: California | B8: 13.3 | C8: 5 | D8: 76.640052 | E8: 522.6 | G8: 8 | H8: 75 | I8: 450 | J8: 14.036276 | M8: Adjusted R Square | N8: 0.29354824 | U8: Adjusted R Square | V8: 0.3043845 | AC8: α | AF8: 0.05 | AJ8: AICc | AK8: =AK7+2*(AK5+2)*(AK5+3)/(AK4-AK5-3) -> 95.626532 | AL8: =AL7+2*(AL5+2)*(AL5+3)/(AL4-AL5-3) -> 92.139723
A9: Colorado | B9: 11.4 | C9: 5.7 | D9: 89.734092 | E9: 347.8 | M9: Standard Error | N9: 2.470251 | U9: Standard Error | V9: 2.4512322 | AC9: p-value | AF9: =FDIST(AF7,AF5,AD5) -> 0.53615052 | AH9: =FDIST(AF7,AF5,AD5) | AJ9: SBC | AK9: =AK4*LN(AK6/AK4)+LN(AK4)*(AK5+1) -> 101.91099 | AL9: =AL4*LN(AL6/AL4)+LN(AL4)*(AL5+1) -> 95.44203
A10: Connecticut | B10: 9.3 | C10: 6.2 | D10: 84.278652 | E10: 256 | G10: Output from LINEST | M10: Observations | N10: 50 | U10: Observations | V10: 50 | AC10: sig | AF10: =IF(AF9<AF8,"yes","no") -> no | AH10: =IF(AF9<AF8,"yes","no")
A11: Delaware | B11: 10 | C11: 8.3 | D11: 74.266057 | E11: 689.2 | AJ11: AIC/SBC using the Real Statistics functions
A12: Florida | B12: 13.2 | C12: 7.3 | D12: 79.811069 | E12: 722.6 | H12: b3 | I12: b2 | J12: b1 | K12: intercept | M12: ANOVA | U12: ANOVA
A13: Georgia | B13: 14.7 | C13: 8.1 | D13: 65.387718 | E13: 493.2 | G13: Slope (b) | H13: {=LINEST(B4:B53,C4:E53,TRUE,TRUE)} -> 0.001421499 | I13: 0.036326923 | J13: 1.2793697 | K13: 0.43712522 | L13: Intercept (a) | N13: df | O13: SS | P13: MS | Q13: F | R13: Significance F | V13: df | W13: SS | X13: MS | Y13: F | Z13: Significance F | AD13: complete | AE13: reduced | AF13: difference | AJ13: AIC | AK13: =RegAIC(C4:E53,B4:B53) -> #NAME? | AL13: =RegAIC(C4:C53,B4:B53) -> #NAME?
A14: Hawaii | B14: 9.1 | C14: 5.6 | D14: 29.667334 | E14: 272.8 | G14: S.E. of slope (sb) | H14: 0.0022421017 | I14: 0.033602532 | J14: 0.30067291 | K14: 3.9875337 | L14: S.E. of intercept (sa) | M14: Regression | N14: 3 | O14: 142.55036 | P14: 47.516787 | Q14: 7.7869053 | R14: 0.0002622132 | U14: Regression | V14: 1 | W14: 134.83891 | X14: 134.83891 | Y14: 22.441214 | Z14: 1.9607327e-05 | AC14: R-Square | AD14: =N7 -> 0.33680039 | AE14: =V7 -> 0.31858074 | AF14: =AD14-AE14 -> 0.01821965 | AH14: =AD14-AE14 | AJ14: AICc | AK14: =RegAICc(C4:E53,B4:B53) -> #NAME? | AL14: =RegAICc(C4:C53,B4:B53) -> #NAME?
A15: Idaho | B15: 12.6 | C15: 6.8 | D15: 94.60066 | E15: 239.4 | G15: R Square | H15: 0.33680039 | I15: 2.470251 | J15: #N/A | K15: #N/A | L15: S.E. of estimate (sRes) | M15: Residual | N15: 46 | O15: 280.69844 | P15: 6.10214 | U15: Residual | V15: 48 | W15: 288.40989 | X15: 6.0085393 | AC15: dfE | AD15: =N15 -> 46 | AE15: =V15 -> 48 | AF15: =AE15-AD15 -> 2 | AH15: =AE15-AD15 | AJ15: SBC | AK15: =RegSBC(C4:E53,B4:B53) -> #NAME? | AL15: =RegSBC(C4:C53,B4:B53) -> #NAME?
A16: Illinois | B16: 12.2 | C16: 7.3 | D16: 79.13311 | E16: 533.2 | G16: F | H16: 7.7869053 | I16: 46 | J16: #N/A | K16: #N/A | L16: dfRes | M16: Total | N16: 49 | O16: 423.2488 | U16: Total | V16: 49 | W16: 423.2488 | AC16: F | AF16: =AF14*AD15/(AF15*(1-AD14)) -> 0.63186397 | AH16: =AF14*AD15/(AF15*(1-AD14))
A17: Indiana | B17: 13.1 | C17: 8 | D17: 88.000001 | E17: 333.6 | G17: SSReg | H17: 142.55036 | I17: 280.69844 | J17: #N/A | K17: #N/A | L17: SSRes | AC17: α | AF17: 0.05 | AJ17: Augmented versions
A18: Iowa | B18: 11.5 | C18: 5.1 | D18: 94.170465 | E18: 294.7 | N18: Coefficients | O18: Standard Error | P18: t Stat | Q18: P-value | R18: Lower 95% | S18: Upper 95% | V18: Coefficients | W18: Standard Error | X18: t Stat | Y18: P-value | Z18: Lower 95% | AA18: Upper 95% | AC18: p-value | AF18: =FDIST(AF16,AF15,AD15) -> 0.53615052 | AH18: =FDIST(AF16,AF15,AD15)
A19: Kansas | B19: 11.3 | C19: 7.1 | D19: 88.703717 | E19: 452.7 | M19: Intercept | N19: 0.43712522 | O19: 3.9875337 | P19: 0.10962295 | Q19: 0.91318525 | R19: -7.5893638 | S19: 8.4636142 | U19: Intercept | V19: 4.2690992 | W19: 1.8197942 | X19: 2.3459242 | Y19: 0.023158322 | Z19: 0.61015774 | AA19: 7.9280407 | AC19: sig | AF19: =IF(AF18<AF17,"yes","no") -> no | AH19: =IF(AF18<AF17,"yes","no") | AJ19: AIC | AK19: =RegAIC(C4:E53,B4:B53,,TRUE) -> #NAME? | AL19: =RegAIC(C4:C53,B4:B53,,TRUE) -> #NAME?
A20: Kentucky | B20: 17.3 | C20: 7.5 | D20: 89.904327 | E20: 295 | M20: Infant Mort | N20: 1.2793697 | O20: 0.30067291 | P20: 4.2550214 | Q20: 0.00010162763 | R20: 0.67414648 | S20: 1.8845928 | U20: Infant Mort | V20: 1.2390777 | W20: 0.26156244 | X20: 4.7372158 | Y20: 1.9607327e-05 | Z20: 0.71317119 | AA20: 1.7649842 | AJ20: AICc | AK20: =RegAICc(C4:E53,B4:B53,,TRUE) -> #NAME? | AL20: =RegAICc(C4:C53,B4:B53,, TRUE) -> #NAME?
A21: Louisiana | B21: 17.3 | C21: 9.9 | D21: 64.839544 | E21: 729.5 | M21: White | N21: 0.036326923 | O21: 0.033602532 | P21: 1.081077 | Q21: 0.28529815 | R21: -0.031311466 | S21: 0.10396531 | AC21: Using Rsquare Test | AF21: =RSquareTest(C4:E53,C4:C53,B4:B53) -> #NAME? | AH21: =RSquareTest(C4:E53,C4:C53,B4:B53) | AJ21: SBC | AK21: =RegSBC(C4:E53,B4:B53,,TRUE) -> #NAME? | AL21: =RegSBC(C4:C53,B4:B53,,TRUE) -> #NAME?
A22: Maine | B22: 12.3 | C22: 6.3 | D22: 96.389853 | E22: 118 | M22: Crime | N22: 0.001421499 | O22: 0.0022421017 | P22: 0.63400291 | Q22: 0.52921922 | R22: -0.0030916176 | S22: 0.0059346156
A23: Maryland | B23: 8.1 | C23: 8 | D23: 63.398021 | E23: 641.9 | AC23: Alternative form of test
A24: Massachusetts | B24: 10 | C24: 4.8 | D24: 86.20367 | E24: 431.5
A25: Michigan | B25: 14.4 | C25: 7.4 | D25: 81.183409 | E25: 536 | AD25: complete | AE25: reduced | AF25: difference
A26: Minnesota | B26: 9.6 | C26: 5.2 | D26: 89.045557 | E26: 288.7 | AC26: SSReg | AD26: =O14 -> 142.55036 | AE26: =W14 -> 134.83891 | AF26: =AD26-AE26 -> 7.7114449
A27: Mississippi | B27: 21.2 | C27: 10.6 | D27: 60.598179 | E27: 291.3 | AC27: dfReg | AD27: =N14 -> 3 | AE27: =V14 -> 1 | AF27: =AD27-AE27 -> 2
A28: Missouri | B28: 13.4 | C28: 7.4 | D28: 85.028888 | E28: 504.9 | AC28: MSE | AD28: =P15 -> 6.10214
A29: Montana | B29: 14.8 | C29: 5.8 | D29: 90.467729 | E29: 287.5 | AC29: dfE | AD29: =N15 -> 46
A30: Nebraska | B30: 10.8 | C30: 5.6 | D30: 91.372477 | E30: 302.4 | AC30: F | AF30: =AF26/(AF27*AD28) -> 0.63186397
A31: Nevada | B31: 11.3 | C31: 6.4 | D31: 80.891227 | E31: 750.6 | AC31: α | AF31: 0.05
A32: New Hampshire | B32: 7.6 | C32: 6.1 | D32: 95.487187 | E32: 137.3 | AC32: p-value | AF32: =FDIST(AF30,AF27,AD29) -> 0.53615052
A33: New Jersey | B33: 8.7 | C33: 5.5 | D33: 76.032117 | E33: 329.3 | AC33: sig | AF33: =IF(AF32<AF31,"yes","no") -> no
A34: New Mexico | B34: 17.1 | C34: 5.8 | D34: 83.996521 | E34: 664.2
A35: New York | B35: 13.6 | C35: 5.6 | D35: 73.422529 | E35: 414.1
A36: North Carolina | B36: 14.6 | C36: 8.1 | D36: 73.937344 | E36: 466.4
A37: North Dakota | B37: 12 | C37: 5.8 | D37: 91.39351 | E37: 142.4
A38: Ohio | B38: 13.4 | C38: 7.8 | D38: 84.764237 | E38: 343.2
A39: Oklahoma | B39: 15.9 | C39: 8 | D39: 78.141239 | E39: 499.6
A40: Oregon | B40: 13.6 | C40: 5.5 | D40: 90.140446 | E40: 287.6
A41: Pennsylvania | B41: 12.1 | C41: 7.6 | D41: 85.424564 | E41: 416.5
A42: Rhode Island | B42: 11.7 | C42: 6.1 | D42: 88.483881 | E42: 227.3
A43: South Carolina | B43: 15.7 | C43: 8.4 | D43: 68.748136 | E43: 788.3
A44: South Dakota | B44: 12.5 | C44: 6.9 | D44: 88.18979 | E44: 169.2
A45: Tennessee | B45: 15.5 | C45: 8.7 | D45: 80.371971 | E45: 753.3
... A53: Wyoming | B53: 9.4 | C53: 7 | D53: 93.867287 | E53: 239.3
A55: Poverty - % below poverty level
A56: Infant Mort - infant mortality per 1,000 births, death prior to 1 yr, excludes fetal death, residents only
A57: White - % of the population that is white
A58: Crime - violent crime (murder, forcible rape, robbery, and aggravated assault) per 100,000 people

Sheet Mult Reg 4A
A1: Multiple Regression
B3: Poverty | C3: Infant Mort | D3: White | E3: Crime | F3: Doctors | G3: Traf Deaths | H3: University | I3: Unemployed | J3: Income | N3: QQ Tables
A4: Alabama | B4: 15.7 | C4: 9 | D4: 71.027178 | E4: 448 | F4: 218.17341 | G4: 1.81 | H4: 22 | I4: 5 | J4: 42666
A5: Alaska | B5: 8.4 | C5: 6.9 | D5: 70.623189 | E5: 661.2 | F5: 228.45028 | G5: 1.63 | H5: 27.3 | I5: 6.7 | J5: 68460 | N5: Count | O5: =COUNT(B4:B53) -> 50 | P5: =2*O5 -> 100
A6: Arizona | B6: 14.7 | C6: 6.4 | D6: 86.505697 | E6: 482.7 | F6: 209.66657 | G6: 1.69 | H6: 25.1 | I6: 5.5 | J6: 50958 | N6: Mean | O6: =AVERAGE(B4:B53) -> 12.732
A7: Arkansas | B7: 17.3 | C7: 8.5 | D7: 80.783956 | E7: 529.4 | F7: 203.42286 | G7: 1.96 | H7: 18.8 | I7: 5.1 | J7: 38815 | N7: Std Dev | O7: =STDEV(B4:B53) -> 2.9390016
A8: California | B8: 13.3 | C8: 5 | D8: 76.640052 | E8: 522.6 | F8: 268.69056 | G8: 1.21 | H8: 29.6 | I8: 7.2 | J8: 61021
A9: Colorado | B9: 11.4 | C9: 5.7 | D9: 89.734092 | E9: 347.8 | F9: 259.68609 | G9: 1.14 | H9: 35.6 | I9: 4.9 | J9: 56993 | N9: Interval | O9: Data | P9: Std Norm | Q9: Std Data
A10: Connecticut | B10: 9.3 | C10: 6.2 | D10: 84.278652 | E10: 256 | F10: 376.37527 | G10: 0.86 | H10: 35.6 | I10: 5.7 | J10: 68595 | N10: 1 | O10: 7.6 | P10: =NORMSINV(N10/P$5) -> -2.3263479 | Q10: =STANDARDIZE(O10,O$6,O$7) -> -1.7461712
A11: Delaware | B11: 10 | C11: 8.3 | D11: 74.266057 | E11: 689.2 | F11: 250.94176 | G11: 1.23 | H11: 27.5 | I11: 4.8 | J11: 57989 | N11: =N10+2 -> 3 | O11: 8.1 | P11: =NORMSINV(N11/P$5) -> -1.8807936 | Q11: =STANDARDIZE(O11,O$6,O$7) -> -1.5760454
A12: Florida | B12: 13.2 | C12: 7.3 | D12: 79.811069 | E12: 722.6 | F12: 247.8636 | G12: 1.56 | H12: 25.8 | I12: 6.2 | J12: 47778 | N12: =N11+2 -> 5 | O12: 8.4 | P12: =NORMSINV(N12/P$5) -> -1.6448536 | Q12: =STANDARDIZE(O12,O$6,O$7) -> -1.4739699
A13: Georgia | B13: 14.7 | C13: 8.1 | D13: 65.387718 | E13: 493.2 | F13: 217.4457 | G13: 1.46 | H13: 27.5 | I13: 6.2 | J13: 50861 | N13: =N12+2 -> 7 | O13: 8.7 | P13: =NORMSINV(N13/P$5) -> -1.475791 | Q13: =STANDARDIZE(O13,O$6,O$7) -> -1.3718944
A14: Hawaii | B14: 9.1 | C14: 5.6 | D14: 29.667334 | E14: 272.8 | F14: 316.98289 | G14: 1.33 | H14: 29.1 | I14: 3.9 | J14: 67214 | N14: =N13+2 -> 9 | O14: 9.1 | P14: =NORMSINV(N14/P$5) -> -1.340755 | Q14: =STANDARDIZE(O14,O$6,O$7) -> -1.2357938
A15: Idaho | B15: 12.6 | C15: 6.8 | D15: 94.60066 | E15: 239.4 | F15: 168.8339 | G15: 1.6 | H15: 24 | I15: 4.9 | J15: 47576 | N15: =N14+2 -> 11 | O15: 9.3 | P15: =NORMSINV(N15/P$5) -> -1.2265281 | Q15: =STANDARDIZE(O15,O$6,O$7) -> -1.1677435
A16: Illinois | B16: 12.2 | C16: 7.3 | D16: 79.13311 | E16: 533.2 | F16: 280.15387 | G16: 1.16 | H16: 29.9 | I16: 6.5 | J16: 56235 | N16: =N15+2 -> 13 | O16: 9.4 | P16: =NORMSINV(N16/P$5) -> -1.1263911 | Q16: =STANDARDIZE(O16,O$6,O$7) -> -1.1337183
A17: Indiana | B17: 13.1 | C17: 8 | D17: 88.000001 | E17: 333.6 | F17: 216.9397 | G17: 1.26 | H17: 22.9 | I17: 5.9 | J17: 47966 | N17: =N16+2 -> 15 | O17: 9.6 | P17: =NORMSINV(N17/P$5) -> -1.0364334 | Q17: =STANDARDIZE(O17,O$6,O$7) -> -1.065668
A18: Iowa | B18: 11.5 | C18: 5.1 | D18: 94.170465 | E18: 294.7 | F18: 189.28322 | G18: 1.42 | H18: 24.3 | I18: 4.1 | J18: 48980 | N18: =N17+2 -> 17 | O18: 9.6 | P18: =NORMSINV(N18/P$5) -> -0.95416525 | Q18: =STANDARDIZE(O18,O$6,O$7) -> -1.065668
A19: Kansas | B19: 11.3 | C19: 7.1 | D19: 88.703717 | E19: 452.7 | F19: 222.54771 | G19: 1.38 | H19: 29.6 | I19: 4.4 | J19: 50177 | N19: =N18+2 -> 19 | O19: 10 | P19: =NORMSINV(N19/P$5) -> -0.8778963 | Q19: =STANDARDIZE(O19,O$6,O$7) -> -0.92956736
A20: Kentucky | B20: 17.3 | C20: 7.5 | D20: 89.904327 | E20: 295 | F20: 232.34855 | G20: 1.8 | H20: 19.7 | I20: 6.4 | J20: 41538 | N20: =N19+2 -> 21 | O20: 10 | P20: =NORMSINV(N20/P$5) -> -0.80642125 | Q20: =STANDARDIZE(O20,O$6,O$7) -> -0.92956736
A21: Louisiana | B21: 17.3 | C21: 9.9 | D21: 64.839544 | E21: 729.5 | F21: 262.66146 | G21: 2.17 | H21: 20.3 | I21: 4.6 | J21: 43733 | N21: =N20+2 -> 23 | O21: 10.2 | P21: =NORMSINV(N21/P$5) -> -0.73884685 | Q21: =STANDARDIZE(O21,O$6,O$7) -> -0.86151704
A22: Maine | B22: 12.3 | C22: 6.3 | D22: 96.389853 | E22: 118 | F22: 278.39483 | G22: 1.22 | H22: 25.4 | I22: 5.4 | J22: 46581 | N22: =N21+2 -> 25 | O22: 10.4 | P22: =NORMSINV(N22/P$5) -> -0.67448975 | Q22: =STANDARDIZE(O22,O$6,O$7) -> -0.79346672
... A53: Wyoming | B53: 9.4 | C53: 7 | D53: 93.867287 | E53: 239.3 | F53: 184.42357 | G53: 1.6 | H53: 23.6 | I53: 3.1 | J53: 53207 | N53: =N52+2 -> 87 | O53: 15.9 | P53: =NORMSINV(N53/P$5) -> 1.1263911 | Q53: =STANDARDIZE(O53,O$6,O$7) -> 1.0779171
N54: =N53+2 -> 89 | O54: 17 | P54: =NORMSINV(N54/P$5) -> 1.2265281 | Q54: =STANDARDIZE(O54,O$6,O$7) -> 1.4521938
A55: Poverty - % below poverty level | N55: =N54+2 -> 91 | O55: 17.1 | P55: =NORMSINV(N55/P$5) -> 1.340755 | Q55: =STANDARDIZE(O55,O$6,O$7) -> 1.486219
A56: Infant Mort - infant mortality per 1,000 births, death prior to 1 yr, excludes fetal death, residents only | N56: =N55+2 -> 93 | O56: 17.3 | P56: =NORMSINV(N56/P$5) -> 1.475791 | Q56: =STANDARDIZE(O56,O$6,O$7) -> 1.5542693
A57: White - % of the population that is white | N57: =N56+2 -> 95 | O57: 17.3 | P57: =NORMSINV(N57/P$5) -> 1.6448536 | Q57: =STANDARDIZE(O57,O$6,O$7) -> 1.5542693
A58: Crime - violent crime (murder, forcible rape, robbery, and aggravated assault) per 100,000 people | N58: =N57+2 -> 97 | O58: 17.3 | P58: =NORMSINV(N58/P$5) -> 1.8807936 | Q58: =STANDARDIZE(O58,O$6,O$7) -> 1.5542693
A59: Doctors - # doctors per 100,000 residents, excludes some categories of doctors | N59: =N58+2 -> 99 | O59: 21.2 | P59: =NORMSINV(N59/P$5) -> 2.3263479 | Q59: =STANDARDIZE(O59,O$6,O$7) -> 2.8812505
A60: Traf Deaths - # of traffic fatalities per 100 million vehicle miles
A61: University - % of residents 25 yrs or older with at least a bachelor's degree
A62: Unemployment - % of civilian labor force
A63: Income - median household income

Sheet Mult Reg 5
A1: Multiple Regression | E1: Regression data analysis tool output
A3: Color | B3: Quality | C3: Price | E3: SUMMARY OUTPUT
A4: 7 | B4: 5 | C4: 65
A5: 3 | B5: 7 | C5: 38 | E5: Regression Statistics
A6: 5 | B6: 8 | C6: 51 | E6: Multiple R | F6: 0.92233073
A7: 8 | B7: 1 | C7: 38 | E7: R Square | F7: 0.85069397
A8: 9 | B8: 3 | C8: 55 | E8: Adjusted R Square | F8: 0.81336746
A9: 5 | B9: 4 | C9: 43 | E9: Standard Error | F9: 5.8880845
A10: 4 | B10: 0 | C10: 25 | E10: Observations | F10: 11
A11: 2 | B11: 6 | C11: 33
A12: 8 | B12: 7 | C12: 71 | E12: ANOVA
A13: 6 | B13: 4 | C13: 51 | F13: df | G13: SS | H13: MS | I13: F | J13: Significance F
A14: 9 | B14: 2 | C14: 49 | E14: Regression | F14: 2 | G14: 1580.2801 | H14: 790.14003 | I14: 22.790613 | J14: 0.00049694621
E15: Residual | F15: 8 | G15: 277.35631 | H15: 34.669539
E16: Total | F16: 10 | G16: 1857.6364
F18: Coefficients | G18: Standard Error | H18: t Stat | I18: P-value | J18: Lower 95% | K18: Upper 95%
E19: Intercept | F19: 1.7514037 | G19: 6.9602027 | H19: 0.25163113 | I19: 0.80766962 | J19: -14.298852 | K19: 17.80166
E20: Color | F20: 4.8952884 | G20: 0.82022978 | H20: 5.9681915 | I20: 0.00033508361 | J20: 3.0038351 | K20: 6.7867416
E21: Quality | F21: 3.7584155 | G21: 0.75651099 | H21: 4.9680911 | I21: 0.0010957202 | J21: 2.013898 | K21: 5.5029329
E25: RESIDUAL OUTPUT | J25: PROBABILITY OUTPUT
E27: Observation | F27: Predicted Price | G27: Residuals | H27: Standard Residuals | J27: Percentile | K27: Price
E28: 1 | F28: 54.8105 | G28: 10.1895 | H28: 1.9347901 | J28: 4.5454545 | K28: 25
E29: 2 | F29: 42.746177 | G29: -4.7461771 | H29: -0.90120775 | J29: 13.636364 | K29: 33
E30: 3 | F30: 56.295169 | G30: -5.2951693 | H30: -1.0054508 | J30: 22.727273 | K30: 38
E31: 4 | F31: 44.672126 | G31: -6.6721261 | H31: -1.2669084 | J31: 31.818182 | K31: 38
E32: 5 | F32: 57.084245 | G32: -2.0842454 | H32: -0.39575811 | J32: 40.909091 | K32: 43
E33: 6 | F33: 41.261507 | G33: 1.7384926 | H33: 0.3301063 | J33: 50 | K33: 49
E34: 7 | F34: 21.332557 | G34: 3.6674429 | H34: 0.69637686 | J34: 59.090909 | K34: 51
E35: 8 | F35: 34.092473 | G35: -1.0924733 | H35: -0.20743966 | J35: 68.181818 | K35: 51
E36: 9 | F36: 67.222619 | G36: 3.777381 | H36: 0.71725201 | J36: 77.272727 | K36: 55
E37: 10 | F37: 46.156796 | G37: 4.8432042 | H37: 0.91963133 | J37: 86.363636 | K37: 65
E38: 11 | F38: 53.32583 | G38: -4.3258299 | H38: -0.8213919 | J38: 95.454545 | K38: 71 | N38: Problem plots for homogeneity of variances
N40: 1 | O40: -1
N41: =N40+1 -> 2 | O41: 7
N42: =N41+1 -> 3 | O42: 8
N43: =N42+1 -> 4 | O43: 7
N44: =N43+1 -> 5 | O44: 0
N45: =N44+1 -> 6 | O45: -7
N46: =N45+1 -> 7 | O46: -4
N47: =N46+1 -> 8 | O47: 1
N48: =N47+1 -> 9 | O48: 8
N49: =N48+1 -> 10 | O49: 5
N50: =N49+1 -> 11 | O50: 6
N51: =N50+1 -> 12 | O51: -2
N52: =N51+1 -> 13 | O52: -1
... N59: =N58+1 -> 20 | O59: -3
N61: 1 | O61: =INT(O40*0.3) -> -1
N62: =N61+1 -> 2 | O62: 1
N63: =N62+1 -> 3 | O63: -2
N64: =N63+1 -> 4 | O64: 1
N65: =N64+1 -> 5 | O65: =INT(O44*0.3) -> 0
N66: =N65+1 -> 6 | O66: =INT(O45*0.3) -> -3
N67: =N66+1 -> 7 | O67: -1
N68: =N67+1 -> 8 | O68: =INT(O47*0.6) -> 0
N69: =N68+1 -> 9 | O69: =INT(O48*0.6) -> 4
N70: =N69+1 -> 10 | O70: =INT(O49*0.6) -> 3
N71: =N70+1 -> 11 | O71: =INT(O50*0.6) -> 3
N72: =N71+1 -> 12 | O72: =INT(O51*0.6) -> -2
N73: =N72+1 -> 13 | O73: =INT(O52*0.6) -> -1
N74: =N73+1 -> 14 | O74: =INT(O53*0.6) -> 4
N75: =N74+1 -> 15 | O75: =INT(O54) -> 0
N76: =N75+1 -> 16 | O76: =INT(O55) -> -4
N77: =N76+1 -> 17 | O77: 8
N78: =N77+1 -> 18 | O78: =INT(O57) -> 5
N79: =N78+1 -> 19 | O79: =INT(O58) -> -8
N80: =N79+1 -> 20 | O80: =INT(O59) -> -3
N82: 1 | O82: =INT(O61*0.3) -> -1
N83: =N82+1 -> 2 | O83: 1
N84: =N83+1 -> 3 | O84: 3
N85: =N84+1 -> 4 | O85: 6
N86: =N85+1 -> 5 | O86: 6
N87: =N86+1 -> 6 | O87: 4
N88: =N87+1 -> 7 | O88: 3
N89: =N88+1 -> 8 | O89: 1
N90: =N89+1 -> 9 | O90: =INT(O69*0.6) -> 2
N91: =N90+1 -> 10 | O91: =INT(O70*0.6) -> 1
N92: =N91+1 -> 11 | O92: =INT(O71*0.6) -> 1
N93: =N92+1 -> 12 | O93: =INT(O72*0.6) -> -2
N94: =N93+1 -> 13 | O94: =INT(O73*0.6) -> -1
N95: =N94+1 -> 14 | O95: =INT(O74*0.6) -> 2
N96: =N95+1 -> 15 | O96: =INT(O75) -> 0
N97: =N96+1 -> 16 | O97: 6
N98: =N97+1 -> 17 | O98: 8
N99: =N98+1 -> 18 | O99: -3
N100: =N99+1 -> 19 | O100: 6
N101: =N100+1 -> 20 | O101: 4

Sheet Mult Reg 5A
A1: SUMMARY OUTPUT
A3: Regression Statistics
A4: Multiple R | B4: 0.58034506
A5: R Square | B5: 0.33680039
A6: Adjusted R Square | B6: 0.29354824
A7: Standard Error | B7: 2.470251
A8: Observations | B8: 50
A10: ANOVA
B11: df | C11: SS | D11: MS | E11: F | F11: Significance F
A12: Regression | B12: 3 | C12: 142.55036 | D12: 47.516787 | E12: 7.7869053 | F12: 0.0002622132
A13: Residual | B13: 46 | C13: 280.69844 | D13: 6.10214
A14: Total | B14: 49 | C14: 423.2488
B16: Coefficients | C16: Standard Error | D16: t Stat | E16: P-value | F16: Lower 95% | G16: Upper 95%
A17: Intercept | B17: 0.43712522 | C17: 3.9875337 | D17: 0.10962295 | E17: 0.91318525 | F17: -7.5893638 | G17: 8.4636142
A18: Infant Mort | B18: 1.2793697 | C18: 0.30067291 | D18: 4.2550214 | E18: 0.00010162763 | F18: 0.67414648 | G18: 1.8845928
A19: White | B19: 0.036326923 | C19: 0.033602532 | D19: 1.081077 | E19: 0.28529815 | F19: -0.031311466 | G19: 0.10396531
A20: Crime | B20: 0.001421499 | C20: 0.0022421017 | D20: 0.63400291 | E20: 0.52921922 | F20: -0.0030916176 | G20: 0.0059346156
A24: RESIDUAL OUTPUT | F24: PROBABILITY OUTPUT
A26: Observation | B26: Predicted Poverty | C26: Residuals | D26: Standard Residuals | F26: Percentile | G26: Poverty
A27: 1 | B27: 15.168482 | C27: 0.53151753 | D27: 0.22207294 | F27: 1 | G27: 7.6
A28: 2 | B28: 12.770194 | C28: -4.3701941 | D28: -1.8259075 | F28: 3 | G28: 8.1
A29: 3 | B29: 12.453734 | C29: 2.2462656 | D29: 0.93851054 | F29: 5 | G29: 8.4
A30: 4 | B30: 14.998941 | C30: 2.3010586 | D30: 0.96140355 | F30: 7 | G30: 8.7
A31: 5 | B31: 10.360946 | C31: 2.9390539 | D31: 1.2279639 | F31: 9 | G31: 9.1
A32: 6 | B32: 11.483693 | C32: -0.083693053 | D32: -0.034967731 | F32: 11 | G32: 9.3
A33: 7 | B33: 11.794705 | C33: -2.4947049 | D33: -1.0423108 | F33: 13 | G33: 9.4
A34: 8 | B34: 14.733448 | C34: -4.7334478 | D34: -1.9776782 | F34: 15 | G34: 9.6
A35: 9 | B35: 13.702989 | C35: -0.5029894 | D35: -0.21015362 | F35: 17 | G35: 9.6
A36: 10 | B36: 13.876437 | C36: 0.82356268 | D36: 0.3440921 | F36: 19 | G36: 10
A37: 11 | B37: 9.0671032 | C37: 0.032896849 | D37: 0.013744608 | F37: 21 | G37: 10
A38: 12 | B38: 12.913697 | C38: -0.31369663 | D38: -0.13106535 | F38: 23 | G38: 10.2
... A76: 50 | B76: 13.142787 | C76: -3.7427872 | D76: -1.5637711 | F76: 99 | G76: 21.2

Sheet Mult Reg 5B
A1: SUMMARY OUTPUT
A3: Regression Statistics
A4: Multiple R | B4: 0.56442957
A5: R Square | B5: 0.31858074
A6: Adjusted R Square | B6: 0.3043845
A7: Standard Error | B7: 2.4512322
A8: Observations | B8: 50
A10: ANOVA
B11: df | C11: SS | D11: MS | E11: F | F11: Significance F
A12: Regression | B12: 1 | C12: 134.83891 | D12: 134.83891 | E12: 22.441214 | F12: 1.9607327e-05
A13: Residual | B13: 48 | C13: 288.40989 | D13: 6.0085393
A14: Total | B14: 49 | C14: 423.2488
B16: Coefficients | C16: Standard Error | D16: t Stat | E16: P-value | F16: Lower 95% | G16: Upper 95%
A17: Intercept | B17: 4.2690992 | C17: 1.8197942 | D17: 2.3459242 | E17: 0.023158322 | F17: 0.61015774 | G17: 7.9280407
A18: Infant Mort | B18: 1.2390777 | C18: 0.26156244 | D18: 4.7372158 | E18: 1.9607327e-05 | F18: 0.71317119 | G18: 1.7649842
A22: RESIDUAL OUTPUT | F22: PROBABILITY OUTPUT
A24: Observation | B24: Predicted Poverty | C24: Residuals | D24: Standard Residuals | F24: Percentile | G24: Poverty
A25: 1 | B25: 15.420799 | C25: 0.27920137 | D25: 0.11508282 | F25: 1 | G25: 7.6
A26: 2 | B26: 12.818735 | C26: -4.4187354 | D26: -1.8213398 | F26: 3 | G26: 8.1
A27: 3 | B27: 12.199197 | C27: 2.5008034 | D27: 1.0307955 | F27: 5 | G27: 8.4
A28: 4 | B28: 14.80126 | C28: 2.4987402 | D28: 1.0299451 | F28: 7 | G28: 8.7
A29: 5 | B29: 10.464488 | C29: 2.8355122 | D29: 1.1687577 | F29: 9 | G29: 9.1
A30: 6 | B30: 11.331842 | C30: 0.068157814 | D30: 0.028093679 | F30: 11 | G30: 9.3
A31: 7 | B31: 11.951381 | C31: -2.651381 | D31: -1.0928615 | F31: 13 | G31: 9.4
A32: 8 | B32: 14.553444 | C32: -4.5534442 | D32: -1.8768648 | F32: 15 | G32: 9.6
A33: 9 | B33: 13.314367 | C33: -0.11436652 | D33: -0.047140251 | F33: 17 | G33: 9.6
A34: 10 | B34: 14.305629 | C34: 0.39437131 | D34: 0.16255423 | F34: 19 | G34: 10
A35: 11 | B35: 11.207934 | C35: -2.1079344 | D35: -0.86886052 | F35: 21 | G35: 10
A36: 12 | B36: 12.694828 | C36: -0.094827669 | D36: -0.039086613 | F36: 23 | G36: 10.2
... A74: 50 | B74: 12.942643 | C74: -3.5426432 | D74: -1.460227 | F74: 99 | G74: 21.2

Sheet Mult Reg 5C
A1: SUMMARY OUTPUT
A3: Regression Statistics
A4: Multiple R | B4: 0.92233073
A5: R Square | B5: 0.85069397
A6: Adjusted R Square | B6: 0.81336746
A7: Standard Error | B7: 5.8880845
A8: Observations | B8: 11
A10: ANOVA
B11: df | C11: SS | D11: MS | E11: F | F11: Significance F
A12: Regression | B12: 2 | C12: 1580.2801 | D12: 790.14003 | E12: 22.790613 | F12: 0.00049694621
A13: Residual | B13: 8 | C13: 277.35631 | D13: 34.669539
A14: Total | B14: 10 | C14: 1857.6364
B16: Coefficients | C16: Standard Error | D16: t Stat | E16: P-value | F16: Lower 95% | G16: Upper 95%
A17: Intercept | B17: 1.7514037 | C17: 6.9602027 | D17: 0.25163113 | E17: 0.80766962 | F17: -14.298852 | G17: 17.80166
A18: Color | B18: 4.8952884 | C18: 0.82022978 | D18: 5.9681915 | E18: 0.00033508361 | F18: 3.0038351 | G18: 6.7867416
A19: Quality | B19: 3.7584155 | C19: 0.75651099 | D19: 4.9680911 | E19: 0.0010957202 | F19: 2.013898 | G19: 5.5029329
A23: RESIDUAL OUTPUT | F23: PROBABILITY OUTPUT
A25: Observation | B25: Predicted Price | C25: Residuals | D25: Standard Residuals | F25: Percentile | G25: Price
A26: 1 | B26: 54.8105 | C26: 10.1895 | D26: 1.9347901 | F26: 4.5454545 | G26: 25
A27: 2 | B27: 42.746177 | C27: -4.7461771 | D27: -0.90120775 | F27: 13.636364 | G27: 33
A28: 3 | B28: 56.295169 | C28: -5.2951693 | D28: -1.0054508 | F28: 22.727273 | G28: 38
A29: 4 | B29: 44.672126 | C29: -6.6721261 | D29: -1.2669084 | F29: 31.818182 | G29: 38
A30: 5 | B30: 57.084245 | C30: -2.0842454 | D30: -0.39575811 | F30: 40.909091 | G30: 43
A31: 6 | B31: 41.261507 | C31: 1.7384926 | D31: 0.3301063 | F31: 50 | G31: 49
A32: 7 | B32: 21.332557 | C32: 3.6674429 | D32: 0.69637686 | F32: 59.090909 | G32: 51
A33: 8 | B33: 34.092473 | C33: -1.0924733 | D33: -0.20743966 | F33: 68.181818 | G33: 51
A34: 9 | B34: 67.222619 | C34: 3.777381 | D34: 0.71725201 | F34: 77.272727 | G34: 55
A35: 10 | B35: 46.156796 | C35: 4.8432042 | D35: 0.91963133 | F35: 86.363636 | G35: 65
A36: 11 | B36: 53.32583 | C36: -4.3258299 | D36: -0.8213919 | F36: 95.454545 | G36: 71

Sheet Mult Reg 6
A1: Multiple Regression | E1: Regression data analysis (formulas inserted)
A3: Color | B3: Quality | C3: Price | E3: SUMMARY OUTPUT | N3: Alternative derivations of Multiple R
A4: 7 | B4: 5 | C4: 65
A5: 3 | B5: 7 | C5: 38 | E5: Regression Statistics | N5: Price | O5: Predicted Price | Q5: Pairwise Correlations
A6: 5 | B6: 8 | C6: 51 | E6: Multiple R | F6: =SQRT(F7) -> 0.92233073 | N6: =C4 -> 65 | O6: =F26 -> 54.8105 | Q6: Price - Color | R6: =CORREL(C4:C14,A4:A14) -> 0.62453893
A7: 8 | B7: 1 | C7: 38 | E7: R Square | F7: =G14/G16 -> 0.85069397 | N7: =C5 -> 38 | O7: =F27 -> 42.746177 | Q7: Price - Quality | R7: =CORREL(C4:C14,B4:B14) -> 0.43118646
A8: 9 | B8: 3 | C8: 55 | E8: Adjusted R Square | F8: =1-(1-F7)*(F10-1)/(F10-F14-1) -> 0.81336746 | N8: =C6 -> 51 | O8: =F28 -> 56.295169 | Q8: Color - Quality | R8: =CORREL(A4:A14,B4:B14) -> -0.33394197
A9: 5 | B9: 4 | C9: 43 | E9: Standard Error | F9: =SQRT(H15) -> 5.8880845 | N9: =C7 -> 38 | O9: =F29 -> 44.672126
A10: 4 | B10: 0 | C10: 25 | E10: Observations | F10: =COUNT(A4:A14) -> 11 | N10: =C8 -> 55 | O10: =F30 -> 57.084245 | Q10: Multiple R | R10: =SQRT((R6^2+R7^2-2*R6*R7*R8)/(1-R8^2)) -> 0.92233073
A11: 2 | B11: 6 | C11: 33 | N11: =C9 -> 43 | O11: =F31 -> 41.261507
A12: 8 | B12: 7 | C12: 71 | E12: ANOVA | N12: =C10 -> 25 | O12: =F32 -> 21.332557
A13: 6 | B13: 4 | C13: 51 | F13: df | G13: SS | H13: MS | I13: F | J13: Significance F | N13: =C11 -> 33 | O13: =F33 -> 34.092473
A14: 9 | B14: 2 | C14: 49 | E14: Regression | F14: =COUNT(A4:B4) -> 2 | G14: =DEVSQ('Mult Reg 2'!M4:M14) -> 1580.2801 | H14: =G14/F14 -> 790.14003 | I14: =H14/H15 -> 22.790613 | J14: =FDIST(I14,F14,F15) -> 0.00049694621 | N14: =C12 -> 71 | O14: =F34 -> 67.222619
E15: Residual | F15: =F16-F14 -> 8 | G15: =G16-G14 -> 277.35631 | H15: =G15/F15 -> 34.669539 | N15: =C13 -> 51 | O15: =F35 -> 46.156796
E16: Total | F16: =F10-1 -> 10 | G16: =DEVSQ(C4:C14) -> 1857.6364 | N16: =C14 -> 49 | O16: =F36 -> 53.32583
N17: Multiple R | O17: =CORREL(N6:N16,O6:O16) -> 0.92233073
F18: Coefficients | G18: Standard Error | H18: t Stat | I18: P-value | J18: Lower 95% | K18: Upper 95%
E19: Intercept | F19: ='Mult Reg 2'!K4 -> 1.7514037 | G19: =SQRT($H$15*'Mult Reg 2'!E17) -> 6.9602027 | H19: =F19/G19 -> 0.25163113 | I19: =TDIST(ABS(H19),$F$15,2) -> 0.80766962 | J19: =F19-TINV(0.05,$F$15)*G19 -> -14.298852 | K19: =F19+TINV(0.05,$F$15)*G19 -> 17.80166 | N19: SSRes = SST (1 – r2) | O19: =G16*(1-F7) -> 277.35631
E20: Color | F20: ='Mult Reg 2'!K5 -> 4.8952884 | G20: =SQRT($H$15*'Mult Reg 2'!F18) -> 0.82022978 | H20: =F20/G20 -> 5.9681915 | I20: =TDIST(ABS(H20),$F$15,2) -> 0.00033508361 | J20: =F20-TINV(0.05,$F$15)*G20 -> 3.0038351 | K20: =F20+TINV(0.05,$F$15)*G20 -> 6.7867416
E21: Quality | F21: ='Mult Reg 2'!K6 -> 3.7584155 | G21: =SQRT($H$15*'Mult Reg 2'!G19) -> 0.75651099 | H21: =F21/G21 -> 4.9680911 | I21: =TDIST(ABS(H21),$F$15,2) -> 0.0010957202 | J21: =F21-TINV(0.05,$F$15)*G21 -> 2.013898 | K21: =F21+TINV(0.05,$F$15)*G21 -> 5.5029329
E23: RESIDUAL OUTPUT | J23: PROBABILITY OUTPUT | AC23: QQ Tables
E25: Observation | F25: Predicted Price | G25: Residuals | H25: Std Residuals | J25: Percentile | K25: Price | AC25: Count | AD25: =COUNT(C4:C14) -> 11 | AE25: =2*AD25 -> 22
E26: 1 | F26: =$F$19+A4*$F$20+B4*$F$21 -> 54.8105 | G26: =C4-F26 -> 10.1895 | H26: =G26/STDEV($G$26:$G$36) -> 1.9347901 | J26: =100/(2*$E$36) -> 4.5454545 | K26: {=QSORT(C4:C14)} -> #NAME? | AC26: Mean | AD26: =AVERAGE(C4:C14) -> 47.181818
E27: 2 | F27: =$F$19+A5*$F$20+B5*$F$21 -> 42.746177 | G27: =C5-F27 -> -4.7461771 | H27: =G27/STDEV($G$26:$G$36) -> -0.90120775 | J27: =J26+100/$E$36 -> 13.636364 | K27: #NAME? | AC27: Std Dev | AD27: =STDEV(C4:C14) -> 13.629513 | AP27: QQ Table reversing axes
E28: 3 | F28: =$F$19+A6*$F$20+B6*$F$21 -> 56.295169 | G28: =C6-F28 -> -5.2951693 | H28: =G28/STDEV($G$26:$G$36) -> -1.0054508 | J28: =J27+100/$E$36 -> 22.727273 | K28: #NAME?
E29: 4 | F29: =$F$19+A7*$F$20+B7*$F$21 -> 44.672126 | G29: =C7-F29 -> -6.6721261 | H29: =G29/STDEV($G$26:$G$36) -> -1.2669084 | J29: =J28+100/$E$36 -> 31.818182 | K29: #NAME? | AC29: Interval | AD29: Data | AE29: Std Norm | AF29: Std Data | AP29: Std Norm | AQ29: Data
E30: 5 | F30: =$F$19+A8*$F$20+B8*$F$21 -> 57.084245 | G30: =C8-F30 -> -2.0842454 | H30: =G30/STDEV($G$26:$G$36) -> -0.39575811 | J30: =J29+100/$E$36 -> 40.909091 | K30: #NAME? | AC30: 1 | AD30: 25 | AE30: =NORMSINV(AC30/AE$25) -> -1.6906216 | AF30: =STANDARDIZE(AD30,AD$26,AD$27) -> -1.6274842 | AP30: =AE30 -> -1.6906216 | AQ30: =AD30 -> 25
E31: 6 | F31: =$F$19+A9*$F$20+B9*$F$21 -> 41.261507 | G31: =C9-F31 -> 1.7384926 | H31: =G31/STDEV($G$26:$G$36) -> 0.3301063 | J31: =J30+100/$E$36 -> 50 | K31: #NAME? | AC31: =AC30+2 -> 3 | AD31: 33 | AE31: =NORMSINV(AC31/AE$25) -> -1.0968036 | AF31: =STANDARDIZE(AD31,AD$26,AD$27) -> -1.0405227 | AP31: =AE31 -> -1.0968036 | AQ31: =AD31 -> 33
E32: 7 | F32: =$F$19+A10*$F$20+B10*$F$21 -> 21.332557 | G32: =C10-F32 -> 3.6674429 | H32: =G32/STDEV($G$26:$G$36) -> 0.69637686 | J32: =J31+100/$E$36 -> 59.090909 | K32: #NAME? | AC32: =AC31+2 -> 5 | AD32: 38 | AE32: =NORMSINV(AC32/AE$25) -> -0.74785859 | AF32: =STANDARDIZE(AD32,AD$26,AD$27) -> -0.67367175 | AP32: =AE32 -> -0.74785859 | AQ32: =AD32 -> 38
E33: 8 | F33: =$F$19+A11*$F$20+B11*$F$21 -> 34.092473 | G33: =C11-F33 -> -1.0924733 | H33: =G33/STDEV($G$26:$G$36) -> -0.20743966 | J33: =J32+100/$E$36 -> 68.181818 | K33: #NAME? | AC33: =AC32+2 -> 7 | AD33: 38 | AE33: =NORMSINV(AC33/AE$25) -> -0.47278912 | AF33: =STANDARDIZE(AD33,AD$26,AD$27) -> -0.67367175 | AP33: =AE33 -> -0.47278912 | AQ33: =AD33 -> 38
E34: 9 | F34: =$F$19+A12*$F$20+B12*$F$21 -> 67.222619 | G34: =C12-F34 -> 3.777381 | H34: =G34/STDEV($G$26:$G$36) -> 0.71725201 | J34: =J33+100/$E$36 -> 77.272727 | K34: #NAME? | AC34: =AC33+2 -> 9 | AD34: 43 | AE34: =NORMSINV(AC34/AE$25) -> -0.22988412 | AF34: =STANDARDIZE(AD34,AD$26,AD$27) -> -0.3068208 | AP34: =AE34 -> -0.22988412 | AQ34: =AD34 -> 43
E35: 10 | F35: =$F$19+A13*$F$20+B13*$F$21 -> 46.156796 | G35: =C13-F35 -> 4.8432042 | H35: =G35/STDEV($G$26:$G$36) -> 0.91963133 | J35: =J34+100/$E$36 -> 86.363636 | K35: #NAME? | AC35: =AC34+2 -> 11 | AD35: 49 | AE35: =NORMSINV(AC35/AE$25) -> 0 | AF35: =STANDARDIZE(AD35,AD$26,AD$27) -> 0.13340035 | AP35: =AE35 -> 0 | AQ35: =AD35 -> 49
E36: 11 | F36: =$F$19+A14*$F$20+B14*$F$21 -> 53.32583 | G36: =C14-F36 -> -4.3258299 | H36: =G36/STDEV($G$26:$G$36) -> -0.8213919 | J36: =J35+100/$E$36 -> 95.454545 | K36: #NAME? | AC36: =AC35+2 -> 13 | AD36: 51 | AE36: =NORMSINV(AC36/AE$25) -> 0.22988412 | AF36: =STANDARDIZE(AD36,AD$26,AD$27) -> 0.28014073 | AP36: =AE36 -> 0.22988412 | AQ36: =AD36 -> 51
AC37: =AC36+2 -> 15 | AD37: 51 | AE37: =NORMSINV(AC37/AE$25) -> 0.47278912 | AF37: =STANDARDIZE(AD37,AD$26,AD$27) -> 0.28014073 | AP37: =AE37 -> 0.47278912 | AQ37: =AD37 -> 51
AC38: =AC37+2 -> 17 | AD38: 55 | AE38: =NORMSINV(AC38/AE$25) -> 0.74785859 | AF38: =STANDARDIZE(AD38,AD$26,AD$27) -> 0.57362149 | AP38: =AE38 -> 0.74785859 | AQ38: =AD38 -> 55
F39: Residual Plots | AC39: =AC38+2 -> 19 | AD39: 65 | AE39: =NORMSINV(AC39/AE$25) -> 1.0968036 | AF39: =STANDARDIZE(AD39,AD$26,AD$27) -> 1.3073234 | AP39: =AE39 -> 1.0968036 | AQ39: =AD39 -> 65
AC40: =AC39+2 -> 21 | AD40: 71 | AE40: =NORMSINV(AC40/AE$25) -> 1.6906216 | AF40: =STANDARDIZE(AD40,AD$26,AD$27) -> 1.7475445 | AP40: =AE40 -> 1.6906216 | AQ40: =AD40 -> 71
F41: Color | G41: Residuals | I41: Quality | J41: Residuals
F42: =A4 -> 7 | G42: =G26 -> 10.1895 | I42: =B4 -> 5 | J42: =G42 -> 10.1895
F43: =A5 -> 3 | G43: =G27 -> -4.7461771 | I43: =B5 -> 7 | J43: =G43 -> -4.7461771
F44: =A6 -> 5 | G44: =G28 -> -5.2951693 | I44: =B6 -> 8 | J44: =G44 -> -5.2951693
F45: =A7 -> 8 | G45: =G29 -> -6.6721261 | I45: =B7 -> 1 | J45: =G45 -> -6.6721261
F46: =A8 -> 9 | G46: =G30 -> -2.0842454 | I46: =B8 -> 3 | J46: =G46 -> -2.0842454
F47: =A9 -> 5 | G47: =G31 -> 1.7384926 | I47: =B9 -> 4 | J47: =G47 -> 1.7384926
F48: =A10 -> 4 | G48: =G32 -> 3.6674429 | I48: =B10 -> 0 | J48: =G48 -> 3.6674429
F49: =A11 -> 2 | G49: =G33 -> -1.0924733 | I49: =B11 -> 6 | J49: =G49 -> -1.0924733
F50: =A12 -> 8 | G50: =G34 -> 3.777381 | I50: =B12 -> 7 | J50: =G50 -> 3.777381
F51: =A13 -> 6 | G51: =G35 -> 4.8432042 | I51: =B13 -> 4 | J51: =G51 -> 4.8432042
F52: =A14 -> 9 | G52: =G36 -> -4.3258299 | I52: =B14 -> 2 | J52: =G52 -> -4.3258299
F55: Fit Plots
F57: Color | G57: Price | H57: Pred Price | J57: Quality | K57: Price | L57: Pred Price
F58: =A4 -> 7 | G58: =C4 -> 65 | H58: =F26 -> 54.8105 | J58: =B4 -> 5 | K58: =C4 -> 65 | L58: =H58 -> 54.8105
F59: =A5 -> 3 | G59: =C5 -> 38 | H59: =F27 -> 42.746177 | J59: =B5 -> 7 | K59: =C5 -> 38 | L59: =H59 -> 42.746177
F60: =A6 -> 5 | G60: =C6 -> 51 | H60: =F28 -> 56.295169 | J60: =B6 -> 8 | K60: =C6 -> 51 | L60: =H60 -> 56.295169
F61: =A7 -> 8 | G61: =C7 -> 38 | H61: =F29 -> 44.672126 | J61: =B7 -> 1 | K61: =C7 -> 38 | L61: =H61 -> 44.672126
F62: =A8 -> 9 | G62: =C8 -> 55 | H62: =F30 -> 57.084245 | J62: =B8 -> 3 | K62: =C8 -> 55 | L62: =H62 -> 57.084245
F63: =A9 -> 5 | G63: =C9 -> 43 | H63: =F31 -> 41.261507 | J63: =B9 -> 4 | K63: =C9 -> 43 | L63: =H63 -> 41.261507
F64: =A10 -> 4 | G64: =C10 -> 25 | H64: =F32 -> 21.332557 | J64: =B10 -> 0 | K64: =C10 -> 25 | L64: =H64 -> 21.332557
F65: =A11 -> 2 | G65: =C11 -> 33 | H65: =F33 -> 34.092473 | J65: =B11 -> 6 | K65: =C11 -> 33 | L65: =H65 -> 34.092473
F66: =A12 -> 8 | G66: =C12 -> 71 | H66: =F34 -> 67.222619 | J66: =B12 -> 7 | K66: =C12 -> 71 | L66: =H66 -> 67.222619
F67: =A13 -> 6 | G67: =C13 -> 51 | H67: =F35 -> 46.156796 | J67: =B13 -> 4 | K67: =C13 -> 51 | L67: =H67 -> 46.156796
F68: =A14 -> 9 | G68: =C14 -> 49 | H68: =F36 -> 53.32583 | J68: =B14 -> 2 | K68: =C14 -> 49 | L68: =H68 -> 53.32583

Sheet Mult Reg 6A
A1: Multiple Regression | E1: Regression data analysis (Real Statistics formulas inserted)
A3: Color | B3: Quality | C3: Price | E3: SUMMARY OUTPUT
A4: 7 | B4: 5 | C4: 65
A5: 3 | B5: 7 | C5: 38 | E5: Regression Statistics
A6: 5 | B6: 8 | C6: 51 | E6: Multiple R | F6: =MultipleR(A4:B14,C4:C14) -> #NAME?
A7: 8 | B7: 1 | C7: 38 | E7: R Square | F7: =RSquare(A4:B14,C4:C14) -> #NAME?
A8: 9 | B8: 3 | C8: 55 | E8: Adjusted R Square | F8: =AdjRSquare(A4:B14,C4:C14) -> #NAME?
A9: 5 | B9: 4 | C9: 43 | E9: Standard Error | F9: =RegSE(A4:B14,C4:C14) -> #NAME?
A10: 4 | B10: 0 | C10: 25 | E10: Observations | F10: =COUNT(A4:A14) -> 11
A11: 2 | B11: 6 | C11: 33
A12: 8 | B12: 7 | C12: 71 | E12: ANOVA
A13: 6 | B13: 4 | C13: 51 | F13: df | G13: SS | H13: MS | I13: F | J13: Significance F
A14: 9 | B14: 2 | C14: 49 | E14: Regression | F14: =dfReg(A4:B14) -> #NAME? | G14: =SSReg(A4:B14,C4:C14) -> #NAME? | H14: =MSReg(A4:B14,C4:C14) -> #NAME? | I14: =RegF(A4:B14,C4:C14) -> #NAME? | J14: =RegTEST(A4:B14,C4:C14) -> #NAME?
E15: Residual | F15: =dfRes(A4:B14) -> #NAME? | G15: =SSRes(A4:B14,C4:C14) -> #NAME? | H15: =MSRes(A4:B14,C4:C14) -> #NAME?
E16: Total | F16: =dfRegTot(A4:B14) -> #NAME? | G16: =SSRegTot(C4:C14) -> #NAME?
F18: Coefficients | G18: Standard Error | H18: t Stat | I18: P-value | J18: Lower 95% | K18: Upper 95%
E19: Intercept | F19: {=RegCoeff(A4:B14,C4:C14)} -> #NAME? | G19: {=RegCoeffSE(A4:B14,C4:C14)} -> #NAME? | H19: =F19/G19 -> #NAME? | I19: =TDIST(ABS(H19),$F$15,2) -> #NAME? | J19: =F19-TINV(0.05,$F$15)*G19 -> #NAME? | K19: =F19+TINV(0.05,$F$15)*G19 -> #NAME?
E20: Color | F20: #NAME? | G20: #NAME? | H20: =F20/G20 -> #NAME? | I20: =TDIST(ABS(H20),$F$15,2) -> #NAME? | J20: =F20-TINV(0.05,$F$15)*G20 -> #NAME? | K20: =F20+TINV(0.05,$F$15)*G20 -> #NAME?
E21: Quality | F21: #NAME? | G21: #NAME? | H21: =F21/G21 -> #NAME? | I21: =TDIST(ABS(H21),$F$15,2) -> #NAME? | J21: =F21-TINV(0.05,$F$15)*G21 -> #NAME? | K21: =F21+TINV(0.05,$F$15)*G21 -> #NAME?

Sheet Mult Reg 6B
A1: Multiple Regression (Real Statistics data analysis tool)
A3: Color | B3: Quality | C3: Price | E3: Regression Analysis
A4: 7 | B4: 5 | C4: 65
A5: 3 | B5: 7 | C5: 38 | E5: OVERALL FIT
A6: 5 | B6: 8 | C6: 51 | E6: Multiple R | F6: =SQRT(F7) -> #NAME? | H6: AIC | I6: =F10*LN(G15/F10)+2*(F14+1) -> #NAME?
A7: 8 | B7: 1 | C7: 38 | E7: R Square | F7: =G14/G16 -> #NAME? | H7: AICc | I7: =I6+2*(F14+2)*(F14+3)/(F10-F14-3) -> #NAME?
A8: 9 | B8: 3 | C8: 55 | E8: Adjusted R Square | F8: =1-(1-F7)*(F10-1)/(F10-F14-1) -> #NAME? | H8: SBC | I8: =F10*LN(G15/F10)+(F14+1)*LN(F10) -> #NAME?
A9: 5 | B9: 4 | C9: 43 | E9: Standard Error | F9: =SQRT(H15) -> #NAME?
A10: 4 | B10: 0 | C10: 25 | E10: Observations | F10: =COUNT(C4:C14) -> 11
A11: 2 | B11: 6 | C11: 33
A12: 8 | B12: 7 | C12: 71 | E12: ANOVA | I12: Alpha | J12: 0.05
A13: 6 | B13: 4 | C13: 51 | F13: df | G13: SS | H13: MS | I13: F | J13: p-value | K13: sig
A14: 9 | B14: 2 | C14: 49 | E14: Regression | F14: =COUNT(A4:B4) -> 2 | G14: =DEVSQ(MMULT(DESIGN(A4:B14),F19:F21)) -> #NAME? | H14: =G14/F14 -> #NAME? | I14: =H14/H15 -> #NAME? | J14: =FDIST(I14,F14,F15) -> #NAME? | K14: =IF(J14<J12,"yes","no") -> #NAME?
E15: Residual | F15: =F16-F14 -> 8 | G15: =G16-G14 -> #NAME? | H15: =G15/F15 -> #NAME?
E16: Total | F16: =F10-1 -> 10 | G16: =DEVSQ(C4:C14) -> 1857.6364
F18: coeff | G18: std err | H18: t stat | I18: p-value | J18: lower | K18: upper | L18: vif
E19: Intercept | F19: {=RegCoeff(A4:B14,C4:C14)} -> #NAME? | G19: #NAME? | H19: =F19/G19 -> #NAME? | I19: =TDIST(ABS(H19),$F$15,2) -> #NAME? | J19: =F19-TINV(J$12,$F$15)*G19 -> #NAME? | K19: =F19+TINV(J$12,$F$15)*G19 -> #NAME?
E20: {=TRANSPOSE(A3:B3)} -> Color | F20: #NAME? | G20: #NAME? | H20: =F20/G20 -> #NAME? | I20: =TDIST(ABS(H20),$F$15,2) -> #NAME? | J20: =F20-TINV(J$12,$F$15)*G20 -> #NAME? | K20: =F20+TINV(J$12,$F$15)*G20 -> #NAME? | L20: =VIF(A4:B14,1) -> #NAME?
E21: Quality | F21: #NAME? | G21: #NAME? | H21: =F21/G21 -> #NAME? | I21: =TDIST(ABS(H21),$F$15,2) -> #NAME? | J21: =F21-TINV(J$12,$F$15)*G21 -> #NAME? | K21: =F21+TINV(J$12,$F$15)*G21 -> #NAME? | L21: =VIF(A4:B14,2) -> #NAME?

Sheet Mult Reg 6C
A1: Multiple Regression with Categorical Variables | L1: Regression Analysis
A3: Age | B3: Party | C3: Gender | D3: Income | F3: Age | G3: Party 1 | H3: Party 2 | I3: Gender 1 | J3: Income | L3: OVERALL FIT
A4: 20 | B4: Rep | C4: Male | D4: 45000 | F4: 20 | G4: 1 | H4: 0 | I4: 1 | J4: 45000 | L4: Multiple R | M4: =SQRT(M5) -> #NAME? | O4: AIC | P4: =M8*LN(N13/M8)+2*(M12+1) -> #NAME?
A5: 25 | B5: Dem | C5: Male | D5: 39000 | F5: 25 | G5: 0 | H5: 1 | I5: 1 | J5: 39000 | L5: R Square | M5: =N12/N14 -> #NAME? | O5: AICc | P5: =P4+2*(M12+2)*(M12+3)/(M8-M12-3) -> #NAME?
A6: 45 | B6: Ind | C6: Male | D6: 56000 | F6: 45 | G6: 0 | H6: 0 | I6: 1 | J6: 56000 | L6: Adjusted R Square | M6: =1-(1-M5)*(M8-1)/(M8-M12-1) -> #NAME? | O6: SBC | P6: =M8*LN(N13/M8)+(M12+1)*LN(M8) -> #NAME?
A7: 35 | B7: Rep | C7: Female | D7: 49000 | F7: 35 | G7: 1 | H7: 0 | I7: 0 | J7: 49000 | L7: Standard Error | M7: =SQRT(O13) -> #NAME?
A8: 50 | B8: Dem | C8: Female | D8: 41000 | F8: 50 | G8: 0 | H8: 1 | I8: 0 | J8: 41000 | L8: Observations | M8: =COUNT(J4:J19) -> 16
A9: 55 | B9: Ind | C9: Female | D9: 42000 | F9: 55 | G9: 0 | H9: 0 | I9: 0 | J9: 42000
A10: 39 | B10: Rep | C10: Male | D10: 58000 | F10: 39 | G10: 1 | H10: 0 | I10: 1 | J10: 58000 | L10: ANOVA | P10: Alpha | Q10: 0.05
A11: 48 | B11: Dem | C11: Male | D11: 55000 | F11: 48 | G11: 0 | H11: 1 | I11: 1 | J11: 55000 | M11: df | N11: SS | O11: MS | P11: F | Q11: p-value | R11: sig
A12: 30 | B12: Ind | C12: Male | D12: 46000 | F12: 30 | G12: 0 | H12: 0 | I12: 1 | J12: 46000 | L12: Regression | M12: =COUNT(F4:I4) -> 4 | N12: =DEVSQ(MMULT(DESIGN(F4:I19),M17:M21)) -> #NAME? | O12: =N12/M12 -> #NAME? | P12: =O12/O13 -> #NAME? | Q12: =FDIST(P12,M12,M13) -> #NAME? | R12: =IF(Q12<Q10,"yes","no") -> #NAME?
A13: 27 | B13: Rep | C13: Female | D13: 42000 | F13: 27 | G13: 1 | H13: 0 | I13: 0 | J13: 42000 | L13: Residual | M13: =M14-M12 -> 11 | N13: =N14-N12 -> #NAME? | O13: =N13/M13 -> #NAME?
A14: 47 | B14: Dem | C14: Female | D14: 37000 | F14: 47 | G14: 0 | H14: 1 | I14: 0 | J14: 37000 | L14: Total | M14: =M8-1 -> 15 | N14: =DEVSQ(J4:J19) -> 2065000000
A15: 21 | B15: Ind | C15: Female | D15: 25000 | F15: 21 | G15: 0 | H15: 0 | I15: 0 | J15: 25000
A16: 48 | B16: Rep | C16: Male | D16: 75000 | F16: 48 | G16: 1 | H16: 0 | I16: 1 | J16: 75000 | M16: coeff | N16: std err | O16: t stat | P16: p-value | Q16: lower | R16: upper | S16: vif
A17: 24 | B17: Ind | C17: Male | D17: 43000 | F17: 24 | G17: 0 | H17: 0 | I17: 1 | J17: 43000 | L17: Intercept | M17: {=RegCoeff(F4:I19,J4:J19)} -> #NAME? | N17: #NAME? | O17: =M17/N17 -> #NAME? | P17: =TDIST(ABS(O17),$M$13,2) -> #NAME? | Q17: =M17-TINV(Q$10,$M$13)*N17 -> #NAME? | R17: =M17+TINV(Q$10,$M$13)*N17 -> #NAME?
A18: 28 | B18: Ind | C18: Female | D18: 40000 | F18: 28 | G18: 0 | H18: 0 | I18: 0 | J18: 40000 | L18: {=TRANSPOSE(F3:I3)} -> Age | M18: #NAME? | N18: #NAME? | O18: =M18/N18 -> #NAME? | P18: =TDIST(ABS(O18),$M$13,2) -> #NAME? | Q18: =M18-TINV(Q$10,$M$13)*N18 -> #NAME? | R18: =M18+TINV(Q$10,$M$13)*N18 -> #NAME? | S18: =VIF(F4:I19,1) -> #NAME?
A19: 40 | B19: Dem | C19: Female | D19: 31000 | F19: 40 | G19: 0 | H19: 1 | I19: 0 | J19: 31000 | L19: Party 1 | M19: #NAME? | N19: #NAME? | O19: =M19/N19 -> #NAME? | P19: =TDIST(ABS(O19),$M$13,2) -> #NAME? | Q19: =M19-TINV(Q$10,$M$13)*N19 -> #NAME? | R19: =M19+TINV(Q$10,$M$13)*N19 -> #NAME? | S19: =VIF(F4:I19,2) -> #NAME?
L20: Party 2 | M20: #NAME? | N20: #NAME? | O20: =M20/N20 -> #NAME? | P20: =TDIST(ABS(O20),$M$13,2) -> #NAME? | Q20: =M20-TINV(Q$10,$M$13)*N20 -> #NAME? | R20: =M20+TINV(Q$10,$M$13)*N20 -> #NAME? | S20: =VIF(F4:I19,3) -> #NAME?
A21: Age | B21: Party | C21: Gender | D21: Income | F21: Age | G21: Party 1 | H21: Party 2 | I21: Gender 1 | J21: Income | L21: Gender 1 | M21: #NAME? | N21: #NAME? | O21: =M21/N21 -> #NAME? | P21: =TDIST(ABS(O21),$M$13,2) -> #NAME? | Q21: =M21-TINV(Q$10,$M$13)*N21 -> #NAME? | R21: =M21+TINV(Q$10,$M$13)*N21 -> #NAME? | S21: =VIF(F4:I19,4) -> #NAME?
A22: 25 | B22: Dem | C22: Female | D22: ? | F22: 25 | G22: 0 | H22: 1 | I22: 0 | J22: {=TREND(J4:J19,F4:I19,F22:I23)} -> 24493.589
A23: 40 | B23: Ind | C23: Male | D23: ? | F23: 40 | G23: 0 | H23: 0 | I23: 1 | J23: 52696.701
L25: Regression Analysis
F27: Age | G27: Party 1 | H27: Party 2 | I27: Gender 1 | J27: Income | L27: OVERALL FIT
F28: 20 | G28: 1 | H28: 0 | I28: 1 | J28: 45000 | L28: Multiple R | M28: =SQRT(M29) -> #NAME? | O28: AIC | P28: =M32*LN(N37/M32)+2*(M36+1) -> #NAME?
F29: 25 | G29: 0 | H29: 1 | I29: 1 | J29: 39000 | L29: R Square | M29: =N36/N38 -> #NAME? | O29: AICc | P29: =P28+2*(M36+2)*(M36+3)/(M32-M36-3) -> #NAME?
F30: 45 | G30: -1 | H30: -1 | I30: 1 | J30: 56000 | L30: Adjusted R Square | M30: =1-(1-M29)*(M32-1)/(M32-M36-1) -> #NAME? | O30: SBC | P30: =M32*LN(N37/M32)+(M36+1)*LN(M32) -> #NAME?
F31: 35 | G31: 1 | H31: 0 | I31: -1 | J31: 49000 | L31: Standard Error | M31: =SQRT(O37) -> #NAME?
F32: 50 | G32: 0 | H32: 1 | I32: -1 | J32: 41000 | L32: Observations | M32: =COUNT(J28:J43) -> 16
F33: 55 | G33: -1 | H33: -1 | I33: -1 | J33: 42000
F34: 39 | G34: 1 | H34: 0 | I34: 1 | J34: 58000 | L34: ANOVA | P34: Alpha | Q34: 0.05
F35: 48 | G35: 0 | H35: 1 | I35: 1 | J35: 55000 | M35: df | N35: SS | O35: MS | P35: F | Q35: p-value | R35: sig
F36: 30 | G36: -1 | H36: -1 | I36: 1 | J36: 46000 | L36: Regression | M36: =COUNT(F28:I28) -> 4 | N36: =DEVSQ(MMULT(DESIGN(F28:I43),M41:M45)) -> #NAME? | O36: =N36/M36 -> #NAME? | P36: =O36/O37 -> #NAME? | Q36: =FDIST(P36,M36,M37) -> #NAME? | R36: =IF(Q36<Q34,"yes","no") -> #NAME?
F37: 27 | G37: 1 | H37: 0 | I37: -1 | J37: 42000 | L37: Residual | M37: =M38-M36 -> 11 | N37: =N38-N36 -> #NAME? | O37: =N37/M37 -> #NAME?
F38: 47 | G38: 0 | H38: 1 | I38: -1 | J38: 37000 | L38: Total | M38: =M32-1 -> 15 | N38: =DEVSQ(J28:J43) -> 2065000000
F39: 21 | G39: -1 | H39: -1 | I39: -1 | J39: 25000
F40: 48 | G40: 1 | H40: 0 | I40: 1 | J40: 75000 | M40: coeff | N40: std err | O40: t stat | P40: p-value | Q40: lower | R40: upper | S40: vif
F41: 24 | G41: -1 | H41: -1 | I41: 1 | J41: 43000 | L41: Intercept | M41: {=RegCoeff(F28:I43,J28:J43)} -> #NAME? | N41: #NAME? | O41: =M41/N41 -> #NAME? | P41: =TDIST(ABS(O41),$M$37,2) -> #NAME? | Q41: =M41-TINV(Q$34,$M$37)*N41 -> #NAME? | R41: =M41+TINV(Q$34,$M$37)*N41 -> #NAME?
F42: 28 | G42: -1 | H42: -1 | I42: -1 | J42: 40000 | L42: {=TRANSPOSE(F27:I27)} -> Age | M42: #NAME? | N42: #NAME? | O42: =M42/N42 -> #NAME? | P42: =TDIST(ABS(O42),$M$37,2) -> #NAME? | Q42: =M42-TINV(Q$34,$M$37)*N42 -> #NAME? | R42: =M42+TINV(Q$34,$M$37)*N42 -> #NAME? | S42: =VIF(F28:I43,1) -> #NAME?
F43: 40 | G43: 0 | H43: 1 | I43: -1 | J43: 31000 | L43: Party 1 | M43: #NAME? | N43: #NAME? | O43: =M43/N43 -> #NAME? | P43: =TDIST(ABS(O43),$M$37,2) -> #NAME? | Q43: =M43-TINV(Q$34,$M$37)*N43 -> #NAME? | R43: =M43+TINV(Q$34,$M$37)*N43 -> #NAME? | S43: =VIF(F28:I43,2) -> #NAME?
L44: Party 2 | M44: #NAME? | N44: #NAME? | O44: =M44/N44 -> #NAME? | P44: =TDIST(ABS(O44),$M$37,2) -> #NAME? | Q44: =M44-TINV(Q$34,$M$37)*N44 -> #NAME? | R44: =M44+TINV(Q$34,$M$37)*N44 -> #NAME? | S44: =VIF(F28:I43,3) -> #NAME?
L45: Gender 1 | M45: #NAME? | N45: #NAME? | O45: =M45/N45 -> #NAME? | P45: =TDIST(ABS(O45),$M$37,2) -> #NAME? | Q45: =M45-TINV(Q$34,$M$37)*N45 -> #NAME? | R45: =M45+TINV(Q$34,$M$37)*N45 -> #NAME? | S45: =VIF(F28:I43,4) -> #NAME?

Sheet Mult Reg 7
A1: Multiple Regression (Alternative Approach)
A3: Color | B3: Quality | C3: Price | E3: n | F3: =COUNT(A4:A14) -> 11
A4: 7 | B4: 5 | C4: 65 | E4: k | F4: =COUNT(A4:B4) -> 2
A5: 3 | B5: 7 | C5: 38 | E5: R Square | F5: ='Mult Reg 6'!O17^2 -> 0.85069397
A6: 5 | B6: 8 | C6: 51 | E6: df1 | F6: =F4 -> 2
A7: 8 | B7: 1 | C7: 38 | E7: df2 | F7: =F3-F4-1 -> 8
A8: 9 | B8: 3 | C8: 55 | E8: α | F8: 0.05
A9: 5 | B9: 4 | C9: 43 | E9: F | F9: =F7*F5/(F4*(1-F5)) -> 22.790613
A10: 4 | B10: 0 | C10: 25 | E10: p-value | F10: =FDIST(F9,F6,F7) -> 0.00049694621
A11: 2 | B11: 6 | C11: 33 | E11: F-crit | F11: =FINV(F8,F6,F7) -> 4.4589701
A12: 8 | B12: 7 | C12: 71 | E12: sig | F12: =IF(F10<F8,"yes","no") -> yes
A13: 6 | B13: 4 | C13: 51
A14: 9 | B14: 2 | C14: 49

Sheet Mult Reg 8
A1: Multiple Regression - confidence and prediction intervals
B3: Poverty | C3: Infant Mort | D3: White | E3: Crime | G3: Regression Analysis | O3: Confidence and prediction Intervals | S3: Real Statistics function
A4: Alabama | B4: 15.7 | C4: 9 | D4: 71.027178 | E4: 448
A5: Alaska | B5: 8.4 | C5: 6.9 | D5: 70.623189 | E5: 661.2 | G5: OVERALL FIT | J5: Core Matrix | P5: Conf | Q5: Pred
A6: Arizona | B6: 14.7 | C6: 6.4 | D6: 86.505697 | E6: 482.7 | G6: Multiple R | H6: =SQRT(H7) -> #NAME? | J6: {=CORE(C4:E53)} -> #NAME? | K6: #NAME? | L6: #NAME? | M6: #NAME? | O6: alpha | P6: 0.05 | Q6: =P6 -> 0.05 | S6: {=RegPred(O20:O22,C4:E53,B4:B53,TRUE)} -> #NAME? | T6: #NAME?
A7: Arkansas | B7: 17.3 | C7: 8.5 | D7: 80.783956 | E7: 529.4 | G7: R Square | H7: =I14/I16 -> #NAME? | J7: #NAME? | K7: #NAME? | L7: #NAME? | M7: #NAME? | O7: poverty | P7: =SUMPRODUCT(H19:H22,O19:O22) -> #NAME? | Q7: =P7 -> #NAME? | S7: #NAME? | T7: #NAME?
A8: California | B8: 13.3 | C8: 5 | D8: 76.640052 | E8: 522.6 | G8: Adjusted R Square | H8: =1-(1-H7)*(H10-1)/(H10-H14-1) -> #NAME? | J8: #NAME? | K8: #NAME? | L8: #NAME? | M8: #NAME? | O8: MSRes | P8: =J15 -> #NAME? | Q8: =P8 -> #NAME? | S8: #NAME? | T8: #NAME?
A9: Colorado | B9: 11.4 | C9: 5.7 | D9: 89.734092 | E9: 347.8 | G9: Standard Error | H9: =SQRT(J15) -> #NAME? | J9: #NAME? | K9: #NAME? | L9: #NAME? | M9: #NAME? | O9: dfRes | P9: =H15 -> 46 | Q9: =P9 -> 46 | S9: #NAME? | T9: #NAME?
A10: Connecticut | B10: 9.3 | C10: 6.2 | D10: 84.278652 | E10: 256 | G10: Observations | H10: =COUNT(B4:B53) -> 50 | O10: t-crit | P10: =TINV(P6,P9) -> 2.0128956 | Q10: =P10 -> 2.0128956 | S10: #NAME? | T10: #NAME?
A11: Delaware | B11: 10 | C11: 8.3 | D11: 74.266057 | E11: 689.2 | O11: s.e. | P11: {=SQRT(P8*MMULT(TRANSPOSE(O19:O22),MMULT(J6:M9,O19:O22)))} -> #NAME? | Q11: {=SQRT(P8*(1+MMULT(TRANSPOSE(O19:O22),MMULT(J6:M9,O19:O22))))} -> #NAME? | S11: #NAME? | T11: #NAME?
A12: Florida | B12: 13.2 | C12: 7.3 | D12: 79.811069 | E12: 722.6 | G12: ANOVA | K12: Alpha | L12: 0.05 | O12: lower | P12: =P7-P11*P10 -> #NAME? | Q12: =Q7-Q11*Q10 -> #NAME? | S12: #NAME? | T12: #NAME?
A13: Georgia | B13: 14.7 | C13: 8.1 | D13: 65.387718 | E13: 493.2 | H13: df | I13: SS | J13: MS | K13: F | L13: p-value | M13: sig | O13: upper | P13: =P7+P11*P10 -> #NAME? | Q13: =Q7+Q11*Q10 -> #NAME?
A14: Hawaii | B14: 9.1 | C14: 5.6 | D14: 29.667334 | E14: 272.8 | G14: Regression | H14: =COUNT(C4:E4) -> 3 | I14: =DEVSQ(MMULT(DESIGN(C4:E53),H19:H22)) -> #NAME? | J14: =I14/H14 -> #NAME? | K14: =J14/J15 -> #NAME? | L14: =FDIST(K14,H14,H15) -> #NAME? | M14: =IF(L14<L12,"yes","no") -> #NAME?
A15: Idaho | B15: 12.6 | C15: 6.8 | D15: 94.60066 | E15: 239.4 | G15: Residual | H15: =H16-H14 -> 46 | I15: =I16-I14 -> #NAME? | J15: =I15/H15 -> #NAME?
A16: Illinois | B16: 12.2 | C16: 7.3 | D16: 79.13311 | E16: 533.2 | G16: Total | H16: =H10-1 -> 49 | I16: =DEVSQ(B4:B53) -> 423.2488
A17: Indiana | B17: 13.1 | C17: 8 | D17: 88.000001 | E17: 333.6
A18: Iowa | B18: 11.5 | C18: 5.1 | D18: 94.170465 | E18: 294.7 | H18: coeff | I18: std err | J18: t stat | K18: p-value | L18: lower | M18: upper | O18: data
A19: Kansas | B19: 11.3 | C19: 7.1 | D19: 88.703717 | E19: 452.7 | G19: Intercept | H19: {=RegCoeff(C4:E53,B4:B53)} -> #NAME? | I19: #NAME? | J19: =H19/I19 -> #NAME? | K19: =TDIST(ABS(J19),$H$15,2) -> #NAME? | L19: =H19-TINV(L$12,$H$15)*I19 -> #NAME? | M19: =H19+TINV(L$12,$H$15)*I19 -> #NAME? | O19: 1
A20: Kentucky | B20: 17.3 | C20: 7.5 | D20: 89.904327 | E20: 295 | G20: {=TRANSPOSE(C3:E3)} -> Infant Mort | H20: #NAME? | I20: #NAME? | J20: =H20/I20 -> #NAME? | K20: =TDIST(ABS(J20),$H$15,2) -> #NAME? | L20: =H20-TINV(L$12,$H$15)*I20 -> #NAME? | M20: =H20+TINV(L$12,$H$15)*I20 -> #NAME? | O20: 7
A21: Louisiana | B21: 17.3 | C21: 9.9 | D21: 64.839544 | E21: 729.5 | G21: White | H21: #NAME? | I21: #NAME? | J21: =H21/I21 -> #NAME? | K21: =TDIST(ABS(J21),$H$15,2) -> #NAME? | L21: =H21-TINV(L$12,$H$15)*I21 -> #NAME? | M21: =H21+TINV(L$12,$H$15)*I21 -> #NAME? | O21: 80
A22: Maine | B22: 12.3 | C22: 6.3 | D22: 96.389853 | E22: 118 | G22: Crime | H22: #NAME? | I22: #NAME? | J22: =H22/I22 -> #NAME? | K22: =TDIST(ABS(J22),$H$15,2) -> #NAME? | L22: =H22-TINV(L$12,$H$15)*I22 -> #NAME? | M22: =H22+TINV(L$12,$H$15)*I22 -> #NAME? | O22: 400
A23: Maryland | B23: 8.1 | C23: 8 | D23: 63.398021 | E23: 641.9
A24: Massachusetts | B24: 10 | C24: 4.8 | D24: 86.20367 | E24: 431.5
A25: Michigan | B25: 14.4 | C25: 7.4 | D25: 81.183409 | E25: 536
A26: Minnesota | B26: 9.6 | C26: 5.2 | D26: 89.045557 | E26: 288.7
A27: Mississippi | B27: 21.2 | C27: 10.6 | D27: 60.598179 | E27: 291.3
A28: Missouri | B28: 13.4 | C28: 7.4 | D28: 85.028888 | E28: 504.9
A29: Montana | B29: 14.8 | C29: 5.8 | D29: 90.467729 | E29: 287.5
A30: Nebraska | B30: 10.8 | C30: 5.6 | D30: 91.372477 | E30: 302.4
A31: Nevada | B31: 11.3 | C31: 6.4 | D31: 80.891227 | E31: 750.6
A32: New Hampshire | B32: 7.6 | C32: 6.1 | D32: 95.487187 | E32: 137.3
A33: New Jersey | B33: 8.7 | C33: 5.5 | D33: 76.032117 | E33: 329.3
A34: New Mexico | B34: 17.1 | C34: 5.8 | D34: 83.996521 | E34: 664.2
... A53: Wyoming | B53: 9.4 | C53: 7 | D53: 93.867287 | E53: 239.3
A55: Poverty - % below poverty level
A56: Infant Mort - infant mortality per 1,000 births, death prior to 1 yr, excludes fetal death, residents only
A57: White - % of the population that is white
A58: Crime - violent crime (murder, forcible rape, robbery, and aggravated assault) per 100,000 people

Sheet Mult Reg 8a
A1: Simple Regression - confidence and prediction intervals
A3: Cig (x) | B3: Life Exp (y) | D3: Regression Analysis | L3: Confidence and prediction Intervals | P3: Real Statistics function
A4: 5 | B4: 80
A5: 23 | B5: 78 | D5: OVERALL FIT | G5: Core Matrix | M5: Conf | N5: Pred
A6: 25 | B6: 60 | D6: Multiple R | E6: =SQRT(E7) -> #NAME? | G6: {=CORE(A4:A18)} -> #NAME? | H6: #NAME? | L6: alpha | M6: 0.05 | N6: =M6 -> 0.05 | P6: {=RegPred(L20,A4:A18,B4:B18,TRUE)} -> #NAME? | Q6: #NAME?
A7: 48 | B7: 53 | D7: R Square | E7: =F14/F16 -> #NAME? | G7: #NAME? | H7: #NAME? | L7: poverty | M7: =SUMPRODUCT(E19:E20,L19:L20) -> #NAME? | N7: =M7 -> #NAME? | P7: #NAME? | Q7: #NAME?
A8: 17 | B8: 85 | D8: Adjusted R Square | E8: =1-(1-E7)*(E10-1)/(E10-E14-1) -> #NAME? | L8: MSRes | M8: =G15 -> #NAME? | N8: =M8 -> #NAME? | P8: #NAME? | Q8: #NAME?
A9: 8 | B9: 84 | D9: Standard Error | E9: =SQRT(G15) -> #NAME? | L9: dfRes | M9: =E15 -> 13 | N9: =M9 -> 13 | P9: #NAME? | Q9: #NAME?
A10: 4 | B10: 73 | D10: Observations | E10: =COUNT(B4:B18) -> 15 | L10: t-crit | M10: =TINV(M6,M9) -> 2.1603687 | N10: =M10 -> 2.1603687 | P10: #NAME? | Q10: #NAME?
A11: 26 | B11: 79 | L11: s.e. | M11: {=SQRT(M8*MMULT(TRANSPOSE(L19:L20),MMULT(G6:H7,L19:L20)))} -> #NAME? | N11: {=SQRT(M8*(1+MMULT(TRANSPOSE(L19:L20),MMULT(G6:H7,L19:L20))))} -> #NAME? | P11: #NAME? | Q11: #NAME?
A12: 11 | B12: 81 | D12: ANOVA | H12: Alpha | I12: 0.05 | L12: lower | M12: =M7-M11*M10 -> #NAME? | N12: =N7-N11*N10 -> #NAME? | P12: #NAME? | Q12: #NAME?
A13: 19 | B13: 75 | E13: df | F13: SS | G13: MS | H13: F | I13: p-value | J13: sig | L13: upper | M13: =M7+M11*M10 -> #NAME? | N13: =N7+N11*N10 -> #NAME?
A14: 14 | B14: 68 | D14: Regression | E14: =COUNT(A4) -> 1 | F14: =DEVSQ(MMULT(DESIGN(A4:A18),E19:E20)) -> #NAME? | G14: =F14/E14 -> #NAME? | H14: =G14/G15 -> #NAME? | I14: =FDIST(H14,E14,E15) -> #NAME? | J14: =IF(I14<I12,"yes","no") -> #NAME?
A15: 35 | B15: 72 | D15: Residual | E15: =E16-E14 -> 13 | F15: =F16-F14 -> #NAME? | G15: =F15/E15 -> #NAME?
A16: 29 | B16: 58 | D16: Total | E16: =E10-1 -> 14 | F16: =DEVSQ(B4:B18) -> 1683.7333
A17: 4 | B17: 92
A18: 23 | B18: 65 | E18: coeff | F18: std err | G18: t stat | H18: p-value | I18: lower | J18: upper | L18: data
D19: Intercept | E19: {=RegCoeff(A4:A18,B4:B18)} -> #NAME? | F19: #NAME? | G19: =E19/F19 -> #NAME? | H19: =TDIST(ABS(G19),$E$15,2) -> #NAME? | I19: =E19-TINV(I$12,$E$15)*F19 -> #NAME? | J19: =E19+TINV(I$12,$E$15)*F19 -> #NAME? | L19: 1
D20: {=TRANSPOSE(A3)} -> Cig (x) | E20: #NAME? | F20: #NAME? | G20: =E20/F20 -> #NAME? | H20: =TDIST(ABS(G20),$E$15,2) -> #NAME? | I20: =E20-TINV(I$12,$E$15)*F20 -> #NAME? | J20: =E20+TINV(I$12,$E$15)*F20 -> #NAME? | L20: 20

Sheet Stepwise 1
A1: Stepwise Regression
A3: input data | G3: variables to retain | L3: p-values | Q3: alpha | R3: 0.15
T4: Regression Analysis
A5: y | B5: x1 | C5: x2 | D5: x3 | E5: x4 | G5: 1 | H5: =G5+1 -> 2 | I5: =H5+1 -> 3 | J5: =I5+1 -> 4 | L5: x1 | M5: x2 | N5: x3 | O5: x4 | Q5: min p | R5: var #
A6: 49.25 | B6: 13 | C6: 7 | D6: 72 | E6: 11 | F6: 1a | L6: {=RegRank($B$6:$E$18,$A$6:$A$18,G6:J6)} -> #NAME? | M6: #NAME? | N6: #NAME? | O6: #NAME? | Q6: =MIN(L6:O6) -> #NAME? | R6: =MATCH(Q6,L6:O6,0) -> #NAME? | T6: OVERALL FIT
A7: 47.15 | B7: 1 | C7: 20 | D7: 57 | E7: 14 | F7: 1b | G7: =IF($R6=G$5,G$5,IF(G6="","",G6)) -> #NAME? | H7: =IF($R6=H$5,H$5,IF(H6="","",H6)) -> #NAME? | I7: =IF($R6=I$5,I$5,IF(I6="","",I6)) -> #NAME? | J7: =IF($R6=J$5,J$5,IF(J6="","",J6)) -> #NAME? | L7: {=RegCoeffP($B$6:$E$18,$A$6:$A$18,G7:J7)} -> #NAME? | M7: #NAME? | N7: #NAME? | O7: #NAME? | T7: Multiple R | U7: =SQRT(U8) -> #NAME? | W7: AIC | X7: =U11*LN(V16/U11)+2*(U15+1) -> #NAME?
A8: 62.15 | B8: 21 | C8: 10 | D8: 16 | E8: 41 | F8: 2a | G8: =IF(L7>=$R$3,"",IF(G7="","",G7)) -> #NAME? | H8: =IF(M7>=$R$3,"",IF(H7="","",H7)) -> #NAME? | I8: =IF(N7>=$R$3,"",IF(I7="","",I7)) -> #NAME? | J8: =IF(O7>=$R$3,"",IF(J7="","",J7)) -> #NAME? | L8: {=RegRank($B$6:$E$18,$A$6:$A$18,G8:J8)} -> #NAME? | M8: #NAME? | N8: #NAME? | O8: #NAME? | Q8: =MIN(L8:O8) -> #NAME? | R8: =MATCH(Q8,L8:O8,0) -> #NAME? | T8: R Square | U8: =V15/V17 -> #NAME? | W8: AICc | X8: =X7+2*(U15+2)*(U15+3)/(U11-U15-3) -> #NAME?
A9: 53.8 | B9: 24 | C9: 10 | D9: 51 | E9: 16 | F9: 2b | G9: =IF($R8=G$5,G$5,IF(G8="","",G8)) -> #NAME? | H9: =IF($R8=H$5,H$5,IF(H8="","",H8)) -> #NAME? | I9: =IF($R8=I$5,I$5,IF(I8="","",I8)) -> #NAME? | J9: =IF($R8=J$5,J$5,IF(J8="","",J8)) -> #NAME? | L9: {=RegCoeffP($B$6:$E$18,$A$6:$A$18,G9:J9)} -> #NAME? | M9: #NAME? | N9: #NAME? | O9: #NAME? | T9: Adjusted R Square | U9: =1-(1-U8)*(U11-1)/(U11-U15-1) -> #NAME? | W9: SBC | X9: =U11*LN(V16/U11)+(U15+1)*LN(U11) -> #NAME?
A10: 57.95 | B10: 13 | C10: 7 | D10: 32 | E10: 37 | F10: 3a | G10: =IF(L9>=$R$3,"",IF(G9="","",G9)) -> #NAME? | H10: =IF(M9>=$R$3,"",IF(H9="","",H9)) -> #NAME? | I10: =IF(N9>=$R$3,"",IF(I9="","",I9)) -> #NAME? | J10: =IF(O9>=$R$3,"",IF(J9="","",J9)) -> #NAME? | L10: {=RegRank($B$6:$E$18,$A$6:$A$18,G10:J10)} -> #NAME? | M10: #NAME? | N10: #NAME? | O10: #NAME? | Q10: =MIN(L10:O10) -> #NAME? | R10: =MATCH(Q10,L10:O10,0) -> #NAME? | T10: Standard Error | U10: =SQRT(W16) -> #NAME?
A11: 64.6 | B11: 21 | C11: 11 | D11: 18 | E11: 40 | F11: 3b | G11: =IF($R10=G$5,G$5,IF(G10="","",G10)) -> #NAME? | H11: =IF($R10=H$5,H$5,IF(H10="","",H10)) -> #NAME? | I11: =IF($R10=I$5,I$5,IF(I10="","",I10)) -> #NAME? | J11: =IF($R10=J$5,J$5,IF(J10="","",J10)) -> #NAME? | L11: {=RegCoeffP($B$6:$E$18,$A$6:$A$18,G11:J11)} -> #NAME? | M11: #NAME? | N11: #NAME? | O11: #NAME? | T11: Observations | U11: =COUNT(A6:A18) -> 13
A12: 61.35 | B12: 5 | C12: 22 | D12: 1 | E12: 56 | F12: 4a | G12: =IF(L11>=$R$3,"",IF(G11="","",G11)) -> #NAME? | H12: =IF(M11>=$R$3,"",IF(H11="","",H11)) -> #NAME? | I12: =IF(N11>=$R$3,"",IF(I11="","",I11)) -> #NAME? | J12: =IF(O11>=$R$3,"",IF(J11="","",J11)) -> #NAME? | L12: {=RegRank($B$6:$E$18,$A$6:$A$18,G12:J12)} -> #NAME? | M12: #NAME? | N12: #NAME? | O12: #NAME? | Q12: =MIN(L12:O12) -> #NAME? | R12: =MATCH(Q12,L12:O12,0) -> #NAME?
A13: 46.25 | B13: 2 | C13: 29 | D13: 47 | E13: 16 | T13: ANOVA | X13: Alpha | Y13: 0.05
A14: 56.55 | B14: 3 | C14: 24 | D14: 18 | E14: 39 | U14: df | V14: SS | W14: MS | X14: F | Y14: p-value | Z14: sig
A15: 67.95 | B15: 41 | C15: 4 | D15: 23 | E15: 32 | T15: Regression | U15: =COUNT(G12:J12) -> 0 | V15: =DEVSQ(MMULT(DESIGN(SelectCols(B6:E18,G12:J12)),U20:U22)) -> #NAME? | W15: =V15/U15 -> #NAME? | X15: =W15/W16 -> #NAME? | Y15: =FDIST(X15,U15,U16) -> #NAME? | Z15: =IF(Y15<Y13,"yes","no") -> #NAME?
A16: 51.9 | B16: 1 | C16: 31 | D16: 34 | E16: 25 | T16: Residual | U16: =U17-U15 -> 12 | V16: =V17-V15 -> #NAME? | W16: =V16/U16 -> #NAME?
A17: 66.65 | B17: 21 | C17: 11 | D17: 5 | E17: 51 | T17: Total | U17: =U11-1 -> 12 | V17: =DEVSQ(A6:A18) -> 678.94077
A18: 64.7 | B18: 18 | C18: 10 | D18: 5 | E18: 53
U19: coeff | V19: std err | W19: t stat | X19: p-value | Y19: lower | Z19: upper | AA19: vif
L20: =FTEXT(L22) -> #NAME? | T20: Intercept | U20: {=RegCoeff(SelectCols(B6:E18,G12:J12),A6:A18)} -> #NAME? | V20: #NAME? | W20: =U20/V20 -> #NAME? | X20: =TDIST(ABS(W20),$U$16,2) -> #NAME? | Y20: =U20-TINV(Y$13,$U$16)*V20 -> #NAME? | Z20: =U20+TINV(Y$13,$U$16)*V20 -> #NAME?
T21: {=TRANSPOSE(SelectCols(B5:E5,G12:J12))} -> #NAME? | U21: #NAME? | V21: #NAME? | W21: =U21/V21 -> #NAME? | X21: =TDIST(ABS(W21),$U$16,2) -> #NAME? | Y21: =U21-TINV(Y$13,$U$16)*V21 -> #NAME? | Z21: =U21+TINV(Y$13,$U$16)*V21 -> #NAME? | AA21: {=VIF(SelectCols(B6:E18,G12:J12),2)} -> #NAME?
L22: {=RegStepwise(B6:E18,A6:A18)} -> #NAME? | M22: #NAME? | N22: #NAME? | O22: #NAME? | P22: #NAME? | T22: #NAME? | U22: #NAME? | V22: #NAME? | W22: =U22/V22 -> #NAME? | X22: =TDIST(ABS(W22),$U$16,2) -> #NAME? | Y22: =U22-TINV(Y$13,$U$16)*V22 -> #NAME? | Z22: =U22+TINV(Y$13,$U$16)*V22 -> #NAME? | AA22: #NAME?

Sheet Stepwise 2
A1: Stepwise Regression
A3: input data | G3: Stepwise Regression | U3: Regression Analysis
A5: y | B5: x1 | C5: x2 | D5: x3 | E5: x4 | G5: Alpha | H5: 0.15 | U5: OVERALL FIT
A6: 49.25 | B6: 13 | C6: 7 | D6: 72 | E6: 11 | U6: Multiple R | V6: =SQRT(V7) -> #NAME? | X6: AIC | Y6: =V10*LN(W15/V10)+2*(V14+1) -> #NAME?
A7: 47.15 | B7: 1 | C7: 20 | D7: 57 | E7: 14 | G7: Step | H7: 1 | I7: =H7+1 -> 2 | J7: =I7+1 -> 3 | K7: =J7+1 -> 4 | M7: =B5 -> x1 | N7: =C5 -> x2 | O7: =D5 -> x3 | P7: =E5 -> x4 | R7: min p | S7: var # | U7: R Square | V7: =W14/W16 -> #NAME? | X7: AICc | Y7: =Y6+2*(V14+2)*(V14+3)/(V10-V14-3) -> #NAME?
A8: 62.15 | B8: 21 | C8: 10 | D8: 16 | E8: 41 | G8: 1a | M8: {=RegRank(B6:E18,A6:A18,H8:K8)} -> #NAME? | N8: #NAME? | O8: #NAME? | P8: #NAME? | R8: =MIN(M8:P8) -> #NAME? | S8: =MATCH(R8,M8:P8,0) -> #NAME? | U8: Adjusted R Square | V8: =1-(1-V7)*(V10-1)/(V10-V14-1) -> #NAME? | X8: SBC | Y8: =V10*LN(W15/V10)+(V14+1)*LN(V10) -> #NAME?
A9: 53.8 | B9: 24 | C9: 10 | D9: 51 | E9: 16 | G9: 1b | H9: =IF($S8=H$7,H$7,IF(H8="","",H8)) -> #NAME? | I9: =IF($S8=I$7,I$7,IF(I8="","",I8)) -> #NAME? | J9: =IF($S8=J$7,J$7,IF(J8="","",J8)) -> #NAME? | K9: =IF($S8=K$7,K$7,IF(K8="","",K8)) -> #NAME? | M9: {=RegCoeffP(B6:E18,A6:A18,H9:K9)} -> #NAME? | N9: #NAME? | O9: #NAME? | P9: #NAME? | U9: Standard Error | V9: =SQRT(X15) -> #NAME?
A10: 57.95 | B10: 13 | C10: 7 | D10: 32 | E10: 37 | G10: 2a | H10: =IF(M$9>=$H5,"",IF(H9="","",H9)) -> #NAME? | I10: =IF(N$9>=$H5,"",IF(I9="","",I9)) -> #NAME? | J10: =IF(O$9>=$H5,"",IF(J9="","",J9)) -> #NAME? | K10: =IF(P$9>=$H5,"",IF(K9="","",K9)) -> #NAME? | M10: {=RegRank(B6:E18,A6:A18,H10:K10)} -> #NAME? | N10: #NAME? | O10: #NAME? | P10: #NAME? | R10: =MIN(M10:P10) -> #NAME? | S10: =MATCH(R10,M10:P10,0) -> #NAME? | U10: Observations | V10: =COUNT(A6:A18) -> 13
A11: 64.6 | B11: 21 | C11: 11 | D11: 18 | E11: 40 | G11: 2b | H11: =IF($S10=H$7,H$7,IF(H10="","",H10)) -> #NAME? | I11: =IF($S10=I$7,I$7,IF(I10="","",I10)) -> #NAME? | J11: =IF($S10=J$7,J$7,IF(J10="","",J10)) -> #NAME? | K11: =IF($S10=K$7,K$7,IF(K10="","",K10)) -> #NAME? | M11: {=RegCoeffP(B6:E18,A6:A18,H11:K11)} -> #NAME? | N11: #NAME? | O11: #NAME? | P11: #NAME?
A12: 61.35 | B12: 5 | C12: 22 | D12: 1 | E12: 56 | G12: 3a | H12: =IF(M$11>=$H5,"",IF(H11="","",H11)) -> #NAME? | I12: =IF(N$11>=$H5,"",IF(I11="","",I11)) -> #NAME? | J12: =IF(O$11>=$H5,"",IF(J11="","",J11)) -> #NAME? | K12: =IF(P$11>=$H5,"",IF(K11="","",K11)) -> #NAME? | M12: {=RegRank(B6:E18,A6:A18,H12:K12)} -> #NAME? | N12: #NAME? | O12: #NAME? | P12: #NAME? | R12: =MIN(M12:P12) -> #NAME? | S12: =MATCH(R12,M12:P12,0) -> #NAME? | U12: ANOVA | Y12: Alpha | Z12: 0.05
A13: 46.25 | B13: 2 | C13: 29 | D13: 47 | E13: 16 | G13: 3b | H13: =IF($S12=H$7,H$7,IF(H12="","",H12)) -> #NAME? | I13: =IF($S12=I$7,I$7,IF(I12="","",I12)) -> #NAME? | J13: =IF($S12=J$7,J$7,IF(J12="","",J12)) -> #NAME? | K13: =IF($S12=K$7,K$7,IF(K12="","",K12)) -> #NAME? | M13: {=RegCoeffP(B6:E18,A6:A18,H13:K13)} -> #NAME? | N13: #NAME? | O13: #NAME? | P13: #NAME? | V13: df | W13: SS | X13: MS | Y13: F | Z13: p-value | AA13: sig
A14: 56.55 | B14: 3 | C14: 24 | D14: 18 | E14: 39 | G14: 4a | H14: =IF(M$13>=$H5,"",IF(H13="","",H13)) -> #NAME? | I14: =IF(N$13>=$H5,"",IF(I13="","",I13)) -> #NAME? | J14: =IF(O$13>=$H5,"",IF(J13="","",J13)) -> #NAME? | K14: =IF(P$13>=$H5,"",IF(K13="","",K13)) -> #NAME? | M14: {=RegRank(B6:E18,A6:A18,H14:K14)} -> #NAME? | N14: #NAME? | O14: #NAME? | P14: #NAME? | R14: =MIN(M14:P14) -> #NAME? | S14: =MATCH(R14,M14:P14,0) -> #NAME? | U14: Regression | V14: =COUNT(H14:K14) -> 0 | W14: =DEVSQ(MMULT(DESIGN(SelectCols(B6:E18,H14:K14)),V19:V21)) -> #NAME? | X14: =W14/V14 -> #NAME? | Y14: =X14/X15 -> #NAME? | Z14: =FDIST(Y14,V14,V15) -> #NAME? | AA14: =IF(Z14<Z12,"yes","no") -> #NAME?
A15: 67.95 | B15: 41 | C15: 4 | D15: 23 | E15: 32 | U15: Residual | V15: =V16-V14 -> 12 | W15: =W16-W14 -> #NAME? | X15: =W15/V15 -> #NAME?
A16: 51.9 | B16: 1 | C16: 31 | D16: 34 | E16: 25 | U16: Total | V16: =V10-1 -> 12 | W16: =DEVSQ(A6:A18) -> 678.94077
A17: 66.65 | B17: 21 | C17: 11 | D17: 5 | E17: 51
A18: 64.7 | B18: 18 | C18: 10 | D18: 5 | E18: 53 | V18: coeff | W18: std err | X18: t stat | Y18: p-value | Z18: lower | AA18: upper | AB18: vif
U19: Intercept | V19: {=RegCoeff(SelectCols(B6:E18,H14:K14),A6:A18)} -> #NAME? | W19: #NAME? | X19: =V19/W19 -> #NAME? | Y19: =TDIST(ABS(X19),$V$15,2) -> #NAME? | Z19: =V19-TINV(Z$12,$V$15)*W19 -> #NAME? | AA19: =V19+TINV(Z$12,$V$15)*W19 -> #NAME?
U20: {=TRANSPOSE(SelectCols(B5:E5,H14:K14))} -> #NAME? | V20: #NAME? | W20: #NAME? | X20: =V20/W20 -> #NAME? | Y20: =TDIST(ABS(X20),$V$15,2) -> #NAME? | Z20: =V20-TINV(Z$12,$V$15)*W20 -> #NAME? | AA20: =V20+TINV(Z$12,$V$15)*W20 -> #NAME? | AB20: {=VIF(SelectCols(B6:E18,H14:K14),1)} -> #NAME?
U21: #NAME? | V21: #NAME? | W21: #NAME? | X21: =V21/W21 -> #NAME? | Y21: =TDIST(ABS(X21),$V$15,2) -> #NAME? | Z21: =V21-TINV(Z$12,$V$15)*W21 -> #NAME? | AA21: =V21+TINV(Z$12,$V$15)*W21 -> #NAME? | AB21: {=VIF(SelectCols(B6:E18,H14:K14),2)} -> #NAME?

Sheet Season
A1: Regression Forecast with Seasonality
A3: Year | B3: Quarter | C3: Rev ($M) | D3: t | E3: Q1 | F3: Q2 | G3: Q3 | H3: Pred | J3: Regression Analysis
A4: 2012 | B4: 1 | C4: 10.5 | D4: 1 | E4: 1 | F4: 0 | G4: 0 | H4: {=TREND(C4:C19,D4:G19,D4:G23)} -> 10.8125
B5: 2 | C5: 9.2 | D5: 2 | E5: 0 | F5: 1 | G5: 0 | H5: 9.6125 | J5: OVERALL FIT
B6: 3 | C6: 13.1 | D6: 3 | E6: 0 | F6: 0 | G6: 1 | H6: 13.4125 | J6: Multiple R | K6: =SQRT(K7) -> #NAME? | M6: AIC | N6: =K10*LN(L15/K10)+2*(K14+1) -> #NAME?
B7: 4 | C7: 16 | D7: 4 | E7: =INDEX($L$4:$L$7,B7) -> 0 | F7: 0 | G7: 0 | H7: 16.4625 | J7: R Square | K7: =L14/L16 -> #NAME? | M7: AICc | N7: =N6+2*(K14+2)*(K14+3)/(K10-K14-3) -> #NAME?
A8: 2013 | B8: 1 | C8: 13.6 | D8: 5 | E8: 1 | F8: 0 | G8: 0 | H8: 13.0375 | J8: Adjusted R Square | K8: =1-(1-K7)*(K10-1)/(K10-K14-1) -> #NAME? | M8: SBC | N8: =K10*LN(L15/K10)+(K14+1)*LN(K10) -> #NAME?
B9: 2 | C9: 12.2 | D9: 6 | E9: 0 | F9: 1 | G9: 0 | H9: 11.8375 | J9: Standard Error | K9: =SQRT(M15) -> #NAME?
B10: 3 | C10: 15.6 | D10: 7 | E10: 0 | F10: 0 | G10: 1 | H10: 15.6375 | J10: Observations | K10: =COUNT(C4:C19) -> 16
B11: 4 | C11: 19.4 | D11: 8 | E11: =INDEX($L$4:$L$7,B11) -> 0 | F11: 0 | G11: 0 | H11: 18.6875
A12: 2014 | B12: 1 | C12: 15.9 | D12: 9 | E12: 1 | F12: 0 | G12: 0 | H12: 15.2625 | J12: ANOVA | N12: Alpha | O12: 0.05
B13: 2 | C13: 14.7 | D13: 10 | E13: 0 | F13: 1 | G13: 0 | H13: 14.0625 | K13: df | L13: SS | M13: MS | N13: F | O13: p-value | P13: sig
B14: 3 | C14: 18.3 | D14: 11 | E14: 0 | F14: 0 | G14: 1 | H14: 17.8625 | J14: Regression | K14: =COUNT(D4:G4) -> 4 | L14: =DEVSQ(MMULT(DESIGN(D4:G19),K19:K23)) -> #NAME? | M14: =L14/K14 -> #NAME? | N14: =M14/M15 -> #NAME? | O14: =FDIST(N14,K14,K15) -> #NAME? | P14: =IF(O14<O12,"yes","no") -> #NAME?
B15: 4 | C15: 20.5 | D15: 12 | E15: =INDEX($L$4:$L$7,B15) -> 0 | F15: 0 | G15: 0 | H15: 20.9125 | J15: Residual | K15: =K16-K14 -> 11 | L15: =L16-L14 -> #NAME? | M15: =L15/K15 -> #NAME?
A16: 2015 | B16: 1 | C16: 16.6 | D16: 13 | E16: 1 | F16: 0 | G16: 0 | H16: 17.4875 | J16: Total | K16: =K10-1 -> 15 | L16: =DEVSQ(C4:C19) -> 213.6775
B17: 2 | C17: 15.7 | D17: 14 | E17: 0 | F17: 1 | G17: 0 | H17: 16.2875
B18: 3 | C18: 20 | D18: 15 | E18: 0 | F18: 0 | G18: 1 | H18: 20.0875 | K18: coeff | L18: std err | M18: t stat | N18: p-value | O18: lower | P18: upper | Q18: vif
B19: 4 | C19: 23.3 | D19: 16 | E19: =INDEX($L$4:$L$7,B19) -> 0 | F19: 0 | G19: 0 | H19: 23.1375 | J19: Intercept | K19: {=RegCoeff(D4:G19,C4:C19)} -> #NAME? | L19: #NAME? | M19: =K19/L19 -> #NAME? | N19: =TDIST(ABS(M19),$K$15,2) -> #NAME? | O19: =K19-TINV(O$12,$K$15)*L19 -> #NAME? | P19: =K19+TINV(O$12,$K$15)*L19 -> #NAME?
A20: 2016 | B20: 1 | D20: 17 | E20: 1 | F20: 0 | G20: 0 | H20: 19.7125 | J20: {=TRANSPOSE(D3:G3)} -> t | K20: #NAME? | L20: #NAME? | M20: =K20/L20 -> #NAME? | N20: =TDIST(ABS(M20),$K$15,2) -> #NAME? | O20: =K20-TINV(O$12,$K$15)*L20 -> #NAME? | P20: =K20+TINV(O$12,$K$15)*L20 -> #NAME? | Q20: =VIF(D4:G19,1) -> #NAME?
B21: 2 | D21: 18 | E21: 0 | F21: 1 | G21: 0 | H21: 18.5125 | J21: Q1 | K21: #NAME? | L21: #NAME? | M21: =K21/L21 -> #NAME? | N21: =TDIST(ABS(M21),$K$15,2) -> #NAME? | O21: =K21-TINV(O$12,$K$15)*L21 -> #NAME? | P21: =K21+TINV(O$12,$K$15)*L21 -> #NAME? | Q21: =VIF(D4:G19,2) -> #NAME?
B22: 3 | D22: 19 | E22: 0 | F22: 0 | G22: 1 | H22: 22.3125 | J22: Q2 | K22: #NAME? | L22: #NAME? | M22: =K22/L22 -> #NAME? | N22: =TDIST(ABS(M22),$K$15,2) -> #NAME? | O22: =K22-TINV(O$12,$K$15)*L22 -> #NAME? | P22: =K22+TINV(O$12,$K$15)*L22 -> #NAME? | Q22: =VIF(D4:G19,3) -> #NAME?
B23: 4 | D23: 20 | E23: =INDEX($L$4:$L$7,B23) -> 0 | F23: 0 | G23: 0 | H23: 25.3625 | J23: Q3 | K23: #NAME? | L23: #NAME? | M23: =K23/L23 -> #NAME? | N23: =TDIST(ABS(M23),$K$15,2) -> #NAME? | O23: =K23-TINV(O$12,$K$15)*L23 -> #NAME? | P23: =K23+TINV(O$12,$K$15)*L23 -> #NAME? | Q23: =VIF(D4:G19,4) -> #NAME?
E25: MAE | F25: MSE
E26: =SUMPRODUCT(ABS(C4:C19-H4:H19))/COUNT(C4:C19) -> 0.4390625 | F26: =SUMXMY2(C4:C19,H4:H19)/COUNT(C4:C19) -> 0.24234375

Sheet Shapely
A1: Shapely-Owen
A3: x1 | B3: x2 | C3: x3 | D3: y | G3: r-sq | K3: w/o | L3: with | M3: r-sq w/o | N3: r-sq w/ | O3: diff | P3: weight | Q3: w*d
A4: 7 | B4: 3 | C4: 6 | D4: 23 | F4: 0 | G4: 0 | K4: 0 | L4: 1 | M4: =INDEX($G$4:$G$11,MATCH(K4,$F$4:$F$11,0)) -> 0 | N4: =INDEX($G$4:$G$11,MATCH(L4,$F$4:$F$11,0)) -> #NAME? | O4: =N4-M4 -> #NAME? | P4: =1/3 -> 0.33333333 | Q4: =O4*P4 -> #NAME?
A5: 9 | B5: 4 | C5: 8 | D5: 45 | F5: 1 | G5: =RSquare(A4:A8,D4:D8) -> #NAME? | I5: =FTEXT(G5) -> #NAME? | K5: 2 | L5: 12 | M5: =INDEX($G$4:$G$11,MATCH(K5,$F$4:$F$11,0)) -> #NAME? | N5: =INDEX($G$4:$G$11,MATCH(L5,$F$4:$F$11,0)) -> #NAME? | O5: =N5-M5 -> #NAME? | P5: =1/6 -> 0.16666667 | Q5: =O5*P5 -> #NAME?
A6: 12 | B6: 5 | C6: 9 | D6: 68 | F6: 2 | G6: =RSquare(B4:B8,D4:D8) -> #NAME? | I6: =FTEXT(G6) -> #NAME? | K6: 3 | L6: 13 | M6: =INDEX($G$4:$G$11,MATCH(K6,$F$4:$F$11,0)) -> #NAME? | N6: =INDEX($G$4:$G$11,MATCH(L6,$F$4:$F$11,0)) -> #NAME? | O6: =N6-M6 -> #NAME? | P6: =1/6 -> 0.16666667 | Q6: =O6*P6 -> #NAME?
A7: 10 | B7: 8 | C7: 12 | D7: 59 | F7: 3 | G7: =RSquare(C4:C8,D4:D8) -> #NAME? | I7: =FTEXT(G7) -> #NAME? | K7: 23 | L7: 123 | M7: =INDEX($G$4:$G$11,MATCH(K7,$F$4:$F$11,0)) -> #NAME? | N7: =INDEX($G$4:$G$11,MATCH(L7,$F$4:$F$11,0)) -> #NAME? | O7: =N7-M7 -> #NAME? | P7: =1/3 -> 0.33333333 | Q7: =O7*P7 -> #NAME?
A8: 20 | B8: 9 | C8: 23 | D8: 89 | F8: 12 | G8: =RSquare(A4:B8,D4:D8) -> #NAME? | I8: =FTEXT(G8) -> #NAME? | L8: 1 | Q8: =SUM(Q4:Q7) -> #NAME? | S8: =Q8/Q22 -> #NAME?
F9: 23 | G9: =RSquare(B4:C8,D4:D8) -> #NAME? | I9: =FTEXT(G9) -> #NAME?
B10: x1 | C10: x3 | D10: y | F10: 13 | G10: =RSquare(B11:C15,D11:D15) -> #NAME? | I10: =FTEXT(G10) -> #NAME? | K10: 0 | L10: 2 | M10: =INDEX($G$4:$G$11,MATCH(K10,$F$4:$F$11,0)) -> 0 | N10: =INDEX($G$4:$G$11,MATCH(L10,$F$4:$F$11,0)) -> #NAME? | O10: =N10-M10 -> #NAME? | P10: =1/3 -> 0.33333333 | Q10: =O10*P10 -> #NAME?
B11: 7 | C11: 6 | D11: 23 | F11: 123 | G11: =RSquare(A4:C8,D4:D8) -> #NAME? | I11: =FTEXT(G11) -> #NAME? | K11: 1 | L11: 12 | M11: =INDEX($G$4:$G$11,MATCH(K11,$F$4:$F$11,0)) -> #NAME? | N11: =INDEX($G$4:$G$11,MATCH(L11,$F$4:$F$11,0)) -> #NAME? | O11: =N11-M11 -> #NAME? | P11: =1/6 -> 0.16666667 | Q11: =O11*P11 -> #NAME?
B12: 9 | C12: 8 | D12: 45 | K12: 3 | L12: 23 | M12: =INDEX($G$4:$G$11,MATCH(K12,$F$4:$F$11,0)) -> #NAME? | N12: =INDEX($G$4:$G$11,MATCH(L12,$F$4:$F$11,0)) -> #NAME? | O12: =N12-M12 -> #NAME? | P12: =1/6 -> 0.16666667 | Q12: =O12*P12 -> #NAME?
B13: 12 | C13: 9 | D13: 68 | F13: 1 | G13: {=Shapely(A4:C8,D4:D8)} -> #NAME? | I13: =FTEXT(G13) -> #NAME? | K13: 13 | L13: 123 | M13: =INDEX($G$4:$G$11,MATCH(K13,$F$4:$F$11,0)) -> #NAME? | N13: =INDEX($G$4:$G$11,MATCH(L13,$F$4:$F$11,0)) -> #NAME? | O13: =N13-M13 -> #NAME? | P13: =1/3 -> 0.33333333 | Q13: =O13*P13 -> #NAME?
B14: 10 | C14: 12 | D14: 59 | F14: 2 | G14: #NAME? | L14: 2 | Q14: =SUM(Q10:Q13) -> #NAME? | S14: =Q14/Q22 -> #NAME?
B15: 20 | C15: 23 | D15: 89 | F15: 3 | G15: #NAME?
F16: tot | G16: =SUM(G13:G15) -> #NAME? | I16: =FTEXT(G16) -> #NAME? | K16: 0 | L16: 3 | M16: =INDEX($G$4:$G$11,MATCH(K16,$F$4:$F$11,0)) -> 0 | N16: =INDEX($G$4:$G$11,MATCH(L16,$F$4:$F$11,0)) -> #NAME? | O16: =N16-M16 -> #NAME? | P16: =1/3 -> 0.33333333 | Q16: =O16*P16 -> #NAME?
K17: 1 | L17: 13 | M17: =INDEX($G$4:$G$11,MATCH(K17,$F$4:$F$11,0)) -> #NAME? | N17: =INDEX($G$4:$G$11,MATCH(L17,$F$4:$F$11,0)) -> #NAME? | O17: =N17-M17 -> #NAME? | P17: =1/6 -> 0.16666667 | Q17: =O17*P17 -> #NAME?
K18: 2 | L18: 23 | M18: =INDEX($G$4:$G$11,MATCH(K18,$F$4:$F$11,0)) -> #NAME? | N18: =INDEX($G$4:$G$11,MATCH(L18,$F$4:$F$11,0)) -> #NAME? | O18: =N18-M18 -> #NAME? | P18: =1/6 -> 0.16666667 | Q18: =O18*P18 -> #NAME?
K19: 12 | L19: 123 | M19: =INDEX($G$4:$G$11,MATCH(K19,$F$4:$F$11,0)) -> #NAME? | N19: =INDEX($G$4:$G$11,MATCH(L19,$F$4:$F$11,0)) -> #NAME? | O19: =N19-M19 -> #NAME? | P19: =1/3 -> 0.33333333 | Q19: =O19*P19 -> #NAME?
L20: 3 | Q20: =SUM(Q16:Q19) -> #NAME? | S20: =Q20/Q22 -> #NAME?
L22: tot | Q22: =Q8+Q14+Q20 -> #NAME?

Sheet MCorr
A1: Multiple Correlation | G1: Correlation matrix | Q1: Regression Analysis
B3: Crime | C3: Doctors | D3: Traf Deaths | E3: University | H3: Crime | I3: Doctors | J3: Traf Deaths | K3: University | Q3: OVERALL FIT
A4: Alabama | B4: 448 | C4: 218.17341 | D4: 1.81 | E4: 22 | G4: {=TRANSPOSE(H3:K3)} -> Crime | H4: {=CORR(B4:E18)} -> #NAME? | I4: #NAME? | J4: #NAME? | K4: #NAME? | Q4: Multiple R | R4: =SQRT(R5) -> #NAME?
A5: Alaska | B5: 661.2 | C5: 228.45028 | D5: 1.63 | E5: 27.3 | G5: Doctors | H5: #NAME? | I5: #NAME? | J5: #NAME? | K5: #NAME? | Q5: R Square | R5: =S12/S14 -> #NAME?
A6: Arizona | B6: 482.7 | C6: 209.66657 | D6: 1.69 | E6: 25.1 | G6: Traf Deaths | H6: #NAME? | I6: #NAME? | J6: #NAME? | K6: #NAME? | Q6: Adjusted R Square | R6: =1-(1-R5)*(R8-1)/(R8-R12-1) -> #NAME?
A7: Arkansas | B7: 529.4 | C7: 203.42286 | D7: 1.96 | E7: 18.8 | G7: University | H7: #NAME? | I7: #NAME? | J7: #NAME? | K7: #NAME? | Q7: Standard Error | R7: =SQRT(T13) -> #NAME?
A8: California | B8: 522.6 | C8: 268.69056 | D8: 1.21 | E8: 29.6 | Q8: Observations | R8: =COUNT(B4:B18) -> 15
A9: Colorado | B9: 347.8 | C9: 259.68609 | D9: 1.14 | E9: 35.6 | G9: Inverse of correlation matrix | M9: Sqrt Diag | O9: Alternative
A10: Connecticut | B10: 256 | C10: 376.37527 | D10: 0.86 | E10: 35.6 | Q10: ANOVA | U10: Alpha | V10: 0.05
A11: Delaware | B11: 689.2 | C11: 250.94176 | D11: 1.23 | E11: 27.5 | G11: 1 | H11: {=MINVERSE(H4:K7)} -> #NAME? | I11: #NAME? | J11: #NAME? | K11: #NAME? | M11: {=SQRT(DIAG(H11:K14))} -> #NAME? | O11: {=SQRT(INDEX(H11:K14,G11:G14,G11:G14))} -> #NAME? | R11: df | S11: SS | T11: MS | U11: F | V11: p-value | W11: sig
A12: Florida | B12: 722.6 | C12: 247.8636 | D12: 1.56 | E12: 25.8 | G12: =G11+1 -> 2 | H12: #NAME? | I12: #NAME? | J12: #NAME? | K12: #NAME? | M12: #NAME? | O12: #NAME? | Q12: Regression | R12: =COUNT(C4:E4) -> 3 | S12: =DEVSQ(MMULT(DESIGN(C4:E18),R17:R20)) -> #NAME? | T12: =S12/R12 -> #NAME? | U12: =T12/T13 -> #NAME? | V12: =FDIST(U12,R12,R13) -> #NAME? | W12: =IF(V12<V10,"yes","no") -> #NAME?
A13: Georgia | B13: 493.2 | C13: 217.4457 | D13: 1.46 | E13: 27.5 | G13: =G12+1 -> 3 | H13: #NAME? | I13: #NAME? | J13: #NAME? | K13: #NAME? | M13: #NAME? | O13: #NAME? | Q13: Residual | R13: =R14-R12 -> 11 | S13: =S14-S12 -> #NAME? | T13: =S13/R13 -> #NAME?
A14: Hawaii | B14: 272.8 | C14: 316.98289 | D14: 1.33 | E14: 29.1 | G14: =G13+1 -> 4 | H14: #NAME? | I14: #NAME? | J14: #NAME? | K14: #NAME? | M14: #NAME? | O14: #NAME? | Q14: Total | R14: =R8-1 -> 14 | S14: =DEVSQ(B4:B18) -> 358680.69
A15: Idaho | B15: 239.4 | C15: 168.8339 | D15: 1.6 | E15: 24
A16: Illinois | B16: 533.2 | C16: 280.15387 | D16: 1.16 | E16: 29.9 | G16: Partial correlation matrix | R16: coeff | S16: std err | T16: t stat | U16: p-value | V16: lower | W16: upper
A17: Indiana | B17: 333.6 | C17: 216.9397 | D17: 1.26 | E17: 22.9 | Q17: Intercept | R17: {=RegCoeff(C4:E18,B4:B18)} -> #NAME? | S17: {=RegCoeffSE(C4:E18,B4:B18)} -> #NAME? | T17: =R17/S17 -> #NAME? | U17: =TDIST(ABS(T17),$R$13,2) -> #NAME? | V17: =R17-TINV(V$10,$R$13)*S17 -> #NAME? | W17: =R17+TINV(V$10,$R$13)*S17 -> #NAME?
A18: Iowa | B18: 294.7 | C18: 189.28322 | D18: 1.42 | E18: 24.3 | H18: Crime | I18: Doctors | J18: Traf Deaths | K18: University | Q18: {=TRANSPOSE(C3:E3)} -> Doctors | R18: #NAME? | S18: #NAME? | T18: =R18/S18 -> #NAME? | U18: =TDIST(ABS(T18),$R$13,2) -> #NAME? | V18: =R18-TINV(V$10,$R$13)*S18 -> #NAME? | W18: =R18+TINV(V$10,$R$13)*S18 -> #NAME?
G19: {=TRANSPOSE(H18:K18)} -> Crime | H19: {=-H11:K14/MMULT(M11:M14,TRANSPOSE(M11:M14))} -> #NAME? | I19: #NAME? | J19: #NAME? | K19: #NAME? | Q19: Traf Deaths | R19: #NAME? | S19: #NAME? | T19: =R19/S19 -> #NAME? | U19: =TDIST(ABS(T19),$R$13,2) -> #NAME? | V19: =R19-TINV(V$10,$R$13)*S19 -> #NAME? | W19: =R19+TINV(V$10,$R$13)*S19 -> #NAME?
A20: Partial correlation Crime x Doctors | G20: Doctors | H20: #NAME? | I20: #NAME? | J20: #NAME? | K20: #NAME? | Q20: University | R20: #NAME? | S20: #NAME? | T20: =R20/S20 -> #NAME? | U20: =TDIST(ABS(T20),$R$13,2) -> #NAME? | V20: =R20-TINV(V$10,$R$13)*S20 -> #NAME? | W20: =R20+TINV(V$10,$R$13)*S20 -> #NAME?
G21: Traf Deaths | H21: #NAME? | I21: #NAME? | J21: #NAME? | K21: #NAME?
B22: {=INDEX(-H11:K14/(M11:M12*TRANSPOSE(M11:M14)),1,2)} -> #NAME? | G22: University | H22: #NAME? | I22: #NAME? | J22: #NAME? | K22: #NAME? | Q22: Other ways of calculating R-square
B23: {=PCORREL(B4:E18,1,2)} -> #NAME?
G24: Alternative formula | Q24: =RSquare(C4:E18,B4:B18) | S24: =RSquare(C4:E18,B4:B18) -> #NAME?
Q25: =RSquare(B4:E18,1) | S25: =RSquare(B4:E18,1) -> #NAME?
H26: Crime | I26: Doctors | J26: Traf Deaths | K26: University | Q26: =1-1/H11 | S26: =1-1/H11 -> #NAME?
G27: Crime | H27: {=-H11:K14/(M11:M14*TRANSPOSE(M11:M14))} -> #NAME? | I27: #NAME? | J27: #NAME? | K27: #NAME?
G28: Doctors | H28: #NAME? | I28: #NAME? | J28: #NAME? | K28: #NAME?
G29: Traf Deaths | H29: #NAME? | I29: #NAME? | J29: #NAME? | K29: #NAME?
G30: University | H30: #NAME? | I30: #NAME? | J30: #NAME? | K30: #NAME?
G32: Real Statistics formula
H34: Crime | I34: Doctors | J34: Traf Deaths | K34: University
G35: Crime | H35: {=PCORR(B4:E18)} -> #NAME? | I35: #NAME? | J35: #NAME? | K35: #NAME?
G36: Doctors | H36: #NAME? | I36: #NAME? | J36: #NAME? | K36: #NAME?
G37: Traf Deaths | H37: #NAME? | I37: #NAME? | J37: #NAME? | K37: #NAME?
G38: University | H38: #NAME? | I38: #NAME? | J38: #NAME? | K38: #NAME?

Sheet Mult Reg Pow
A1: Multiple regression - Statistical Power
A3: Color | B3: Quality | C3: Price | E3: Regression Analysis | M3: n | N3: =COUNT(A4:A14) -> 11 | P3: =FTEXT(N3) -> #NAME?
A4: 7 | B4: 5 | C4: 65 | M4: k | N4: =COUNTA(A3:B3) -> 2 | P4: =FTEXT(N4) -> #NAME?
A5: 3 | B5: 7 | C5: 38 | E5: OVERALL FIT | M5: dfRes | N5: =N3-N4-1 -> 8 | P5: =FTEXT(N5) -> #NAME?
A6: 5 | B6: 8 | C6: 51 | E6: Multiple R | F6: =SQRT(F7) -> #NAME? | M6: dfReg | N6: =N4 -> 2 | P6: =FTEXT(N6) -> #NAME?
A7: 8 | B7: 1 | C7: 38 | E7: R Square | F7: =G14/G16 -> #NAME?
A8: 9 | B8: 3 | C8: 55 | E8: Adjusted R Square | F8: =1-(1-F7)*(F10-1)/(F10-F14-1) -> #NAME? | M8: R-square | N8: =F7 -> #NAME? | P8: =FTEXT(N8) -> #NAME?
A9: 5 | B9: 4 | C9: 43 | E9: Standard Error | F9: =SQRT(H15) -> #NAME? | M9: f-square | N9: =N8/(1-N8) -> #NAME? | P9: =FTEXT(N9) -> #NAME?
A10: 4 | B10: 0 | C10: 25 | E10: Observations | F10: =COUNT(C4:C14) -> 11 | M10: λ | N10: =N9*N3 -> #NAME? | P10: =FTEXT(N10) -> #NAME?
A11: 2 | B11: 6 | C11: 33
A12: 8 | B12: 7 | C12: 71 | E12: ANOVA | I12: Alpha | J12: 0.05 | M12: α | N12: 0.05
A13: 6 | B13: 4 | C13: 51 | F13: df | G13: SS | H13: MS | I13: F | J13: p-value | K13: sig | M13: F-crit | N13: =FINV(N12,N6,N5) -> 4.4589701 | P13: =FTEXT(N13) -> #NAME?
A14: 9 | B14: 2 | C14: 49 | E14: Regression | F14: =COUNT(A4:B4) -> 2 | G14: =DEVSQ(MMULT(DESIGN(A4:B14),F19:F21)) -> #NAME? | H14: =G14/F14 -> #NAME? | I14: =H14/H15 -> #NAME? | J14: =FDIST(I14,F14,F15) -> #NAME? | K14: =IF(J14<J12,"yes","no") -> #NAME? | M14: β | N14: =NF_DIST(N13,N6,N5,N10,TRUE) -> #NAME? | P14: =FTEXT(N14) -> #NAME?
E15: Residual | F15: =F16-F14 -> 8 | G15: =G16-G14 -> #NAME? | H15: =G15/F15 -> #NAME? | M15: 1-β | N15: =1-N14 -> #NAME? | P15: =FTEXT(N15) -> #NAME?
E16: Total | F16: =F10-1 -> 10 | G16: =DEVSQ(C4:C14) -> 1857.6364
M17: SSRes | N17: =G15 -> #NAME? | P17: =FTEXT(N17) -> #NAME?
F18: coeff | G18: std err | H18: t stat | I18: p-value | J18: lower | K18: upper | M18: SSReg | N18: =G14 -> #NAME? | P18: =FTEXT(N18) -> #NAME?
E19: Intercept | F19: {=RegCoeff(A4:B14,C4:C14)} -> #NAME? | G19: #NAME? | H19: =F19/G19 -> #NAME? | I19: =TDIST(ABS(H19),$F$15,2) -> #NAME? | J19: =F19-TINV(J$12,$F$15)*G19 -> #NAME? | K19: =F19+TINV(J$12,$F$15)*G19 -> #NAME? | M19: f-square | N19: =N18/N17 -> #NAME? | P19: =FTEXT(N19) -> #NAME?
E20: {=TRANSPOSE(A3:B3)} -> Color | F20: #NAME? | G20: #NAME? | H20: =F20/G20 -> #NAME? | I20: =TDIST(ABS(H20),$F$15,2) -> #NAME? | J20: =F20-TINV(J$12,$F$15)*G20 -> #NAME? | K20: =F20+TINV(J$12,$F$15)*G20 -> #NAME?
E21: Quality | F21: #NAME? | G21: #NAME? | H21: =F21/G21 -> #NAME? | I21: =TDIST(ABS(H21),$F$15,2) -> #NAME? | J21: =F21-TINV(J$12,$F$15)*G21 -> #NAME? | K21: =F21+TINV(J$12,$F$15)*G21 -> #NAME?

Sheet Mult Reg Pow 1
A1: Multiple Regression - power | T1: Confidence interval of effect size and power
B3: Poverty | C3: Infant Mort | D3: White | E3: Crime | G3: Regression Analysis | O3: n | P3: =COUNT(B4:B53) -> 50 | R3: =FTEXT(P3) -> #NAME? | T3: F | U3: =K14 -> #NAME? | W3: =FTEXT(U3) -> #NAME?
A4: Alabama | B4: 15.7 | C4: 9 | D4: 71.027178 | E4: 448 | O4: k | P4: =COUNTA(C3:E3) -> 3 | R4: =FTEXT(P4) -> #NAME? | T4: dfReg | U4: =H14 -> 3 | W4: =FTEXT(U4) -> #NAME?
A5: Alaska | B5: 8.4 | C5: 6.9 | D5: 70.623189 | E5: 661.2 | G5: OVERALL FIT | O5: dfRes | P5: =P3-P4-1 -> 46 | R5: =FTEXT(P5) -> #NAME? | T5: dfRes | U5: =H15 -> 46 | W5: =FTEXT(U5) -> #NAME?
A6: Arizona | B6: 14.7 | C6: 6.4 | D6: 86.505697 | E6: 482.7 | G6: Multiple R | H6: =SQRT(H7) -> #NAME? | O6: dfReg | P6: =P4 -> 3 | R6: =FTEXT(P6) -> #NAME? | T6: SSReg | U6: =I14 -> #NAME? | W6: =FTEXT(U6) -> #NAME?
A7: Arkansas | B7: 17.3 | C7: 8.5 | D7: 80.783956 | E7: 529.4 | G7: R Square | H7: =I14/I16 -> #NAME? | T7: SSRes | U7: =I15 -> #NAME? | W7: =FTEXT(U7) -> #NAME?
A8: California | B8: 13.3 | C8: 5 | D8: 76.640052 | E8: 522.6 | G8: Adjusted R Square | H8: =1-(1-H7)*(H10-1)/(H10-H14-1) -> #NAME? | O8: R-square | P8: =H7 -> #NAME? | R8: =FTEXT(P8) -> #NAME? | T8: k | U8: =U4 -> 3 | W8: =FTEXT(U8) -> #NAME?
A9: Colorado | B9: 11.4 | C9: 5.7 | D9: 89.734092 | E9: 347.8 | G9: Standard Error | H9: =SQRT(J15) -> #NAME? | O9: f-square | P9: =P8/(1-P8) -> #NAME? | R9: =FTEXT(P9) -> #NAME? | T9: n | U9: =U4+U5+1 -> 50 | W9: =FTEXT(U9) -> #NAME?
A10: Connecticut | B10: 9.3 | C10: 6.2 | D10: 84.278652 | E10: 256 | G10: Observations | H10: =COUNT(B4:B53) -> 50 | O10: λ | P10: =P9*P3 -> #NAME? | R10: =FTEXT(P10) -> #NAME? | T10: alpha | U10: 0.05
A11: Delaware | B11: 10 | C11: 8.3 | D11: 74.266057 | E11: 689.2 | T11: λ | U11: =U14*U9/(1-U14) -> #NAME? | W11: =FTEXT(U11) -> #NAME?
A12: Florida | B12: 13.2 | C12: 7.3 | D12: 79.811069 | E12: 722.6 | G12: ANOVA | K12: Alpha | L12: 0.05 | O12: α | P12: 0.05 | T12: λ lower | U12: =NF_NCP(1-U10/2,U4,U5,U3) -> #NAME? | W12: =FTEXT(U12) -> #NAME?
A13: Georgia | B13: 14.7 | C13: 8.1 | D13: 65.387718 | E13: 493.2 | H13: df | I13: SS | J13: MS | K13: F | L13: p-value | M13: sig | O13: F-crit | P13: =FINV(P12,P6,P5) -> 2.8068449 | R13: =FTEXT(P13) -> #NAME? | T13: λ upper | U13: =NF_NCP(U10/2,U4,U5,U3) -> #NAME? | W13: =FTEXT(U13) -> #NAME?
A14: Hawaii | B14: 9.1 | C14: 5.6 | D14: 29.667334 | E14: 272.8 | G14: Regression | H14: =COUNT(C4:E4) -> 3 | I14: =DEVSQ(MMULT(DESIGN(C4:E53),H19:H22)) -> #NAME? | J14: =I14/H14 -> #NAME? | K14: =J14/J15 -> #NAME? | L14: =FDIST(K14,H14,H15) -> #NAME? | M14: =IF(L14<L12,"yes","no") -> #NAME? | O14: β | P14: =NF_DIST(P13,P6,P5,P10,TRUE) -> #NAME? | R14: =FTEXT(P14) -> #NAME? | T14: R-sq | U14: =H7 -> #NAME? | W14: =FTEXT(U14) -> #NAME?
A15: Idaho | B15: 12.6 | C15: 6.8 | D15: 94.60066 | E15: 239.4 | G15: Residual | H15: =H16-H14 -> 46 | I15: =I16-I14 -> #NAME? | J15: =I15/H15 -> #NAME? | O15: 1-β | P15: =1-P14 -> #NAME? | R15: =FTEXT(P15) -> #NAME? | T15: R-sq lower | U15: =U12/(U9+U12) -> #NAME? | W15: =FTEXT(U15) -> #NAME?
A16: Illinois | B16: 12.2 | C16: 7.3 | D16: 79.13311 | E16: 533.2 | G16: Total | H16: =H10-1 -> 49 | I16: =DEVSQ(B4:B53) -> 423.2488 | T16: R-sq upper | U16: =U13/(U9+U13) -> #NAME? | W16: =FTEXT(U16) -> #NAME?
A17: Indiana | B17: 13.1 | C17: 8 | D17: 88.000001 | E17: 333.6 | O17: SSRes | P17: =I15 -> #NAME? | R17: =FTEXT(P17) -> #NAME? | T17: α | U17: 0.05
A18: Iowa | B18: 11.5 | C18: 5.1 | D18: 94.170465 | E18: 294.7 | H18: coeff | I18: std err | J18: t stat | K18: p-value | L18: lower | M18: upper | O18: SSReg | P18: =I14 -> #NAME? | R18: =FTEXT(P18) -> #NAME? | T18: 1-β | U18: =REG_POWER(U14,U9,U8,2,U17) -> #NAME? | W18: =FTEXT(U18) -> #NAME?
A19: Kansas | B19: 11.3 | C19: 7.1 | D19: 88.703717 | E19: 452.7 | G19: Intercept | H19: {=RegCoeff(C4:E53,B4:B53)} -> #NAME? | I19: #NAME? | J19: =H19/I19 -> #NAME? | K19: =TDIST(ABS(J19),$H$15,2) -> #NAME? | L19: =H19-TINV(L$12,$H$15)*I19 -> #NAME? | M19: =H19+TINV(L$12,$H$15)*I19 -> #NAME? | O19: f-square | P19: =P18/P17 -> #NAME? | R19: =FTEXT(P19) -> #NAME? | T19: 1-β lower | U19: =REG_POWER(U15,U9,U8,2,U17) -> #NAME? | W19: =FTEXT(U19) -> #NAME?
A20: Kentucky | B20: 17.3 | C20: 7.5 | D20: 89.904327 | E20: 295 | G20: {=TRANSPOSE(C3:E3)} -> Infant Mort | H20: #NAME? | I20: #NAME? | J20: =H20/I20 -> #NAME? | K20: =TDIST(ABS(J20),$H$15,2) -> #NAME? | L20: =H20-TINV(L$12,$H$15)*I20 -> #NAME? | M20: =H20+TINV(L$12,$H$15)*I20 -> #NAME? | T20: 1-β upper | U20: =REG_POWER(U16,U9,U8,2,U17) -> #NAME? | W20: =FTEXT(U20) -> #NAME?
A21: Louisiana | B21: 17.3 | C21: 9.9 | D21: 64.839544 | E21: 729.5 | G21: White | H21: #NAME? | I21: #NAME? | J21: =H21/I21 -> #NAME? | K21: =TDIST(ABS(J21),$H$15,2) -> #NAME? | L21: =H21-TINV(L$12,$H$15)*I21 -> #NAME? | M21: =H21+TINV(L$12,$H$15)*I21 -> #NAME?
A22: Maine | B22: 12.3 | C22: 6.3 | D22: 96.389853 | E22: 118 | G22: Crime | H22: #NAME? | I22: #NAME? | J22: =H22/I22 -> #NAME? | K22: =TDIST(ABS(J22),$H$15,2) -> #NAME? | L22: =H22-TINV(L$12,$H$15)*I22 -> #NAME? | M22: =H22+TINV(L$12,$H$15)*I22 -> #NAME?
A23: Maryland | B23: 8.1 | C23: 8 | D23: 63.398021 | E23: 641.9
A24: Massachusetts | B24: 10 | C24: 4.8 | D24: 86.20367 | E24: 431.5
A25: Michigan | B25: 14.4 | C25: 7.4 | D25: 81.183409 | E25: 536
A26: Minnesota | B26: 9.6 | C26: 5.2 | D26: 89.045557 | E26: 288.7
A27: Mississippi | B27: 21.2 | C27: 10.6 | D27: 60.598179 | E27: 291.3
A28: Missouri | B28: 13.4 | C28: 7.4 | D28: 85.028888 | E28: 504.9
A29: Montana | B29: 14.8 | C29: 5.8 | D29: 90.467729 | E29: 287.5
A30: Nebraska | B30: 10.8 | C30: 5.6 | D30: 91.372477 | E30: 302.4
A31: Nevada | B31: 11.3 | C31: 6.4 | D31: 80.891227 | E31: 750.6
A32: New Hampshire | B32: 7.6 | C32: 6.1 | D32: 95.487187 | E32: 137.3
A33: New Jersey | B33: 8.7 | C33: 5.5 | D33: 76.032117 | E33: 329.3
A34: New Mexico | B34: 17.1 | C34: 5.8 | D34: 83.996521 | E34: 664.2
... A53: Wyoming | B53: 9.4 | C53: 7 | D53: 93.867287 | E53: 239.3
A55: Poverty - % below poverty level
A56: Infant Mort - infant mortality per 1,000 births, death prior to 1 yr, excludes fetal death, residents only
A57: White - % of the population that is white
A58: Crime - violent crime (murder, forcible rape, robbery, and aggravated assault) per 100,000 people

Sheet Mult Reg Pow 2
A1: Multiple Regression Power and Sample Size
A3: n | B3: 100 | D3: =FTEXT(B3) -> #NAME? | G3: α | H3: 0.05
A4: k | B4: 10 | D4: =FTEXT(B4) -> #NAME? | G4: k | H4: 8
A5: dfRes | B5: =B3-B4-1 -> 89 | D5: =FTEXT(B5) -> #NAME? | G5: R-square | H5: 0.2
A6: dfReg | B6: =B4 -> 10 | D6: =FTEXT(B6) -> #NAME? | G6: 1-β | H6: 0.9
A8: R-square | B8: 0.15 | G8: n | H8: =REG_SIZE(H5,H4,H6,2,H3) -> #NAME? | J8: =FTEXT(H8) -> #NAME?
A9: f-square | B9: =B8/(1-B8) -> 0.17647059 | D9: =FTEXT(B9) -> #NAME? | G9: f-square | H9: =H5/(1-H5) -> 0.25 | J9: =FTEXT(H9) -> #NAME?
A10: λ | B10: =B9*B3 -> 17.647059 | D10: =FTEXT(B10) -> #NAME? | G10: λ | H10: =H9*H8 -> #NAME? | J10: =FTEXT(H10) -> #NAME?
G11: dfRes | H11: =H8-H4-1 -> #NAME? | J11: =FTEXT(H11) -> #NAME?
A12: α | B12: 0.05 | G12: dfReg | H12: =H4 -> 8 | J12: =FTEXT(H12) -> #NAME?
A13: F-crit | B13: =FINV(B12,B6,B5) -> 1.9387913 | D13: =FTEXT(B13) -> #NAME? | G13: F-crit | H13: =FINV(H3,H12,H11) -> #NAME? | J13: =FTEXT(H13) -> #NAME?
A14: β | B14: =NF_DIST(B13,B6,B5,B10,TRUE) -> #NAME? | D14: =FTEXT(B14) -> #NAME? | G14: actual 1-β | H14: =1-NF_DIST(H13,H12,H11,H10,TRUE) -> #NAME? | J14: =FTEXT(H14) -> #NAME?
A15: 1-β | B15: =1-B14 -> #NAME? | D15: =FTEXT(B15) -> #NAME?
A18: 1-β | B18: =REG_POWER(B8,B3,B4,2,B12) -> #NAME? | D18: =FTEXT(B18) -> #NAME?

Sheet Poly Reg
A1: Polynomial Regression
I2: Month | J2: MonSq | K2: Use | M2: Quadratic Regression Model
B3: Hours per Month | I3: 1 | J3: =I3^2 -> 1 | K3: 7
A4: Person | B4: 1 | C4: 2 | D4: 3 | E4: 4 | F4: 5 | G4: 6 | I4: 2 | J4: =I4^2 -> 4 | K4: 11 | M4: SUMMARY OUTPUT
A5: 1 | B5: 7 | C5: 11 | D5: 23 | E5: 59 | F5: 120 | G5: 180 | I5: 3 | J5: =I5^2 -> 9 | K5: 23
A6: 2 | B6: 3 | C6: 8 | D6: 20 | E6: 48 | F6: 88 | G6: 140 | I6: 4 | J6: =I6^2 -> 16 | K6: 59 | M6: Regression Statistics
A7: 3 | B7: 4 | C7: 11 | D7: 21 | E7: 58 | F7: 128 | G7: 195 | I7: 5 | J7: =I7^2 -> 25 | K7: 120 | M7: Multiple R | N7: 0.97741198
A8: 4 | B8: 5 | C8: 9 | D8: 16 | E8: 45 | F8: 111 | G8: 156 | I8: 6 | J8: =I8^2 -> 36 | K8: 180 | M8: R Square | N8: 0.95533417
A9: 5 | B9: 2 | C9: 5 | D9: 12 | E9: 38 | F9: 78 | G9: 145 | I9: 1 | J9: =I9^2 -> 1 | K9: 3 | M9: Adjusted R Square | N9: 0.95202559
I10: 2 | J10: =I10^2 -> 4 | K10: 8 | M10: Standard Error | N10: 13.217449
I11: 3 | J11: =I11^2 -> 9 | K11: 20 | M11: Observations | N11: 30
I12: 4 | J12: =I12^2 -> 16 | K12: 48
I13: 5 | J13: =I13^2 -> 25 | K13: 88 | M13: ANOVA
I14: 6 | J14: =I14^2 -> 36 | K14: 140 | N14: df | O14: SS | P14: MS | Q14: F | R14: Significance F
I15: 1 | J15: =I15^2 -> 1 | K15: 4 | M15: Regression | N15: 2 | O15: 100887.87 | P15: 50443.937 | Q15: 288.74449 | R15: 5.9520642e-19
I16: 2 | J16: =I16^2 -> 4 | K16: 11 | M16: Residual | N16: 27 | O16: 4716.9257 | P16: 174.70095
I17: 3 | J17: =I17^2 -> 9 | K17: 21 | M17: Total | N17: 29 | O17: 105604.8
I18: 4 | J18: =I18^2 -> 16 | K18: 58
I19: 5 | J19: =I19^2 -> 25 | K19: 128 | N19: Coefficients | O19: Standard Error | P19: t Stat | Q19: P-value | R19: Lower 95% | S19: Upper 95% | U19: Month | V19: 3
I20: 6 | J20: =I20^2 -> 36 | K20: 195 | M20: Intercept | N20: 21.92 | O20: 10.573959 | P20: 2.0730173 | Q20: 0.047839767 | R20: 0.22402819 | S20: 43.615972 | U20: Hours of Use | V20: =N20+V19*N21+V19^2*N22 -> 20.788571
I21: 1 | J21: =I21^2 -> 1 | K21: 5 | M21: Month | N21: -24.548571 | O21: 6.9177729 | P21: -3.5486235 | Q21: 0.0014411959 | R21: -38.742669 | S21: -10.354474
I22: 2 | J22: =I22^2 -> 4 | K22: 9 | M22: MonSq | N22: 8.0571429 | O22: 0.96741819 | P22: 8.3285005 | Q22: 6.145192e-09 | R22: 6.0721647 | S22: 10.042121
I23: 3 | J23: =I23^2 -> 9 | K23: 16
I24: 4 | J24: =I24^2 -> 16 | K24: 45 | M24: Linear Regression Model
I25: 5 | J25: =I25^2 -> 25 | K25: 111
I26: 6 | J26: =I26^2 -> 36 | K26: 156 | M26: SUMMARY OUTPUT
I27: 1 | J27: =I27^2 -> 1 | K27: 2
I28: 2 | J28: =I28^2 -> 4 | K28: 5 | M28: Regression Statistics
I29: 3 | J29: =I29^2 -> 9 | K29: 12 | M29: Multiple R | N29: 0.91683485
I30: 4 | J30: =I30^2 -> 16 | K30: 38 | M30: R Square | N30: 0.84058614
I31: 5 | J31: =I31^2 -> 25 | K31: 78 | M31: Adjusted R Square | N31: 0.83489279
I32: 6 | J32: =I32^2 -> 36 | K32: 145 | M32: Standard Error | N32: 24.520304
M33: Observations | N33: 30
M35: ANOVA
N36: df | O36: SS | P36: MS | Q36: F | R36: Significance F
M37: Regression | N37: 1 | O37: 88769.931 | P37: 88769.931 | Q37: 147.64345 | R37: 1.1087964e-12
M38: Residual | N38: 28 | O38: 16834.869 | P38: 601.24531
M39: Total | N39: 29 | O39: 105604.8
N41: Coefficients | O41: Standard Error | P41: t Stat | Q41: P-value | R41: Lower 95% | S41: Upper 95%
M42: Intercept | N42: -53.28 | O42: 10.208617 | P42: -5.2191205 | Q42: 1.5237399e-05 | R42: -74.191403 | S42: -32.368597
M43: Month | N43: 31.851429 | O43: 2.6213308 | P43: 12.150862 | Q43: 1.1087964e-12 | R43: 26.481876 | S43: 37.220981

Sheet Poly Reg 1
A1: SUMMARY OUTPUT
A3: Regression Statistics
A4: Multiple R | B4: 0.97741198
A5: R Square | B5: 0.95533417
A6: Adjusted R Square | B6: 0.95202559
A7: Standard Error | B7: 13.217449
A8: Observations | B8: 30
A10: ANOVA
B11: df | C11: SS | D11: MS | E11: F | F11: Significance F
A12: Regression | B12: 2 | C12: 100887.87 | D12: 50443.937 | E12: 288.74449 | F12: 5.9520642e-19
A13: Residual | B13: 27 | C13: 4716.9257 | D13: 174.70095
A14: Total | B14: 29 | C14: 105604.8
B16: Coefficients | C16: Standard Error | D16: t Stat | E16: P-value | F16: Lower 95% | G16: Upper 95%
A17: Intercept | B17: 21.92 | C17: 10.573959 | D17: 2.0730173 | E17: 0.047839767 | F17: 0.22402819 | G17: 43.615972
A18: Month | B18: -24.548571 | C18: 6.9177729 | D18: -3.5486235 | E18: 0.0014411959 | F18: -38.742669 | G18: -10.354474
A19: MonSq | B19: 8.0571429 | C19: 0.96741819 | D19: 8.3285005 | E19: 6.145192e-09 | F19: 6.0721647 | G19: 10.042121
A23: RESIDUAL OUTPUT | F23: PROBABILITY OUTPUT
